Workbook
Name feb_11: Comentarios!$A$106

Sheet Índice
A1: Banco Central del Uruguay
A2: Superintendencia de Servicios Financieros
A5: CRÉDITOS BRUTOS SECTOR NO FINANCIERO (SNF)
A8: Bancos públicos
A9: Bancos privados
A10: Cooperativas de intermediación financiera
A11: Casas financieras
A12: Total Sistema Bancario
A13: Instituciones financieras externas (IFEs)
A14: Empresas administradoras de créditos (EACs)
A15: Comentarios

Sheet Bcos. Públ.
A1: Banco Central del Uruguay | T1: Banco Central del Uruguay
A2: Superintendencia de Servicios Financieros | T2: Superintendencia de Instituciones de Intermediación Financiera
M3: Volver al Índice | AH3: Volver al Índice
B4: CRÉDITOS BRUTOS SECTOR NO FINANCIERO (SNF) (1) | T4: CRÉDITOS BRUTOS SNF (1) - ANEXO RESIDENTES POR MONEDAS
B5: BANCOS PÚBLICOS | T5: BANCOS PÚBLICOS
B6: (Crédito Total en millones de pesos) | T6: (Créditos en MN en millones de pesos y en ME en millones de dólares)
B8: TOTAL (MN + ME) en millones de pesos
B9: RESIDENTES | K9: NO RESIDENTES (4) | N9: TOTAL | Q9: Variación mensual | T9: MONEDA NACIONAL en millones de pesos | AD9: MONEDA EXTRANJERA en millones de dólares
A10: Mes | B10: SECTOR PRIVADO (2) | E10: SECTOR PÚBLICO (3) | H10: TOTAL (S.Priv. + S.Públ) | Q10: Castigados (1) | T10: SECTOR PRIVADO (2) | W10: SECTOR PÚBLICO (3) | Z10: TOTAL (S.Priv. + S.Públ) | AC10: Variac. mens. | AD10: SECTOR PRIVADO (2) | AG10: SECTOR PÚBLICO (3) | AJ10: TOTAL (S.Priv. + S.Públ) | AM10: Variac. mens.
B11: Vigentes | C11: Vencidos | D11: Total | E11: Vigentes | F11: Vencidos | G11: Total | H11: Vigentes | I11: Vencidos | J11: Total | K11: Vigentes | L11: Vencidos | M11: Total | N11: Vigentes | O11: Vencidos | P11: Total | Q11: Resid. | R11: No resid. | T11: Vigentes | U11: Vencidos | V11: Total | W11: Vigentes | X11: Vencidos | Y11: Total | Z11: Vigentes | AA11: Vencidos | AB11: Total | AC11: Castigados (1) | AD11: Vigentes | AE11: Vencidos | AF11: Total | AG11: Vigentes | AH11: Vencidos | AI11: Total | AJ11: Vigentes | AK11: Vencidos | AL11: Total | AM11: Castigados (1)
A12: 36130 | B12: 44306.432 | C12: 11703.994 | D12: 55999.609 | E12: 8502.162 | F12: 162.255 | G12: 8664.417 | H12: 52797.777 | I12: 11866.249 | J12: 64664.026 | K12: 0 | L12: 0 | M12: 0 | N12: 52797.777 | O12: 11866.249 | P12: 64664.026 | Q12: 1.6328268 | R12: 0 | T12: 25495.669 | U12: 5505.853 | V12: 31001.522 | W12: 4359.251 | X12: 0 | Y12: 4359.251 | Z12: 29854.92 | AA12: 5505.853 | AB12: 35360.773 | AC12: 1.6328268 | AD12: 1738 | AE12: 573 | AF12: 2311 | AG12: 383 | AH12: 15 | AI12: 398 | AJ12: 2121 | AK12: 588 | AL12: 2709 | AM12: 0
A13: 36161 | B13: 43825.15 | C13: 12999.45 | D13: 56824.6 | E13: 8556.6 | F13: 164.55 | G13: 8721.15 | H13: 52381.75 | I13: 13164 | J13: 65545.75 | K13: 0 | L13: 0 | M13: 0 | N13: 52381.75 | O13: 13164 | P13: 65545.75 | Q13: 0.57398156 | R13: 0 | T13: 24638.62 | U13: 6571.03 | V13: 31209.65 | W13: 4398.97 | X13: 0 | Y13: 4398.97 | Z13: 29048.56 | AA13: 6571.03 | AB13: 35608.62 | AC13: 0.57398156 | AD13: 1748 | AE13: 587 | AF13: 2335 | AG13: 379 | AH13: 15 | AI13: 394 | AJ13: 2127 | AK13: 602 | AL13: 2729 | AM13: 0
A14: 36192 | B14: 43994.925 | C14: 13324.805 | D14: 57330.715 | E14: 8568.3 | F14: 164.775 | G14: 8733.075 | H14: 52563.225 | I14: 13500.565 | J14: 66063.79 | K14: 0 | L14: 0 | M14: 0 | N14: 52563.225 | O14: 13500.565 | P14: 66063.79 | Q14: 0.69165361 | R14: 0 | T14: 24672.31 | U14: 6821.685 | V14: 31493.995 | W14: 4437.94 | X14: 0 | Y14: 4437.94 | Z14: 29110.25 | AA14: 6821.685 | AB14: 35942.92 | AC14: 0.69165361 | AD14: 1759 | AE14: 592 | AF14: 2351 | AG14: 376 | AH14: 15 | AI14: 391 | AJ14: 2135 | AK14: 607 | AL14: 2742 | AM14: 0
A15: 36220 | B15: 45156.65 | C15: 13436.045 | D15: 58592.695 | E15: 8687.385 | F15: 177.52 | G15: 8864.905 | H15: 53844.035 | I15: 13613.565 | J15: 67457.6 | K15: 0 | L15: 0 | M15: 0 | N15: 53844.035 | O15: 13613.565 | P15: 67457.6 | Q15: 2.1017909 | R15: 0 | T15: 25662.735 | U15: 6424.005 | V15: 32086.74 | W15: 4482.38 | X15: 0 | Y15: 4482.38 | Z15: 30134.02 | AA15: 6435.1 | AB15: 36569.12 | AC15: 2.1017909 | AD15: 1757 | AE15: 632 | AF15: 2389 | AG15: 379 | AH15: 15 | AI15: 395 | AJ15: 2137 | AK15: 647 | AL15: 2784 | AM15: 0
A16: 36251 | B16: 45708.586 | C16: 13104.168 | D16: 58812.754 | E16: 8736.112 | F16: 178.288 | G16: 8903.257 | H16: 54433.555 | I16: 13282.456 | J16: 67716.011 | K16: 0 | L16: 0 | M16: 0 | N16: 54433.555 | O16: 13282.456 | P16: 67716.011 | Q16: 2.243071 | R16: 0 | T16: 26152.621 | U16: 6106.364 | V16: 32258.985 | W16: 4501.772 | X16: 0 | Y16: 4512.915 | Z16: 30654.393 | AA16: 6117.507 | AB16: 36760.757 | AC16: 2.243071 | AD16: 1755 | AE16: 628 | AF16: 2383 | AG16: 379 | AH16: 15 | AI16: 395 | AJ16: 2134 | AK16: 643 | AL16: 2778 | AM16: 0
A17: 36281 | B17: 46003.23 | C17: 13252.512 | D17: 59255.742 | E17: 8775.312 | F17: 190.281 | G17: 8965.593 | H17: 54778.542 | I17: 13453.986 | J17: 68221.335 | K17: 0 | L17: 0 | M17: 0 | N17: 54778.542 | O17: 13453.986 | P17: 68221.335 | Q17: 0.86793852 | R17: 0 | T17: 26426.673 | U17: 6044.22 | V17: 32470.893 | W17: 4555.551 | X17: 0 | Y17: 4555.551 | Z17: 30982.224 | AA17: 6044.22 | AB17: 37026.444 | AC17: 0.86793852 | AD17: 1748 | AE17: 645 | AF17: 2393 | AG17: 377 | AH17: 17 | AI17: 394 | AJ17: 2126 | AK17: 662 | AL17: 2787 | AM17: 0
A18: 36312 | B18: 46882.633 | C18: 13417.78 | D18: 60311.784 | E18: 8755.67 | F18: 216.049 | G18: 8971.719 | H18: 55638.303 | I18: 13645.2 | J18: 69283.503 | K18: 0 | L18: 0 | M18: 0 | N18: 55638.303 | O18: 13645.2 | P18: 69283.503 | Q18: 1.8931953 | R18: 0 | T18: 26721.85 | U18: 5969.775 | V18: 32691.625 | W18: 4537.029 | X18: 0 | Y18: 4548.4 | Z18: 31258.879 | AA18: 5969.775 | AB18: 37228.654 | AC18: 1.8931953 | AD18: 1773 | AE18: 656 | AF18: 2429 | AG18: 371 | AH18: 19 | AI18: 390 | AJ18: 2144 | AK18: 675 | AL18: 2819 | AM18: 0
A19: 36342 | B19: 46954.5 | C19: 13811.5 | D19: 60754.5 | E19: 8786 | F19: 230 | G19: 9016 | H19: 55729 | I19: 14030 | J19: 69770.5 | K19: 0 | L19: 0 | M19: 0 | N19: 55740.5 | O19: 14030 | P19: 69770.5 | Q19: 1.2994424 | R19: 0 | T19: 26726 | U19: 6141 | V19: 32855.5 | W19: 4542.5 | X19: 0 | Y19: 4542.5 | Z19: 31257 | AA19: 6141 | AB19: 37409.5 | AC19: 1.2994424 | AD19: 1759 | AE19: 667 | AF19: 2426 | AG19: 369 | AH19: 19 | AI19: 389 | AJ19: 2128 | AK19: 686 | AL19: 2814 | AM19: 0
A20: 36373 | B20: 45341.855 | C20: 15934.39 | D20: 61276.245 | E20: 8947.055 | F20: 198.305 | G20: 9145.36 | H20: 54288.91 | I20: 16132.695 | J20: 70421.605 | K20: 0 | L20: 0 | M20: 0 | N20: 54288.91 | O20: 16132.695 | P20: 70421.605 | Q20: 2.9443771 | R20: 0 | T20: 25068.085 | U20: 7920.535 | V20: 32976.955 | W20: 4549.35 | X20: 0 | Y20: 4561.015 | Z20: 29617.435 | AA20: 7920.535 | AB20: 37537.97 | AC20: 2.9443771 | AD20: 1738 | AE20: 687 | AF20: 2426 | AG20: 377 | AH20: 17 | AI20: 393 | AJ20: 2115 | AK20: 704 | AL20: 2819 | AM20: 0
A21: 36404 | B21: 45404.04 | C21: 16440.6 | D21: 61856.3 | E21: 9024.84 | F21: 198.22 | G21: 9223.06 | H21: 54440.54 | I21: 16638.82 | J21: 71079.36 | K21: 0 | L21: 0 | M21: 0 | N21: 54440.54 | O21: 16638.82 | P21: 71079.36 | Q21: 2.6148383 | R21: 0 | T21: 25162.28 | U21: 8231.96 | V21: 33394.24 | W21: 4594.04 | X21: 0 | Y21: 4594.04 | Z21: 29756.32 | AA21: 8231.96 | AB21: 37988.28 | AC21: 2.6148383 | AD21: 1736 | AE21: 705 | AF21: 2441 | AG21: 381 | AH21: 17 | AI21: 397 | AJ21: 2117 | AK21: 721 | AL21: 2838 | AM21: 0
A22: 36434 | B22: 45493.24 | C22: 17019.47 | D22: 62501.14 | E22: 9059.31 | F22: 104.13 | G22: 9163.44 | H22: 54552.55 | I22: 17123.6 | J22: 71664.58 | K22: 0 | L22: 0 | M22: 0 | N22: 54552.55 | O22: 17123.6 | P22: 71664.58 | Q22: 2.5934455 | R22: 0 | T22: 25106.9 | U22: 8538.66 | V22: 33645.56 | W22: 4604.86 | X22: 0 | Y22: 4604.86 | Z22: 29711.76 | AA22: 8538.66 | AB22: 38250.42 | AC22: 2.5934455 | AD22: 1762 | AE22: 733 | AF22: 2495 | AG22: 386 | AH22: 9 | AI22: 394 | AJ22: 2147 | AK22: 742 | AL22: 2889 | AM22: 0
A23: 36465 | B23: 45133.492 | C23: 17438.99 | D23: 62572.482 | E23: 9273.847 | F23: 196.333 | G23: 9470.18 | H23: 54407.339 | I23: 17635.323 | J23: 72042.662 | K23: 0 | L23: 0 | M23: 0 | N23: 54407.339 | O23: 17635.323 | P23: 72042.662 | Q23: 0.63406123 | R23: 0 | T23: 25165.271 | U23: 8742.593 | V23: 33919.413 | W23: 4688.894 | X23: 11.549 | Y23: 4688.894 | Z23: 29854.165 | AA23: 8754.142 | AB23: 38608.307 | AC23: 0.63406123 | AD23: 1728 | AE23: 753 | AF23: 2481 | AG23: 397 | AH23: 16 | AI23: 414 | AJ23: 2126 | AK23: 769 | AL23: 2895 | AM23: 0
... A251: 43405 | B251: 187631.32 | C251: 9394.5431 | D251: 197025.86 | E251: 13345.872 | F251: 0.10981809 | G251: 13345.981 | H251: 200977.19 | I251: 9394.6529 | J251: 210371.84 | K251: 10.882262 | L251: 1.1936797 | M251: 12.075942 | N251: 200988.07 | O251: 9395.8466 | P251: 210383.92 | Q251: 1149.6303 | R251: 0.042724284 | T251: 127807.55 | U251: 3578.5619 | V251: 131386.11 | W251: 12267.444 | X251: 0.08984978 | Y251: 12267.534 | Z251: 140074.99 | AA251: 3578.6518 | AB251: 143653.65 | AC251: 278.11462 | AD251: 1858.9779 | AE251: 180.72717 | AF251: 2039.7051 | AG251: 33.511316 | AH251: 0.0006205 | AI251: 33.511936 | AJ251: 1892.4892 | AK251: 180.72779 | AL251: 2073.217 | AM251: 27.081684
A252: 43435 | B252: 191798.11 | C252: 9190.1422 | D252: 200988.25 | E252: 9631.1852 | F252: 0.12998941 | G252: 9631.3152 | H252: 201429.3 | I252: 9190.2722 | J252: 210619.57 | K252: 12.638478 | L252: 1.5471441 | M252: 14.185622 | N252: 201441.93 | O252: 9191.8193 | P252: 210633.75 | Q252: 596.54286 | R252: 0.11455039 | T252: 132264.48 | U252: 3479.317 | V252: 135743.8 | W252: 8536.7302 | X252: 0.10621159 | Y252: 8536.8364 | Z252: 140801.21 | AA252: 3479.4232 | AB252: 144280.63 | AC252: 361.35869 | AD252: 1838.0251 | AE252: 176.31446 | AF252: =+AE252+AD252 -> 2014.3395 | AG252: 33.789905 | AH252: 0.00073411 | AI252: =+AH252+AG252 -> 33.790639 | AJ252: 1871.815 | AK252: 176.31519 | AL252: =+AK252+AJ252 -> 2048.1302 | AM252: 7.2610117
A253: 43467 | B253: 189201.63 | C253: 7491.2371 | D253: 196692.87 | E253: 9533.3084 | F253: 0.17288911 | G253: 9533.4813 | H253: 198734.94 | I253: 7491.41 | J253: 206226.35 | K253: 59.322501 | L253: 5.1714979 | M253: 64.493999 | N253: 198794.26 | O253: 7496.5815 | P253: 206290.85 | Q253: ND | R253: ND | T253: 130774.68 | U253: 3574.4275 | V253: 134349.08 | W253: 8433.9393 | X253: 0.14533504 | Y253: 8434.0847 | Z253: 139208.62 | AA253: 3574.5729 | AB253: 142783.19 | AC253: ND | AD253: 1800.9632 | AE253: 120.76924 | AF253: 1921.7324 | AG253: 33.627225 | AH253: 0.00084847 | AI253: 33.628074 | AJ253: 1834.5904 | AK253: 120.77009 | AL253: 1955.3605 | AM253: ND
A254: 43497 | B254: 190582.56 | C254: 7785.2639 | D254: 198367.83 | E254: 8808.302 | F254: 0.14307211 | G254: 8808.4451 | H254: 199390.86 | I254: 7785.407 | J254: 207176.27 | K254: 54.671969 | L254: 8.0468612 | M254: 62.71883 | N254: 199445.54 | O254: 7793.4539 | P254: 207238.99 | Q254: ND | R254: ND | T254: 131829.51 | U254: 3599.473 | V254: 135428.98 | W254: 8130.2442 | X254: 0.11169123 | Y254: 8130.3559 | Z254: 139959.75 | AA254: 3599.5847 | AB254: 143559.34 | AC254: ND | AD254: 1799.4258 | AE254: 128.19794 | AF254: 1927.6238 | AG254: 20.766832 | AH254: 0.0009611 | AI254: 20.767793 | AJ254: 1820.1926 | AK254: 128.1989 | AL254: 1948.3915 | AM254: ND
A255: 43525 | B255: 193152.77 | C255: 8014.8712 | D255: 201167.65 | E255: 8688.8528 | F255: 0.13731052 | G255: 8688.9901 | H255: 201841.63 | I255: 8015.0085 | J255: 209856.64 | K255: 52.159494 | L255: 7.863767 | M255: 60.023261 | N255: 201893.79 | O255: 8022.8723 | P255: 209916.66 | Q255: ND | R255: ND | T255: 133225.97 | U255: 3683.9249 | V255: 136909.89 | W255: 8003.8132 | X255: 0.10125696 | Y255: 8003.9145 | Z255: 141229.78 | AA255: 3684.0261 | AB255: 144913.81 | AC255: ND | AD255: 1789.7146 | AE255: 129.34376 | AF255: 1919.0584 | AG255: 20.458713 | AH255: 0.00107674 | AI255: 20.45979 | AJ255: 1810.1734 | AK255: 129.34483 | AL255: 1939.5182 | AM255: ND
A256: 43556 | B256: 195259.9 | C256: 8882.0222 | D256: 204141.92 | E256: 9719.9377 | F256: 0.14344939 | G256: 9720.0812 | H256: 204979.83 | I256: 8882.1656 | J256: 213862 | K256: 53.524852 | L256: 8.2639198 | M256: 61.788772 | N256: 205033.36 | O256: 8890.4295 | P256: 213923.79 | Q256: ND | R256: ND | T256: 133259.55 | U256: 3778.6416 | V256: 137038.19 | W256: 9008.8359 | X256: 0 | Y256: 9008.8359 | Z256: 142268.38 | AA256: 3778.6416 | AB256: 146047.02 | AC256: ND | AD256: 1772.4007 | AE256: 145.89007 | AF256: 1918.2908 | AG256: 20.32823 | AH256: 0.0012813 | AI256: 20.329512 | AJ256: 1792.729 | AK256: 145.89135 | AL256: 1938.6203 | AM256: ND
A257: 43586 | B257: 195162.23 | C257: 8942.8183 | D257: 204105.05 | E257: 9248.1724 | F257: 0.1445607 | G257: 9248.317 | H257: 204410.4 | I257: 8942.9629 | J257: 213353.36 | K257: 52.595254 | L257: 8.5547981 | M257: 61.150052 | N257: 204463 | O257: 8951.5177 | P257: 213414.51 | Q257: ND | R257: ND | T257: 133294.42 | U257: 3652.0857 | V257: 136946.51 | W257: 8557.5879 | X257: 0.10702331 | Y257: 8557.6949 | Z257: 141852.01 | AA257: 3652.1928 | AB257: 145504.2 | AC257: ND | AD257: 1755.0156 | AE257: 150.08319 | AF257: 1905.0988 | AG257: 19.589938 | AH257: 0.00059837 | AI257: 19.590536 | AJ257: 1774.6055 | AK257: 150.08379 | AL257: 1924.6893 | AM257: ND
A258: 43617 | B258: 195025.58 | C258: 8050.9528 | D258: 203076.54 | E258: 9948.1907 | F258: 0.14427364 | G258: 9948.335 | H258: 204973.77 | I258: 8051.097 | J258: 213024.87 | K258: 55.835895 | L258: 8.3219369 | M258: 64.157832 | N258: 205029.61 | O258: 8059.419 | P258: 213089.03 | Q258: ND | R258: ND | T258: 133484.44 | U258: 3651.4788 | V258: 137135.92 | W258: 9264.2585 | X258: 0 | Y258: 9264.2585 | Z258: 142748.7 | AA258: 3651.4788 | AB258: 146400.18 | AC258: ND | AD258: 1749.2225 | AE258: 125.049 | AF258: 1874.2715 | AG258: 19.439834 | AH258: 0.00093726 | AI258: 19.440771 | AJ258: 1768.6623 | AK258: 125.04994 | AL258: 1893.7122 | AM258: ND
A259: 43647 | B259: 192628.72 | C259: 7833.6887 | D259: 200462.4 | E259: 9222.5861 | F259: 0.072774253 | G259: 9222.6588 | H259: 201851.3 | I259: 7833.7615 | J259: 209685.06 | K259: 63.323075 | L259: 7.1585022 | M259: 70.481578 | N259: 201914.62 | O259: 7840.92 | P259: 209755.54 | Q259: ND | R259: ND | T259: 133707.35 | U259: 3588.5281 | V259: 137295.88 | W259: 8563.9962 | X259: 0.067070092 | Y259: 8564.0633 | Z259: 142271.35 | AA259: 3588.5281 | AB259: 145859.88 | AC259: ND | AD259: 1715.3235 | AE259: 123.58546 | AF259: 1838.909 | AG259: 19.172921 | AH259: 0.00016606 | AI259: 19.173087 | AJ259: 1734.4965 | AK259: 123.58563 | AL259: 1858.0821 | AM259: ND
A260: 43678 | B260: 194779.76 | C260: 9602.7968 | D260: 204382.56 | E260: 9712.7088 | F260: 0.059696414 | G260: 9712.7684 | H260: 204492.47 | I260: 9602.8565 | J260: 214095.32 | K260: 47.204002 | L260: 5.9929486 | M260: 53.19695 | N260: 204539.67 | O260: 9608.8495 | P260: 214148.52 | Q260: ND | R260: ND | T260: 134145.59 | U260: 3753.9276 | V260: 137899.51 | W260: 9049.7669 | X260: 0.051561523 | Y260: 9049.8184 | Z260: 143195.35 | AA260: 3753.9792 | AB260: 146949.33 | AC260: ND | AD260: 1654.7725 | AE260: 159.622 | AF260: 1814.3945 | AG260: 18.092404 | AH260: 0.00022201 | AI260: 18.092626 | AJ260: 1672.8649 | AK260: 159.62222 | AL260: 1832.4871 | AM260: ND
A261: 43709 | B261: 194922.5 | C261: 9463.3848 | D261: 204385.89 | E261: 9761.6186 | F261: 0.077743297 | G261: 9761.6964 | H261: 204684.12 | I261: 9463.4625 | J261: 214147.58 | K261: 50.453473 | L261: 5.6970828 | M261: 56.150556 | N261: 204734.57 | O261: 9469.1596 | P261: 214203.73 | Q261: ND | R261: ND | T261: 134791.5 | U261: 3921.9241 | V261: 138713.43 | W261: 9125.9696 | X261: 0.065367624 | Y261: 9126.035 | Z261: 143917.47 | AA261: 3921.9895 | AB261: 147839.46 | AC261: ND | AD261: 1627.8459 | AE261: 150.01653 | AF261: 1777.8625 | AG261: 17.208074 | AH261: 0.00033503 | AI261: 17.208409 | AJ261: 1645.054 | AK261: 150.01687 | AL261: 1795.0709 | AM261: ND
A262: 43739 | B262: 198754.24 | C262: 8495.262 | D262: 207249.5 | E262: 11210.888 | F262: 0.032919719 | G262: 11210.921 | H262: 209965.12 | I262: 8495.2949 | J262: 218460.42 | K262: 54.029595 | L262: 5.7625807 | M262: 59.792176 | N262: 210019.15 | O262: 8501.0575 | P262: 218520.21 | Q262: ND | R262: ND | T262: 137321.77 | U262: 3925.495 | V262: 141247.27 | W262: 10565.068 | X262: 0.016132283 | Y262: 10565.084 | Z262: 147886.84 | AA262: 3925.5111 | AB262: 151812.35 | AC262: ND | AD262: 1641.8768 | AE262: 122.13403 | AF262: 1764.0109 | AG262: 17.26052 | AH262: 0.00044867 | AI262: 17.260968 | AJ262: 1659.1374 | AK262: 122.13448 | AL262: 1781.2718 | AM262: ND
A263: 43770 | B263: 200250.03 | C263: 8613.8961 | D263: 208863.92 | E263: 10060.917 | F263: 0.022498529 | G263: 10060.94 | H263: 210310.95 | I263: 8613.9185 | J263: 218924.86 | K263: 54.089274 | L263: 5.6676498 | M263: 59.756924 | N263: 210365.03 | O263: 8619.5862 | P263: 218984.62 | Q263: ND | R263: ND | T263: 138510.81 | U263: 3902.7551 | V263: 142413.56 | W263: 9448.1309 | X263: 0.0076818984 | Y263: 9448.1386 | Z263: 147958.94 | AA263: 3902.7627 | AB263: 151861.7 | AC263: ND | AD263: 1631.5862 | AE263: 124.50161 | AF263: 1756.0878 | AG263: 16.194148 | AH263: 0.00039156 | AI263: 16.194539 | AJ263: 1647.7803 | AK263: 124.502 | AL263: 1772.2823 | AM263: ND
A264: 43800 | B264: 204187.11 | C264: 8492.0565 | D264: 212679.17 | E264: 10122.723 | F264: 0.010717672 | G264: 10122.734 | H264: 214309.83 | I264: 8492.0672 | J264: 222801.9 | K264: 52.544677 | L264: 11.648739 | M264: 64.193416 | N264: 214362.38 | O264: 8503.716 | P264: 222866.09 | Q264: ND | R264: ND | T264: 143632.86 | U264: 3720.5109 | V264: 147353.37 | W264: 9514.269 | X264: 0.010717672 | Y264: 9514.2797 | Z264: 153147.13 | AA264: 3720.5216 | AB264: 156867.65 | AC264: ND | AD264: 1621.8729 | AE264: 127.80013 | AF264: 1749.673 | AG264: 16.296714 | AH264: 0 | AI264: 16.296714 | AJ264: 1638.1696 | AK264: 127.80013 | AL264: 1765.9697 | AM264: ND
... A324: 45627 | B324: 331305.27 | C324: 7890.157 | D324: 339195.43 | E324: 22032.701 | F324: 0.0027563283 | G324: 22032.704 | H324: 353337.97 | I324: 7890.1598 | J324: 361228.13 | K324: 84.412889 | L324: 3.712122 | M324: 88.125011 | N324: 353422.38 | O324: 7893.8719 | P324: 361316.26 | Q324: ND | R324: ND | T324: 212159.5 | U324: 5439.9399 | V324: 217599.44 | W324: 17095.037 | X324: 0 | Y324: 17095.037 | Z324: 229254.54 | AA324: 5439.9399 | AB324: 234694.48 | AC324: ND | AD324: 2703.8028 | AE324: 55.603348 | AF324: 2759.4061 | AG324: 112.05155 | AH324: 6.255e-05 | AI324: 112.05162 | AJ324: 2815.8543 | AK324: 55.603411 | AL324: 2871.4577 | AM324: ND
A325: 45658 | B325: =+'[1]Bcos. Públ.'!B325*[2]TC!$B316 -> 329482.3 | C325: =+'[1]Bcos. Públ.'!C325*[2]TC!$B316 -> 7593.5694 | D325: =+'[1]Bcos. Públ.'!D325*[2]TC!$B316 -> 337075.87 | E325: =+'[1]Bcos. Públ.'!E325*[2]TC!$B316 -> 22681.986 | F325: =+'[1]Bcos. Públ.'!F325*[2]TC!$B316 -> 0.0098326784 | G325: =+'[1]Bcos. Públ.'!G325*[2]TC!$B316 -> 22681.996 | H325: =+'[1]Bcos. Públ.'!H325*[2]TC!$B316 -> 352164.28 | I325: =+'[1]Bcos. Públ.'!I325*[2]TC!$B316 -> 7593.5792 | ... P325: =+'[1]Bcos. Públ.'!P325*[2]TC!$B316 -> 359835.59 | Q325: ND | R325: ND | T325: =+'[1]Bcos. Públ.'!T325*[2]TC!$B316 -> 213846.29 | U325: =+'[1]Bcos. Públ.'!U325*[2]TC!$B316 -> 5212.6751 | V325: =+'[1]Bcos. Públ.'!V325*[2]TC!$B316 -> 219058.96 | W325: =+'[1]Bcos. Públ.'!W325*[2]TC!$B316 -> 21197.089 | X325: =+'[1]Bcos. Públ.'!X325*[2]TC!$B316 -> 0.0062263856 | Y325: =+'[1]Bcos. Públ.'!Y325*[2]TC!$B316 -> 21197.095 | Z325: =+'[1]Bcos. Públ.'!Z325*[2]TC!$B316 -> 235043.37 | AA325: =+'[1]Bcos. Públ.'!AA325*[2]TC!$B316 -> 5212.6813 | AB325: =+'[1]Bcos. Públ.'!AB325*[2]TC!$B316 -> 240256.06 | AC325: ND | AD325: =+'[1]Bcos. Públ.'!AD325 -> 2681.6013 | AE325: =+'[1]Bcos. Públ.'!AE325 -> 55.212984 | AF325: =+'[1]Bcos. Públ.'!AF325 -> 2736.8143 | AG325: =+'[1]Bcos. Públ.'!AG325 -> 34.434803 | AH325: =+'[1]Bcos. Públ.'!AH325 -> 8.363e-05 | AI325: =+'[1]Bcos. Públ.'!AI325 -> 34.434887 | AJ325: =+'[1]Bcos. Públ.'!AJ325 -> 2716.0361 | AK325: =+'[1]Bcos. Públ.'!AK325 -> 55.213068 | AL325: =+'[1]Bcos. Públ.'!AL325 -> 2771.2492 | AM325: ND
A326: 45689 | B326: =+'[1]Bcos. Públ.'!B326*[2]TC!$B317 -> 331475.31 | C326: =+'[1]Bcos. Públ.'!C326*[2]TC!$B317 -> 7827.7992 | D326: =+'[1]Bcos. Públ.'!D326*[2]TC!$B317 -> 339303.11 | E326: =+'[1]Bcos. Públ.'!E326*[2]TC!$B317 -> 22192.774 | F326: =+'[1]Bcos. Públ.'!F326*[2]TC!$B317 -> 0 | G326: =+'[1]Bcos. Públ.'!G326*[2]TC!$B317 -> 22192.774 | H326: =+'[1]Bcos. Públ.'!H326*[2]TC!$B317 -> 353668.08 | I326: =+'[1]Bcos. Públ.'!I326*[2]TC!$B317 -> 7827.7992 | ... P326: =+'[1]Bcos. Públ.'!P326*[2]TC!$B317 -> 361574.66 | Q326: ND | R326: ND | T326: =+'[1]Bcos. Públ.'!T326*[2]TC!$B317 -> 215922.09 | U326: =+'[1]Bcos. Públ.'!U326*[2]TC!$B317 -> 5413.14 | V326: =+'[1]Bcos. Públ.'!V326*[2]TC!$B317 -> 221335.23 | W326: =+'[1]Bcos. Públ.'!W326*[2]TC!$B317 -> 20723.066 | X326: =+'[1]Bcos. Públ.'!X326*[2]TC!$B317 -> 0 | Y326: =+'[1]Bcos. Públ.'!Y326*[2]TC!$B317 -> 20723.066 | Z326: =+'[1]Bcos. Públ.'!Z326*[2]TC!$B317 -> 236645.16 | AA326: =+'[1]Bcos. Públ.'!AA326*[2]TC!$B317 -> 5413.14 | AB326: =+'[1]Bcos. Públ.'!AB326*[2]TC!$B317 -> 242058.3 | AC326: ND | AD326: =+'[1]Bcos. Públ.'!AD326 -> 2713.4723 | AE326: =+'[1]Bcos. Públ.'!AE326 -> 56.702105 | AF326: =+'[1]Bcos. Públ.'!AF326 -> 2770.1744 | AG326: =+'[1]Bcos. Públ.'!AG326 -> 34.51233 | AH326: =+'[1]Bcos. Públ.'!AH326 -> 0 | AI326: =+'[1]Bcos. Públ.'!AI326 -> 34.51233 | AJ326: =+'[1]Bcos. Públ.'!AJ326 -> 2747.9846 | AK326: =+'[1]Bcos. Públ.'!AK326 -> 56.702105 | AL326: =+'[1]Bcos. Públ.'!AL326 -> 2804.6867 | AM326: ND
A327: 45717 | B327: =+'[1]Bcos. Públ.'!B327*[2]TC!$B318 -> 334965.14 | C327: =+'[1]Bcos. Públ.'!C327*[2]TC!$B318 -> 7533.0612 | D327: =+'[1]Bcos. Públ.'!D327*[2]TC!$B318 -> 342498.2 | E327: =+'[1]Bcos. Públ.'!E327*[2]TC!$B318 -> 22377.421 | F327: =+'[1]Bcos. Públ.'!F327*[2]TC!$B318 -> 0.013159632 | G327: =+'[1]Bcos. Públ.'!G327*[2]TC!$B318 -> 22377.434 | H327: =+'[1]Bcos. Públ.'!H327*[2]TC!$B318 -> 357342.56 | I327: =+'[1]Bcos. Públ.'!I327*[2]TC!$B318 -> 7533.0744 | ... P327: =+'[1]Bcos. Públ.'!P327*[2]TC!$B318 -> 364950.66 | Q327: ND | R327: ND | T327: =+'[1]Bcos. Públ.'!T327*[2]TC!$B318 -> 217630.88 | U327: =+'[1]Bcos. Públ.'!U327*[2]TC!$B318 -> 5251.3194 | V327: =+'[1]Bcos. Públ.'!V327*[2]TC!$B318 -> 222882.2 | W327: =+'[1]Bcos. Públ.'!W327*[2]TC!$B318 -> 20912.912 | X327: =+'[1]Bcos. Públ.'!X327*[2]TC!$B318 -> 0 | Y327: =+'[1]Bcos. Públ.'!Y327*[2]TC!$B318 -> 20912.912 | Z327: =+'[1]Bcos. Públ.'!Z327*[2]TC!$B318 -> 238543.8 | AA327: =+'[1]Bcos. Públ.'!AA327*[2]TC!$B318 -> 5251.3194 | AB327: =+'[1]Bcos. Públ.'!AB327*[2]TC!$B318 -> 243795.12 | AC327: ND | AD327: =+'[1]Bcos. Públ.'!AD327 -> 2785.2507 | AE327: =+'[1]Bcos. Públ.'!AE327 -> 54.163407 | AF327: =+'[1]Bcos. Públ.'!AF327 -> 2839.4141 | AG327: =+'[1]Bcos. Públ.'!AG327 -> 34.764133 | AH327: =+'[1]Bcos. Públ.'!AH327 -> 0.00031238 | AI327: =+'[1]Bcos. Públ.'!AI327 -> 34.764445 | AJ327: =+'[1]Bcos. Públ.'!AJ327 -> 2820.0149 | AK327: =+'[1]Bcos. Públ.'!AK327 -> 54.163719 | AL327: =+'[1]Bcos. Públ.'!AL327 -> 2874.1786 | AM327: ND
A328: 45748 | B328: 337106.78 | C328: 7710.011 | D328: 344816.79 | E328: 22567.385 | F328: 0.0065486584 | G328: 22567.392 | H328: 359674.16 | I328: 7710.0176 | J328: 367384.18 | K328: 70.11785 | L328: 4.3646332 | M328: 74.482483 | N328: 359744.28 | O328: 7714.3822 | P328: 367458.66 | Q328: ND | R328: ND | T328: 219262.02 | U328: 5244.733 | V328: 224506.75 | W328: 21114.424 | X328: 0.0042200694 | Y328: 21114.429 | Z328: 240376.44 | AA328: 5244.7372 | AB328: 245621.18 | AC328: ND | AD328: 2809.2388 | AE328: 58.768458 | AF328: 2868.0073 | AG328: 34.63636 | AH328: 5.551e-05 | AI328: 34.636415 | AJ328: 2843.8752 | AK328: 58.768513 | AL328: 2902.6437 | AM328: ND
A329: 45778 | B329: 337837.08 | C329: 7673.5615 | D329: 345510.64 | E329: 21788.955 | F329: 0 | G329: 21788.955 | H329: 359626.03 | I329: 7673.5615 | J329: 367299.59 | K329: 72.505008 | L329: 3.4458337 | M329: 75.950842 | N329: 359698.54 | O329: 7677.0073 | P329: 367375.54 | Q329: ND | R329: ND | T329: 219828.33 | U329: 5274.1804 | V329: 225102.51 | W329: 20360.311 | X329: 0 | Y329: 20360.311 | Z329: 240188.64 | AA329: 5274.1804 | AB329: 245462.82 | AC329: ND | AD329: 2831.4398 | AE329: 57.569488 | AF329: 2889.0093 | AG329: 34.278142 | AH329: 0 | AI329: 34.278142 | AJ329: 2865.718 | AK329: 57.569488 | AL329: 2923.2875 | AM329: ND
A330: 45809 | B330: 332098.22 | C330: 7622.4858 | D330: 339720.71 | E330: 21858.151 | F330: 0 | G330: 21858.151 | H330: 353956.37 | I330: 7622.4858 | J330: 361578.86 | K330: 73.986185 | L330: 3.2687059 | M330: 77.254891 | N330: 354030.36 | O330: 7625.7546 | P330: 361656.11 | Q330: ND | R330: ND | T330: 220276.61 | U330: 5277.7931 | V330: 225554.4 | W330: 20503.47 | X330: 0 | Y330: 20503.47 | Z330: 240780.08 | AA330: 5277.7931 | AB330: 246057.87 | AC330: ND | AD330: 2827.4909 | AE330: 59.287264 | AF330: 2886.7781 | AG330: 34.2541 | AH330: 0 | AI330: 34.2541 | AJ330: 2861.745 | AK330: 59.287264 | AL330: 2921.0322 | AM330: ND
A331: 45839 | B331: 335339.45 | C331: 7237.1583 | D331: 342576.61 | E331: 21852.525 | F331: 0 | G331: 21852.525 | H331: 357191.98 | I331: 7237.1583 | J331: 364429.14 | K331: 71.964846 | L331: 3.0477946 | M331: 75.01264 | N331: 357263.94 | O331: 7240.2061 | P331: 364504.15 | Q331: ND | R331: ND | T331: 221413.94 | U331: 5267.5884 | V331: 226681.53 | W331: 20473.466 | X331: 0 | Y331: 20473.466 | Z331: 241887.4 | AA331: 5267.5884 | AB331: 247154.99 | AC331: ND | AD331: 2834.2501 | AE331: 48.999153 | AF331: 2883.2493 | AG331: 34.308347 | AH331: 0 | AI331: 34.308347 | AJ331: 2868.5584 | AK331: 48.999153 | AL331: 2917.5576 | AM331: ND
A332: 45870 | B332: 333598.82 | C332: 7417.3997 | D332: 341016.22 | E332: 21614.838 | F332: 15.878149 | G332: 21630.716 | H332: 355213.66 | I332: 7433.2778 | J332: 362646.94 | K332: 74.534016 | L332: 3.0312994 | M332: 77.565315 | N332: 355288.19 | O332: 7436.3091 | P332: 362724.5 | Q332: ND | R332: ND | T332: 221884.63 | U332: 5407.4181 | V332: 227292.05 | W332: 20240.536 | X332: 15.878149 | Y332: 20256.414 | Z332: 242125.16 | AA332: 5423.2963 | AB332: 247548.46 | AC332: ND | AD332: 2793.204 | AE332: 50.255821 | AF332: 2843.4599 | AG332: 34.361829 | AH332: 0 | AI332: 34.361829 | AJ332: 2827.5659 | AK332: 50.255821 | AL332: 2877.8217 | AM332: ND
A333: 45901 | B333: 336401.91 | C333: 7589.9239 | D333: 343991.83 | E333: 21242.871 | F333: 0 | G333: 21242.871 | H333: 357644.78 | I333: 7589.9239 | J333: 365234.7 | K333: 72.955922 | L333: 3.574373 | M333: 76.530295 | N333: 357717.73 | O333: 7593.4983 | P333: 365311.23 | Q333: ND | R333: ND | T333: 226563.58 | U333: 5430.2439 | V333: 231993.82 | W333: 19861.298 | X333: 0 | Y333: 19861.298 | Z333: 246424.87 | AA333: 5430.2439 | AB333: 251855.12 | AC333: ND | AD333: 2756.6403 | AE333: 54.202034 | AF333: 2810.8423 | AG333: 34.673669 | AH333: 0 | AI333: 34.673669 | AJ333: 2791.3139 | AK333: 54.202034 | AL333: 2845.516 | AM333: ND
A335: (1) La variación del saldo contable de los créditos brutos se encuentra influida por la transferencia de créditos a cuentas de orden (créditos castigados) de acuerdo a lo establecido por la normativa. Por este motivo se presenta la variación mensual de los créditos castigados, elemento que, para evaluar la evolución del crédito desde una perspectiva económica, debería sumarse al saldo de los créditos brutos.
A336: (2) Corresponde a los grupos N° 14010 (Préstamos), 14020 (Arrendamientos Financieros), 14060 (Ingresos Percibidos No Devengados), 14070 (Grupos de Ahorro Previo), 14080 (Deudores por Productos Financieros Devengados), 16010 (Créditos Vencidos - Sector No Público) y 16080 (Deudores por Productos Financieros) del Plan de Cuentas para EIF, excepto las cuentas de deudores por créditos documentarios diferidos y domésticos diferidos (185000 y 189001 respectivamente), las cuentas de operaciones a liquidar (369080), sector público (245000 y 393000), sector financiero (407000), y a partir de marzo de 2005 los préstamos domésticos diferidos (185000 y 189001 respectivamente), las cuentas de operaciones a liquidar (369080), sector público (245000 y 393000), sector financiero (407000), y a partir de marzo de 2005 los préstamos garantizados con prenda de depósitos (509000).
A337: Nuevo Plan de cuenta: 1.4.2.1 Créditos vigentes + 1.4.2.2 Créditos vigentes (deudores por intereses)+ 1.4.2.4 Colocacion vencida + 1.4.2.5 Colocación vencida (deudores por intereses) + 1.4.2.7 Créditos en gestión + 1.4.2.8 Créditos en gestión (deudores por intereses) +1.4.2.10 Créditos morosos + 1.4.2.11 Créditos morosos (deudores por intereses)
A338: (3) Incluye a las cuentas de los grupos N° 14050 y 16040 (Créditos Vigentes y Vencidos - Sector Público Nacional y No Nacional), 14080 y 16080 (Créditos Vigentes y Vencidos - Deudores por Productos Financieros Devengados) que corresponden al sector público nacional, excepto las cuentas de operaciones a liquidar (227000, 229000 y 381000) y deudores por créditos domésticos diferidos (221000). Incluye Estado, organismos de seguridad social, gobiernos departamentales y otros integrantes del sector público.
A339: Nuevo Plan de cuenta: 1.4.3.1 Créditos vigentes + 1.4.3.2 Créditos vigentes (deudores por intereses)+ 1.4.3.4 Colocación vencida + 1.4.3.5 Colocación vencida (deudores por intereses)+ 1.4.3.7 Créditos en gestión + 1.4.3.8 Créditos en gestión (deudores por intereses) +1.4.3.10 Créditos morosos + 1.4.3.11 Créditos morosos (deudores por intereses).
A340: (4) Incluye sector privado no residente y sector público no nacional.
A342: Notas:
A343: Los meses que aparecen subrayados incluyen comentarios explicativos y vínculo a la hoja con detalle de todos los comentarios.
A344: Diferencias en las columnas de Total se deben a redondeo de las cifras.

Sheet Bcos. Priv.
A1: Banco Central del Uruguay | T1: Banco Central del Uruguay
A2: Superintendencia de Servicios Financieros | T2: Superintendencia de Instituciones de Intermediación Financiera
M3: Volver al Índice | AH3: Volver al Índice
B4: CRÉDITOS BRUTOS SECTOR NO FINANCIERO (SNF) (1) | T4: CRÉDITOS BRUTOS SNF (1) - ANEXO RESIDENTES POR MONEDAS
B5: BANCOS PRIVADOS (2) | T5: BANCOS PRIVADOS (2)
B6: (Crédito Total en millones de pesos) | T6: (Créditos en MN en millones de pesos y en ME en millones de dólares)
B8: TOTAL (MN + ME) en millones de pesos
B9: RESIDENTES | K9: NO RESIDENTES (5) | N9: TOTAL | Q9: Variación mensual | T9: MONEDA NACIONAL en millones de pesos | AD9: MONEDA EXTRANJERA en millones de dólares
A10: Mes | B10: SECTOR PRIVADO (3) | E10: SECTOR PÚBLICO (4) | H10: TOTAL (S.Priv. + S.Públ) | Q10: Castigados (1) | T10: SECTOR PRIVADO (3) | W10: SECTOR PÚBLICO (4) | Z10: TOTAL (S.Priv. + S.Públ) | AC10: Variac. mens. | AD10: SECTOR PRIVADO (3) | AG10: SECTOR PÚBLICO (4) | AJ10: TOTAL (S.Priv. + S.Públ) | AM10: Variac. mens.
B11: Vigentes | C11: Vencidos | D11: Total | E11: Vigentes | F11: Vencidos | G11: Total | H11: Vigentes | I11: Vencidos | J11: Total | K11: Vigentes | L11: Vencidos | M11: Total | N11: Vigentes | O11: Vencidos | P11: Total | Q11: Resid. | R11: No resid. | T11: Vigentes | U11: Vencidos | V11: Total | W11: Vigentes | X11: Vencidos | Y11: Total | Z11: Vigentes | AA11: Vencidos | AB11: Total | AC11: Castigados (1) | AD11: Vigentes | AE11: Vencidos | AF11: Total | AG11: Vigentes | AH11: Vencidos | AI11: Total | AJ11: Vigentes | AK11: Vencidos | AL11: Total | AM11: Castigados (1)
A12: 36161 | B12: 41389.81 | C12: 4223.45 | D12: 45613.26 | E12: 537.53 | F12: 0 | G12: 537.53 | H12: 41927.34 | I12: 4223.45 | J12: 46150.79 | K12: 9258.68 | L12: 197.46 | M12: 9456.14 | N12: 51186.02 | O12: 4409.94 | P12: 55606.93 | Q12: 68.74794 | R12: 79.222487 | T12: 7251.17 | U12: 998.27 | V12: 8260.41 | W12: 43.88 | X12: 0 | Y12: 43.88 | Z12: 7295.05 | AA12: 998.27 | AB12: 8304.29 | AC12: 1.1683086 | AD12: 3112 | AE12: 294 | AF12: 3405 | AG12: 45 | AH12: 0 | AI12: 45 | AJ12: 3157 | AK12: 294 | AL12: 3451 | AM12: 6.1604039 | AN12: =+AE12/AF12 -> 0.086343612 | AO12: =+U12/V12 -> 0.12084993
A13: 36192 | B13: 40875.185 | C13: 4745.52 | D13: 45620.705 | E13: 450.385 | F13: 0 | G13: 450.385 | H13: 41325.57 | I13: 4745.52 | J13: 46071.09 | K13: 9370.205 | L13: 164.775 | M13: 9534.98 | N13: 50695.775 | O13: 4921.28 | P13: 55617.055 | Q13: 177.05241 | R13: 20.485804 | T13: 6953.505 | U13: 1208.35 | V13: 8172.84 | W13: 32.955 | X13: 0 | Y13: 32.955 | Z13: 6986.46 | AA13: 1219.335 | AB13: 8205.795 | AC13: 3.5704229 | AD13: 3088 | AE13: 322 | AF13: 3409 | AG13: 38 | AH13: 0 | AI13: 38 | AJ13: 3126 | AK13: 322 | AL13: 3447 | AM13: 15.792625 | AN13: =+AE13/AF13 -> 0.094455852 | AO13: =+U13/V13 -> 0.14784946
A14: 36220 | B14: 41106.975 | C14: 3261.93 | D14: 44357.81 | E14: 432.705 | F14: 0 | G14: 432.705 | H14: 41539.68 | I14: 3261.93 | J14: 44801.61 | K14: 9852.36 | L14: 99.855 | M14: 9952.215 | N14: 51392.04 | O14: 3361.785 | P14: 54753.825 | Q14: 1316.3836 | R14: -2.7443804 | T14: 6812.33 | U14: 920.885 | V14: 7733.215 | W14: 33.285 | X14: 0 | Y14: 33.285 | Z14: 6856.71 | AA14: 920.885 | AB14: 7766.5 | AC14: 188.58675 | AD14: 3090 | AE14: 211 | AF14: 3301 | AG14: 36 | AH14: 0 | AI14: 36 | AJ14: 3126 | AK14: 211 | AL14: 3337 | AM14: 101.64911 | AN14: =+AE14/AF14 -> 0.063920024 | AO14: =+U14/V14 -> 0.11908178
A15: 36251 | B15: 40827.952 | C15: 2997.467 | D15: 43825.419 | E15: 445.72 | F15: 0 | G15: 445.72 | H15: 41273.672 | I15: 2997.467 | J15: 44271.139 | K15: 9995.271 | L15: 89.144 | M15: 10084.415 | N15: 51268.943 | O15: 3086.611 | P15: 54366.697 | Q15: 504.03413 | R15: 0.33674713 | T15: 6663.514 | U15: 735.438 | V15: 7398.952 | W15: 44.572 | X15: 0 | Y15: 44.572 | Z15: 6708.086 | AA15: 735.438 | AB15: 7432.381 | AC15: 202.23106 | AD15: 3066 | AE15: 203 | AF15: 3269 | AG15: 37 | AH15: 0 | AI15: 37 | AJ15: 3102 | AK15: 203 | AL15: 3306 | AM15: 27.084544 | AN15: =+AE15/AF15 -> 0.062098501 | AO15: =+U15/V15 -> 0.09939759
A16: 36281 | B16: 41179.047 | C16: 3167.619 | D16: 44335.473 | E16: 514.878 | F16: 0 | G16: 526.071 | H16: 41693.925 | I16: 3167.619 | J16: 44861.544 | K16: 10174.437 | L16: 100.737 | M16: 10275.174 | N16: 51868.362 | O16: 3268.356 | P16: 55136.718 | Q16: 43.680147 | R16: 16.727124 | T16: 6771.765 | U16: 749.931 | V16: 7532.889 | W16: 55.965 | X16: 0 | Y16: 55.965 | Z16: 6827.73 | AA16: 749.931 | AB16: 7577.661 | AC16: 5.056745 | AD16: 3073 | AE16: 215 | AF16: 3289 | AG16: 42 | AH16: 0 | AI16: 42 | AJ16: 3115 | AK16: 215 | AL16: 3331 | AM16: 3.4506747 | AN16: =+AE16/AF16 -> 0.065369413 | AO16: =+U16/V16 -> 0.099554235
A17: 36312 | B17: 42106.813 | C17: 3127.025 | D17: 45233.838 | E17: 477.582 | F17: 0 | G17: 477.582 | H17: 42584.395 | I17: 3127.025 | J17: 45711.42 | K17: 9995.109 | L17: 79.597 | M17: 10074.706 | N17: 52579.504 | O17: 3206.622 | P17: 55786.126 | Q17: 26.529893 | R17: 3.2587873 | T17: 6845.342 | U17: 750.486 | V17: 7595.828 | W17: 68.226 | X17: 0 | Y17: 68.226 | Z17: 6913.568 | AA17: 750.486 | AB17: 7664.054 | AC17: 1.7881484 | AD17: 3101 | AE17: 209 | AF17: 3310 | AG17: 36 | AH17: 0 | AI17: 36 | AJ17: 3137 | AK17: 209 | AL17: 3346 | AM17: 2.1758636 | AN17: =+AE17/AF17 -> 0.063141994 | AO17: =+U17/V17 -> 0.098802395
A18: 36342 | B18: 42423.5 | C18: 3231.5 | D18: 45666.5 | E18: 460 | F18: 0 | G18: 460 | H18: 42883.5 | I18: 3243 | J18: 46126.5 | K18: 9970.5 | L18: 103.5 | M18: 10074 | N18: 52854 | O18: 3335 | P18: 56200.5 | Q18: 9.0791451 | R18: -2.3147588 | T18: 7003.5 | U18: 793.5 | V18: 7797 | W18: 69 | X18: 0 | Y18: 69 | Z18: 7072.5 | AA18: 793.5 | AB18: 7877.5 | AC18: 10.073454 | AD18: 3080 | AE18: 212 | AF18: 3292 | AG18: 34 | AH18: 0 | AI18: 34 | AJ18: 3114 | AK18: 212 | AL18: 3326 | AM18: -0.086461607 | AN18: =+AE18/AF18 -> 0.064398542 | AO18: =+U18/V18 -> 0.10176991
A19: 36373 | B19: 43102.175 | C19: 3441.175 | D19: 46543.35 | E19: 571.585 | F19: 0 | G19: 571.585 | H19: 43673.76 | I19: 3441.175 | J19: 47126.6 | K19: 10090.225 | L19: 104.985 | M19: 10195.21 | N19: 53763.985 | O19: 3557.825 | P19: 57321.81 | Q19: 28.656016 | R19: -6.4389659 | T19: 7337.285 | U19: 793.22 | V19: 8130.505 | W19: 69.99 | X19: 0 | Y19: 69.99 | Z19: 7407.275 | AA19: 793.22 | AB19: 8200.495 | AC19: 10.225124 | AD19: 3066 | AE19: 227 | AF19: 3293 | AG19: 43 | AH19: 0 | AI19: 43 | AJ19: 3109 | AK19: 227 | AL19: 3336 | AM19: 1.5800165 | AN19: =+AE19/AF19 -> 0.068934103 | AO19: =+U19/V19 -> 0.097560976
A20: 36404 | B20: 43258.6 | C20: 3591.28 | D20: 46849.88 | E20: 617.98 | F20: 0 | G20: 629.64 | H20: 43888.24 | I20: 3602.94 | J20: 47479.52 | K20: 9969.3 | L20: 116.6 | M20: 10085.9 | N20: 53845.88 | O20: 3707.88 | P20: 57565.42 | Q20: 35.330026 | R20: 0.51881683 | T20: 7474.06 | U20: 851.18 | V20: 8325.24 | W20: 93.28 | X20: 0 | Y20: 104.94 | Z20: 7567.34 | AA20: 851.18 | AB20: 8430.18 | AC20: 9.9414587 | AD20: 3069 | AE20: 235 | AF20: 3304 | AG20: 45 | AH20: 0 | AI20: 45 | AJ20: 3114 | AK20: 235 | AL20: 3350 | AM20: 2.1774071 | AN20: =+AE20/AF20 -> 0.071125908 | AO20: =+U20/V20 -> 0.1022409
A21: 36434 | B21: 43260.23 | C21: 3737.11 | D21: 47008.91 | E21: 647.92 | F21: 0 | G21: 659.49 | H21: 43919.72 | I21: 3748.68 | J21: 47668.4 | K21: 9811.36 | L21: 115.7 | M21: 9927.06 | N21: 53731.08 | O21: 3864.38 | P21: 57595.46 | Q21: 35.678785 | R21: 0.36730447 | T21: 7462.65 | U21: 890.89 | V21: 8353.54 | W21: 80.99 | X21: 0 | Y21: 92.56 | Z21: 7543.64 | AA21: 902.46 | AB21: 8446.1 | AC21: 11.419696 | AD21: 3095 | AE21: 246 | AF21: 3341 | AG21: 49 | AH21: 0 | AI21: 49 | AJ21: 3144 | AK21: 246 | AL21: 3390 | AM21: 2.0967233 | AN21: =+AE21/AF21 -> 0.07363065 | AO21: =+U21/V21 -> 0.1066482
A22: 36465 | B22: 43216.358 | C22: 3880.464 | D22: 47085.273 | E22: 692.94 | F22: 0 | G22: 692.94 | H22: 43909.298 | I22: 3880.464 | J22: 47789.762 | K22: 14863.563 | L22: 334.921 | M22: 15210.033 | N22: 58772.861 | O22: 4215.385 | P22: 62999.795 | Q22: 30.14972 | R22: 39.245595 | T22: 7345.164 | U22: 923.92 | V22: 8280.633 | W22: 80.843 | X22: 0 | Y22: 92.392 | Z22: 7437.556 | AA22: 935.469 | AB22: 8361.476 | AC22: 7.9688927 | AD22: 3105 | AE22: 255 | AF22: 3361 | AG22: 53 | AH22: 0 | AI22: 53 | AJ22: 3158 | AK22: 255 | AL22: 3413 | AM22: 1.9205843 | AN22: =+AE22/AF22 -> 0.075870277 | AO22: =+U22/V22 -> 0.11157601
A23: 36495 | B23: 44334.455 | C23: 3867.795 | D23: 48202.25 | E23: 662.055 | F23: 0 | G23: 673.67 | H23: 45008.125 | I23: 3867.795 | J23: 48875.92 | K23: 15447.95 | L23: 336.835 | M23: 15784.785 | N23: 60456.075 | O23: 4204.63 | P23: 64660.705 | Q23: 6.7811529 | R23: 0.02820553 | T23: 7468.445 | U23: 940.815 | V23: 8409.26 | W23: 81.305 | X23: 0 | Y23: 81.305 | Z23: 7549.75 | AA23: 940.815 | AB23: 8490.565 | AC23: -41.852945 | AD23: 3174 | AE23: 252 | AF23: 3426 | AG23: 51 | AH23: 0 | AI23: 51 | AJ23: 3225 | AK23: 252 | AL23: 3477 | AM23: 4.1871802 | AN23: =+AE23/AF23 -> 0.073555166 | AO23: =+U23/V23 -> 0.11187845
... A52: 37377 | B52: 52560.04 | C52: 10571.66 | D52: 63131.7 | E52: 2303.23 | F52: 115.99 | G52: 2419.22 | H52: 54863.27 | I52: 10671.08 | J52: 65550.92 | K52: 14382.76 | L52: 2170.67 | M52: 16553.43 | N52: 69246.03 | O52: 12841.75 | P52: 82087.78 | Q52: 121.49717 | R52: 0.21577984 | T52: 6263.46 | U52: 1093.62 | V52: 7357.08 | W52: 314.83 | X52: 16.57 | Y52: 331.4 | Z52: 6578.29 | AA52: 1110.19 | AB52: 7688.48 | AC52: 23.014741 | AD52: 2794 | AE52: 571 | AF52: 3365 | AG52: 120 | AH52: 6 | AI52: 126 | AJ52: 2914 | AK52: 577 | AL52: 3491 | AM52: 5.9434173 | AN52: =+AE52/AF52 -> 0.16968796 | AO52: =+U52/V52 -> 0.14864865
A53: 37408 | B53: 54575 | C53: 12617 | D53: 67192 | E53: 2534.5 | F53: 92.5 | G53: 2627 | H53: 57109.5 | I53: 12728 | J53: 69819 | K53: 14559.5 | L53: 3034 | M53: 17593.5 | N53: 71650.5 | O53: 15762 | P53: 87412.5 | Q53: 238.75751 | R53: 6.206763 | T53: 5957 | U53: 1147 | V53: 7104 | W53: 296 | X53: 18.5 | Y53: 296 | Z53: 6234.5 | AA53: 1165.5 | AB53: 7400 | AC53: 19.224503 | AD53: 2628 | AE53: 621 | AF53: =+AD53+AE53 -> 3249 | AG53: 121 | AH53: 4 | AI53: 125 | AJ53: 2749 | AK53: 625 | AL53: 3374 | AM53: 11.866649 | AN53: =+AE53/AF53 -> 0.19113573 | AO53: =+U53/V53 -> 0.16145833
A54: 37438 | B54: 67225 | C54: 18700 | D54: 85925 | E54: 3175 | F54: 125 | G54: 3300 | H54: 70375 | I54: 18825 | J54: 89200 | K54: 18975 | L54: 5175 | M54: 24125 | N54: 89350 | O54: 24000 | P54: 113350 | Q54: 170.03853 | R54: 6.9581322 | T54: 5650 | U54: 1250 | V54: 6900 | W54: 300 | X54: 25 | Y54: 325 | Z54: 5950 | AA54: 1250 | AB54: 7200 | AC54: 41.321322 | AD54: 2463 | AE54: 698 | AF54: =+AD54+AE54 -> 3161 | AG54: 115 | AH54: 4 | AI54: 119 | AJ54: 2577 | AK54: 703 | AL54: 3280 | AM54: 5.1486883 | AN54: =+AE54/AF54 -> 0.2208162 | AO54: =+U54/V54 -> 0.18115942
A55: 37469 | B55: 69235.2 | C55: 25776 | D55: 95040 | E55: 3542.4 | F55: 172.8 | G55: 3715.2 | H55: 72777.6 | I55: 25948.8 | J55: 98726.4 | K55: 11980.8 | L55: 7891.2 | M55: 19843.2 | N55: 84758.4 | O55: 33840 | P55: 118598.4 | Q55: 239.69773 | R55: 3.5423197 | T55: 5356.8 | U55: 1411.2 | V55: 6768 | W55: 288 | X55: 28.8 | Y55: 288 | Z55: 5616 | AA55: 1440 | AB55: 7056 | AC55: 13.440429 | AD55: =+AD54+($AD$54-$AD$71)/17 -> 2540.2941 | AE55: 846 | AF55: =+AD55+AE55 -> 3386.2941 | AG55: 113 | AH55: 6 | AI55: 118 | AJ55: 2331 | AK55: 852 | AL55: 3183 | AM55: 7.8561564 | AN55: =+AE55/AF55 -> 0.24983063 | AO55: =+U55/V55 -> 0.20851064
A56: 37500 | B56: 57267 | C56: 28134 | D56: 85428 | E56: 3348 | F56: 135 | G56: 3483 | H56: 60615 | I56: 28296 | J56: 88911 | K56: 9234 | L56: 7182 | M56: 16443 | N56: 69876 | O56: 35478 | P56: 105354 | Q56: 446.09183 | R56: 7.9424823 | T56: 4806 | U56: 1674 | V56: 6480 | W56: 270 | X56: 27 | Y56: 297 | Z56: 5076 | AA56: 1701 | AB56: 6777 | AC56: 42.684801 | AD56: =+AD55+($AD$54-$AD$71)/17 -> 2617.5882 | AE56: 980 | AF56: =+AD56+AE56 -> 3597.5882 | AG56: 114 | AH56: 5 | AI56: 118 | AJ56: 2057 | AK56: 985 | AL56: 3042 | AM56: 14.941001 | AN56: =+AE56/AF56 -> 0.27240472 | AO56: =+U56/V56 -> 0.25833333
A57: 37530 | B57: 51584.35 | C57: 30809.95 | D57: 82394.3 | E57: 3300.1 | F57: 135.25 | G57: 3435.35 | H57: 54884.45 | I57: 30945.2 | J57: 85829.65 | K57: 7492.85 | L57: 7601.05 | M57: 15093.9 | N57: 62404.35 | O57: 38546.25 | P57: 100923.55 | Q57: 200.86621 | R57: 1.9425339 | T57: 4409.15 | U57: 1785.3 | V57: 6194.45 | W57: 270.5 | X57: 0 | Y57: 297.55 | Z57: 4706.7 | AA57: 1812.35 | AB57: 6492 | AC57: 31.656531 | AD57: =+AD56+($AD$54-$AD$71)/17 -> 2694.8824 | AE57: 1073 | AF57: =+AD57+AE57 -> 3767.8824 | AG57: 112 | AH57: 5 | AI57: 117 | AJ57: 1856 | AK57: 1078 | AL57: 2933 | AM57: 6.2554408 | AN57: =+AE57/AF57 -> 0.28477535 | AO57: =+U57/V57 -> 0.28820961
A58: 37561 | B58: 45948 | C58: 33202.9 | D58: 79123.55 | E58: 3008.5 | F58: 300.85 | G58: 3309.35 | H58: 48929.15 | I58: 33503.75 | J58: 82432.9 | K58: 6864.85 | L58: 7712.7 | M58: 14577.55 | N58: 55794 | O58: 41216.45 | P58: 97010.45 | Q58: 479.91615 | R58: 141.84899 | T58: 4129.85 | U58: 1723.05 | V58: 5880.25 | W58: 273.5 | X58: 27.35 | Y58: 300.85 | Z58: 4403.35 | AA58: 1750.4 | AB58: 6153.75 | AC58: 114.42163 | AD58: =+AD57+($AD$54-$AD$71)/17 -> 2772.1765 | AE58: 1150 | AF58: =+AD58+AE58 -> 3922.1765 | AG58: 100 | AH58: 10 | AI58: 110 | AJ58: 1628 | AK58: 1160 | AL58: 2788 | AM58: 13.363602 | AN58: =+AE58/AF58 -> 0.29320455 | AO58: =+U58/V58 -> 0.29302326
A59: 37591 | B59: 41507.2 | C59: 35387.2 | D59: 76921.6 | E59: 3155.2 | F59: 353.6 | G59: 3508.8 | H59: 44689.6 | I59: 35740.8 | J59: 80430.4 | K59: 7017.6 | L59: 6827.2 | M59: 13844.8 | N59: 51707.2 | O59: 42568 | P59: 94275.2 | Q59: 644.94915 | R59: 29.15058 | T59: 3971.2 | U59: 1768 | V59: 5739.2 | W59: 244.8 | X59: 54.4 | Y59: 299.2 | Z59: 4188.8 | AA59: 1822.4 | AB59: 6011.2 | AC59: 60.093615 | AD59: =+AD58+($AD$54-$AD$71)/17 -> 2849.4706 | AE59: 1236 | AF59: =+AD59+AE59 -> 4085.4706 | AG59: 107 | AH59: 11 | AI59: 118 | AJ59: 1488 | AK59: 1247 | AL59: 2735 | AM59: 21.502042 | AN59: =+AE59/AF59 -> 0.30253553 | AO59: =+U59/V59 -> 0.30805687
A60: 37622 | B60: 41220.9 | C60: 37280.25 | D60: 78501.15 | E60: 3175.2 | F60: 340.2 | G60: 3543.75 | H60: 44424.45 | I60: 37620.45 | J60: 82044.9 | K60: 7541.1 | L60: 7030.8 | M60: 14571.9 | N60: 51965.55 | O60: 44679.6 | P60: 96616.8 | Q60: -3594.5346 | R60: -191.55393 | T60: 4054.05 | U60: 1786.05 | V60: 5840.1 | W60: 255.15 | X60: 56.7 | Y60: 311.85 | Z60: 4309.2 | AA60: 1842.75 | AB60: 6151.95 | AC60: -375.102 | AD60: =+AD59+($AD$54-$AD$71)/17 -> 2926.7647 | AE60: 1251 | AF60: =+AD60+AE60 -> 4177.7647 | AG60: 103 | AH60: 11 | AI60: 114 | AJ60: 1415 | AK60: 1262 | AL60: 2677 | AM60: -113.56023 | AN60: =+AE60/AF60 -> 0.29944243 | AO60: =+U60/V60 -> 0.30582524
A61: 37653 | B61: 38988 | C61: 38703 | D61: 77691 | E61: 2764.5 | F61: 741 | G61: 3505.5 | H61: 41752.5 | I61: 39444 | J61: 81196.5 | K61: 6298.5 | L61: 8350.5 | M61: 14649 | N61: 48051 | O61: 47794.5 | P61: 95845.5 | Q61: 205.4622 | R61: 65.203149 | T61: 4018.5 | U61: 1966.5 | V61: 5985 | W61: 256.5 | X61: 57 | Y61: 313.5 | Z61: 4275 | AA61: 2023.5 | AB61: 6298.5 | AC61: 17.910877 | AD61: =+AD60+($AD$54-$AD$71)/17 -> 3004.0588 | AE61: 1288 | AF61: =+AD61+AE61 -> 4292.0588 | AG61: 89 | AH61: 24 | AI61: 113 | AJ61: 1315 | AK61: 1313 | AL61: 2628 | AM61: 6.580748 | AN61: =+AE61/AF61 -> 0.30008908 | AO61: =+U61/V61 -> 0.32857143
A62: 37681 | B62: 36356.2 | C62: 29911.5 | D62: 66267.7 | E62: 2803.3 | F62: 289 | G62: 3092.3 | H62: 39159.5 | I62: 30200.5 | J62: 69360 | K62: 6213.5 | L62: 7138.3 | M62: 13351.8 | N62: 45373 | O62: 37338.8 | P62: 82682.9 | Q62: -1762.7959 | R62: 130.11395 | T62: 4074.9 | U62: 1502.8 | V62: 5606.6 | W62: 231.2 | X62: 57.8 | Y62: 289 | Z62: 4335 | AA62: 1560.6 | AB62: 5895.6 | AC62: -260.45762 | AD62: =+AD61+($AD$54-$AD$71)/17 -> 3081.3529 | AE62: 982 | AF62: =+AD62+AE62 -> 4063.3529 | AG62: 88 | AH62: 8 | AI62: 97 | AJ62: 1205 | AK62: 991 | AL62: 2196 | AM62: -51.984023 | AN62: =+AE62/AF62 -> 0.24167234 | AO62: =+U62/V62 -> 0.26804124
A63: 37712 | B63: 36661.8 | C63: 29899.8 | D63: 66532.2 | E63: 2851.8 | F63: 294 | G63: 3145.8 | H63: 39513.6 | I63: 30193.8 | J63: 69707.4 | K63: 6379.8 | L63: 7085.4 | M63: 13465.2 | N63: 45893.4 | O63: 37279.2 | P63: 83172.6 | Q63: 679.98024 | R63: 0.1948196 | T63: 4321.8 | U63: 1528.8 | V63: 5821.2 | W63: 264.6 | X63: 58.8 | Y63: 294 | Z63: 4557 | AA63: 1558.2 | AB63: 6144.6 | AC63: 14.502803 | AD63: =+AD62+($AD$54-$AD$71)/17 -> 3158.6471 | AE63: 965 | AF63: =+AD63+AE63 -> 4123.6471 | AG63: 89 | AH63: 8 | AI63: 97 | AJ63: 1189 | AK63: 973 | AL63: 2162 | AM63: 22.635287 | AN63: =+AE63/AF63 -> 0.23401615 | AO63: =+U63/V63 -> 0.26262626
A64: 37742 | B64: 32807.3 | C64: 20052 | D64: 52859.3 | E64: 2590.05 | F64: 250.65 | G64: 2840.7 | H64: 35397.35 | I64: 20302.65 | J64: 55700 | K64: 4066.1 | L64: 3926.85 | M64: 7992.95 | N64: 39463.45 | O64: 24229.5 | P64: 63692.95 | Q64: 234.94915 | R64: 0.13791161 | T64: 3871.15 | U64: 1086.15 | V64: 4929.45 | W64: 222.8 | X64: 55.7 | Y64: 278.5 | Z64: 4093.95 | AA64: 1141.85 | AB64: 5235.8 | AC64: 27.14091 | AD64: =+AD63+($AD$54-$AD$71)/17 -> 3235.9412 | AE64: 681 | AF64: =+AD64+AE64 -> 3916.9412 | AG64: 85 | AH64: 7 | AI64: 92 | AJ64: 1124 | AK64: 688 | AL64: 1812 | AM64: 7.4616963 | AN64: =+AE64/AF64 -> 0.17386015 | AO64: =+U64/V64 -> 0.22033898
A65: 37773 | B65: 26217 | C65: 23193 | D65: 49383 | E65: 2430 | F65: 324 | G65: 2781 | H65: 28647 | I65: 23517 | J65: 52164 | K65: 3510 | L65: 2997 | M65: 6507 | N65: 32157 | O65: 26541 | P65: 58671 | Q65: 675.93734 | R65: 153.50225 | T65: 3618 | U65: 1134 | V65: 4725 | W65: 108 | X65: 135 | Y65: 243 | Z65: 3726 | AA65: 1269 | AB65: 4968 | AC65: 22.425262 | AD65: =+AD64+($AD$54-$AD$71)/17 -> 3313.2353 | AE65: 817 | AF65: =+AD65+AE65 -> 4130.2353 | AG65: 86 | AH65: 7 | AI65: 94 | AJ65: 923 | AK65: 824 | AL65: 1748 | AM65: 24.204151 | AN65: =+AE65/AF65 -> 0.19780955 | AO65: =+U65/V65 -> 0.24
A66: 37803 | B66: 27208.2 | C66: 21783 | D66: 48991.2 | E66: 2356.4 | F66: 356.2 | G66: 2712.6 | H66: 29564.6 | I66: 22139.2 | J66: 51703.8 | K66: 3370.2 | L66: 2849.6 | M66: 6219.8 | N66: 32934.8 | O66: 24988.8 | P66: 57923.6 | Q66: 248.24268 | R66: 31.106187 | T66: 3479.8 | U66: 1013.8 | V66: 4493.6 | W66: 109.6 | X66: 164.4 | Y66: 274 | Z66: 3589.4 | AA66: 1178.2 | AB66: 4767.6 | AC66: 37.511289 | AD66: =+AD65+($AD$54-$AD$71)/17 -> 3390.5294 | AE66: 758 | AF66: =+AD66+AE66 -> 4148.5294 | AG66: 82 | AH66: 7 | AI66: 89 | AJ66: 948 | AK66: 765 | AL66: 1713 | AM66: 7.6909268 | AN66: =+AE66/AF66 -> 0.18271535 | AO66: =+U66/V66 -> 0.22560976
... A70: 37926 | B70: 32252.4 | C70: 17802.4 | D70: 50054.8 | E70: 2312 | F70: 260.1 | G70: 2572.1 | H70: 34564.4 | I70: 18062.5 | J70: 52626.9 | K70: 4306.1 | L70: 1791.8 | M70: 6097.9 | N70: 38870.5 | O70: 19883.2 | P70: 58753.7 | Q70: 169.99685 | R70: 58.029061 | T70: 3121.2 | U70: 1069.3 | V70: 4190.5 | W70: 57.8 | X70: 115.6 | Y70: 173.4 | Z70: 3207.9 | AA70: 1184.9 | AB70: 4363.9 | AC70: 24.617721 | AD70: =+AD69+($AD$54-$AD$71)/17 -> 3699.7059 | AE70: 579 | AF70: =+AD70+AE70 -> 4278.7059 | AG70: 77 | AH70: 6 | AI70: 83 | AJ70: 1086 | AK70: 584 | AL70: 1670 | AM70: 5.0304197 | AN70: =+AE70/AF70 -> 0.13532129 | AO70: =+U70/V70 -> 0.25517241
A71: 37956 | B71: 36976.6 | C71: 7471.5 | D71: 44477.4 | E71: 2285.4 | F71: 58.6 | G71: 2344 | H71: 39262 | I71: 7559.4 | J71: 46792.1 | K71: 4541.5 | L71: 439.5 | M71: 4981 | N71: 43803.5 | O71: 7998.9 | P71: 51802.4 | Q71: 2111.6552 | R71: 234.26205 | T71: 3310.9 | U71: 380.9 | V71: 3721.1 | W71: 146.5 | X71: 0 | Y71: 175.8 | Z71: 3486.7 | AA71: 410.2 | AB71: 3896.9 | AC71: -150.01452 | AD71: 1149 | AE71: 242 | AF71: 1391 | AG71: 72 | AH71: 2 | AI71: 74 | AJ71: 1221 | AK71: 244 | AL71: 1465 | AM71: 77.190094 | AN71: =+AE71/AF71 -> 0.17397556 | AO71: =+U71/V71 -> 0.1023622
A72: 37987 | B72: 37308.6 | C72: 7203 | D72: 44511.6 | E72: 2205 | F72: 58.8 | G72: 2263.8 | H72: 39513.6 | I72: 7261.8 | J72: 46775.4 | K72: 3969 | L72: 441 | M72: 4380.6 | N72: 43482.6 | O72: 7702.8 | P72: 51156 | Q72: -29.619165 | R72: 266.85865 | T72: 3381 | U72: 382.2 | V72: 3763.2 | W72: 117.6 | X72: 0 | Y72: 147 | Z72: 3498.6 | AA72: 411.6 | AB72: 3910.2 | AC72: 0.29885772 | AD72: 1154 | AE72: 231 | AF72: 1386 | AG72: 71 | AH72: 2 | AI72: 72 | AJ72: 1225 | AK72: 233 | AL72: 1458 | AM72: -1.0176198 | AN72: =+AE72/AF72 -> 0.16666667 | AO72: =+U72/V72 -> 0.1015625
A73: 38018 | B73: 37401.5 | C73: 7009.1 | D73: 44410.6 | E73: 2120.4 | F73: 88.35 | G73: 2238.2 | H73: 39521.9 | I73: 7126.9 | J73: 46648.8 | K73: 3651.8 | L73: 471.2 | M73: 4123 | N73: 43173.7 | O73: 7598.1 | P73: 50742.35 | Q73: 284.14049 | R73: 70.588727 | T73: 3327.85 | U73: 382.85 | V73: 3710.7 | W73: 58.9 | X73: 58.9 | Y73: 117.8 | Z73: 3386.75 | AA73: 441.75 | AB73: 3828.5 | AC73: 14.432348 | AD73: 1157 | AE73: 226 | AF73: 1382 | AG73: 70 | AH73: 2 | AI73: 71 | AJ73: 1227 | AK73: 227 | AL73: 1454 | AM73: 9.1581712 | AN73: =+AE73/AF73 -> 0.16353111 | AO73: =+U73/V73 -> 0.1031746
A74: 38047 | B74: 37003.2 | C74: 6760.2 | D74: 43763.4 | E74: 2164.45 | F74: 88.95 | G74: 2253.4 | H74: 39167.65 | I74: 6878.8 | J74: 46046.45 | K74: 3617.3 | L74: 296.5 | M74: 3913.8 | N74: 42784.95 | O74: 7175.3 | P74: 49960.25 | Q74: 392.46659 | R74: 175.37001 | T74: 3261.5 | U74: 355.8 | V74: 3617.3 | W74: 88.95 | X74: 59.3 | Y74: 118.6 | Z74: 3320.8 | AA74: 415.1 | AB74: 3735.9 | AC74: 17.653777 | AD74: 1139 | AE74: 216 | AF74: 1354 | AG74: 70 | AH74: 2 | AI74: 72 | AJ74: 1209 | AK74: 218 | AL74: 1426 | AM74: 12.641242 | AN74: =+AE74/AF74 -> 0.15952733 | AO74: =+U74/V74 -> 0.098360656
A75: 38078 | B75: 37570.5 | C75: 6326.1 | D75: 43896.6 | E75: 2168.1 | F75: 89.1 | G75: 2257.2 | H75: 39738.6 | I75: 6415.2 | J75: 46183.5 | K75: 3653.1 | L75: 267.3 | M75: 3920.4 | N75: 43391.7 | O75: 6712.2 | P75: 50103.9 | Q75: 181.53141 | R75: 9.7185595 | T75: 3207.6 | U75: 297 | V75: 3504.6 | W75: 89.1 | X75: 59.4 | Y75: 118.8 | Z75: 3267 | AA75: 356.4 | AB75: 3623.4 | AC75: 21.955696 | AD75: 1158 | AE75: 203 | AF75: 1360 | AG75: 70 | AH75: 2 | AI75: 72 | AJ75: 1228 | AK75: 204 | AL75: 1432 | AM75: 5.3729197 | AN75: =+AE75/AF75 -> 0.14926471 | AO75: =+U75/V75 -> 0.084745763
A76: 38108 | B76: 38189.2 | C76: 6552.65 | D76: 44741.85 | E76: 2075.5 | F76: 88.95 | G76: 2164.45 | H76: 40264.7 | I76: 6671.25 | J76: 46906.3 | K76: 3646.95 | L76: 266.85 | M76: 3913.8 | N76: 43911.65 | O76: 6938.1 | P76: 50820.1 | Q76: 218.19208 | R76: -15.534231 | T76: 3498.7 | U76: 296.5 | V76: 3765.55 | W76: 88.95 | X76: 59.3 | Y76: 118.6 | Z76: 3558 | AA76: 326.15 | AB76: 3913.8 | AC76: 13.660999 | AD76: 1170 | AE76: 212 | AF76: 1382 | AG76: 67 | AH76: 2 | AI76: 69 | AJ76: 1237 | AK76: 213 | AL76: 1451 | AM76: 6.8981815 | AN76: =+AE76/AF76 -> 0.15340087 | AO76: =+U76/V76 -> 0.078740157
A77: 38139 | B77: 38693.25 | C77: 6078.25 | D77: 44771.5 | E77: 2105.15 | F77: 88.95 | G77: 2194.1 | H77: 40798.4 | I77: 6196.85 | J77: 46995.25 | K77: 3854.5 | L77: 266.85 | M77: 4121.35 | N77: 44652.9 | O77: 6463.7 | P77: 51086.95 | Q77: 381.48505 | R77: 13.162269 | T77: 3172.55 | U77: 266.85 | V77: 3439.4 | W77: 148.25 | X77: 59.3 | Y77: 207.55 | Z77: 3320.8 | AA77: 326.15 | AB77: 3646.95 | AC77: 22.369061 | AD77: 1198 | AE77: 196 | AF77: 1394 | AG77: 66 | AH77: 2 | AI77: 68 | AJ77: 1264 | AK77: 198 | AL77: 1462 | AM77: 12.111838 | AN77: =+AE77/AF77 -> 0.14060258 | AO77: =+U77/V77 -> 0.077586207
A78: 38169 | B78: 38514 | C78: 5321.4 | D78: 43835.4 | E78: 2263.8 | F78: 88.2 | G78: 2352 | H78: 40777.8 | I78: 5409.6 | J78: 46216.8 | K78: 3910.2 | L78: 264.6 | M78: 4174.8 | N78: 44717.4 | O78: 5674.2 | P78: 50391.6 | Q78: 373.58399 | R78: 4.5017217 | T78: 3116.4 | U78: 294 | V78: 3410.4 | W78: 117.6 | X78: 58.8 | Y78: 176.4 | Z78: 3234 | AA78: 352.8 | AB78: 3586.8 | AC78: 8.1190541 | AD78: 1204 | AE78: 171 | AF78: 1375 | AG78: 73 | AH78: 2 | AI78: 75 | AJ78: 1277 | AK78: 172 | AL78: 1450 | AM78: 12.43078 | AN78: =+AE78/AF78 -> 0.12436364 | AO78: =+U78/V78 -> 0.086206897
A79: 38200 | B79: 37892.5 | C79: 4973.75 | D79: 42866.25 | E79: 2185 | F79: 86.25 | G79: 2300 | H79: 40077.5 | I79: 5060 | J79: 45166.25 | K79: 3795 | L79: 201.25 | M79: 3996.25 | N79: 43872.5 | O79: 5261.25 | P79: 49162.5 | Q79: 310.8301 | R79: 21.964095 | T79: 3220 | U79: 316.25 | V79: 3536.25 | W79: 143.75 | X79: 57.5 | Y79: 172.5 | Z79: 3335 | AA79: 373.75 | AB79: 3708.75 | AC79: 11.603213 | AD79: 1206 | AE79: 162 | AF79: 1368 | AG79: 72 | AH79: 2 | AI79: 74 | AJ79: 1278 | AK79: 163 | AL79: 1441 | AM79: 10.407892 | AN79: =+AE79/AF79 -> 0.11842105 | AO79: =+U79/V79 -> 0.089430894
A80: 38231 | B80: 37360.1 | C80: 4239.25 | D80: 41572 | E80: 2160.65 | F80: 82.05 | G80: 2242.7 | H80: 39493.4 | I80: 4321.3 | J80: 43814.7 | K80: 3746.95 | L80: 191.45 | M80: 3938.4 | N80: 43240.35 | O80: 4512.75 | P80: 47753.1 | Q80: 322.74547 | R80: -12.464423 | T80: 3500.8 | U80: 273.5 | V80: 3774.3 | W80: 164.1 | X80: 54.7 | Y80: 218.8 | Z80: 3637.55 | AA80: 328.2 | AB80: 3965.75 | AC80: 16.593106 | AD80: 1238 | AE80: 144 | AF80: 1382 | AG80: 73 | AH80: 2 | AI80: 75 | AJ80: 1311 | AK80: 146 | AL80: 1457 | AM80: 11.193871 | AN80: =+AE80/AF80 -> 0.10419682 | AO80: =+U80/V80 -> 0.072463768
A81: 38261 | B81: 36933.7 | C81: 3873.6 | D81: 40780.4 | E81: 2501.7 | F81: 80.7 | G81: 2609.3 | H81: 39435.4 | I81: 3954.3 | J81: 43389.7 | K81: 3927.4 | L81: 188.3 | M81: 4115.7 | N81: 43362.8 | O81: 4142.6 | P81: 47505.4 | Q81: 279.28571 | R81: -35.243739 | T81: 3523.9 | U81: 269 | V81: 3792.9 | W81: 188.3 | X81: 53.8 | Y81: 242.1 | Z81: 3739.1 | AA81: 295.9 | AB81: 4035 | AC81: 32.898861 | AD81: 1241 | AE81: 134 | AF81: 1375 | AG81: 86 | AH81: 2 | AI81: 87 | AJ81: 1327 | AK81: 136 | AL81: 1463 | AM81: 9.1593625 | AN81: =+AE81/AF81 -> 0.097454545 | AO81: =+U81/V81 -> 0.070921986
A82: 38292 | B82: 36525.6 | C82: 3898.2 | D82: 40423.8 | E82: 2536.5 | F82: 80.1 | G82: 2643.3 | H82: 39062.1 | I82: 4005 | J82: 43067.1 | K82: 3711.3 | L82: 160.2 | M82: 3871.5 | N82: 42773.4 | O82: 4165.2 | P82: 46938.6 | Q82: 220.77611 | R82: 2.9490662 | T82: 3844.8 | U82: 240.3 | V82: 4085.1 | W82: 240.3 | X82: 53.4 | Y82: 267 | Z82: 4085.1 | AA82: 293.7 | AB82: 4378.8 | AC82: 19.321779 | AD82: 1223 | AE82: 137 | AF82: 1361 | AG82: 87 | AH82: 2 | AI82: 88 | AJ82: 1310 | AK82: 139 | AL82: 1449 | AM82: 7.545106 | AN82: =+AE82/AF82 -> 0.10066128 | AO82: =+U82/V82 -> 0.058823529
... A222: 42552 | B222: 240325.35 | C222: 4585.3092 | D222: 244910.66 | E222: 9718.6503 | F222: 0 | G222: 9718.6503 | H222: 250044 | I222: 4585.3092 | J222: 254629.31 | K222: 4707.2773 | L222: 30.066783 | M222: 4737.3441 | N222: 254751.28 | O222: 4615.376 | P222: 259366.66 | Q222: 57.767517 | R222: -0.78519257 | T222: 73791.787 | U222: 2185.4146 | V222: 75977.201 | W222: 7308.1965 | X222: 0 | Y222: 7308.1965 | Z222: 81099.983 | AA222: 2185.4146 | AB222: 83285.398 | AC222: 45.12221 | AD222: 5597.3906 | AE222: 80.663305 | AF222: 5678.0539 | AG222: 81.018209 | AH222: 0 | AI222: 81.018209 | AJ222: 5678.4088 | AK222: 80.663305 | AL222: 5759.0721 | AM222: 0.42502378 | AN222: =+AE222/AF222 -> 0.014206154 | AO222: =+U222/V222 -> 0.028764084
A223: 42583 | B223: 233029.55 | C223: 4310.2873 | D223: 237339.83 | E223: 9938.3392 | F223: 0 | G223: 9938.3392 | H223: 242967.89 | I223: 4310.2873 | J223: 247278.17 | K223: 4557.2815 | L223: 30.513348 | M223: 4587.7948 | N223: 247525.17 | O223: 4340.8007 | P223: 251865.97 | Q223: 152.07604 | R223: 0.77017412 | T223: 74275.566 | U223: 2221.0474 | V223: 76496.614 | W223: 7305.8648 | X223: 0 | Y223: 7305.8648 | Z223: 81581.431 | AA223: 2221.0474 | AB223: 83802.479 | AC223: 62.905377 | AD223: 5512.6738 | AE223: 72.548093 | AF223: 5585.2219 | AG223: 91.411708 | AH223: 0 | AI223: 91.411708 | AJ223: 5604.0855 | AK223: 72.548093 | AL223: 5676.6336 | AM223: 3.0964186 | AN223: =+AK223/AL223 -> 0.012780126 | AO223: =+U223/V223 -> 0.029034584
A224: 42614 | B224: 228866.59 | C224: 4322.5384 | D224: 233189.13 | E224: 10039.321 | F224: 0 | G224: 10039.321 | H224: 238905.91 | I224: 4322.5384 | J224: 243228.45 | K224: 4830.1671 | L224: 27.760114 | M224: 4857.9273 | N224: 243736.08 | O224: 4350.2985 | P224: 248086.38 | Q224: 52.956957 | R224: 3.3411331 | T224: 74455.56 | U224: 2148.0604 | V224: 76603.62 | W224: 7504.6278 | X224: 0 | Y224: 7504.6278 | Z224: 81960.188 | AA224: 2148.0604 | AB224: 84108.248 | AC224: 18.092923 | AD224: 5440.8397 | AE224: 76.620083 | AF224: 5517.4598 | AG224: 89.312662 | AH224: 0 | AI224: 89.312662 | AJ224: 5530.1524 | AK224: 76.620083 | AL224: 5606.7725 | AM224: 1.2284719 | AN224: =+AK224/AL224 -> 0.013665631 | AO224: =+U224/V224 -> 0.028041239
A225: 42644 | B225: 227430.72 | C225: 4506.1032 | D225: 231936.83 | E225: 10256.008 | F225: 0 | G225: 10256.008 | H225: 237686.73 | I225: 4506.1032 | J225: 242192.83 | K225: 4887.8213 | L225: 27.761449 | M225: 4915.5827 | N225: 242574.55 | O225: 4533.8647 | P225: 247108.42 | Q225: 17.324711 | R225: 1.7569011 | T225: 73560.215 | U225: 2285.0085 | V225: 75845.223 | W225: 7445.9411 | X225: 0 | Y225: 7445.9411 | Z225: 81006.156 | AA225: 2285.0085 | AB225: 83291.164 | AC225: 30.501424 | AD225: 5441.158 | AE225: 78.542194 | AF225: 5519.7002 | AG225: 99.369389 | AH225: 0 | AI225: 99.369389 | AJ225: 5540.5274 | AK225: 78.542194 | AL225: 5619.0696 | AM225: -0.46595399 | AN225: =+AK225/AL225 -> 0.013977793 | AO225: =+U225/V225 -> 0.030127257
A226: 42675 | B226: 233356.36 | C226: 4783.5352 | D226: 238139.9 | E226: 10405.841 | F226: 0 | G226: 10405.841 | H226: 243762.2 | I226: 4783.5352 | J226: 248545.74 | K226: 5026.2556 | L226: 27.789371 | M226: 5054.045 | N226: 248788.46 | O226: 4811.3245 | P226: 253599.78 | Q226: -124.7842 | R226: -4.565792 | T226: 74324.303 | U226: 2268.9367 | V226: 76593.24 | W226: 7430.1417 | X226: 0 | Y226: 7430.1417 | Z226: 81754.445 | AA226: 2268.9367 | AB226: 84023.381 | AC226: -142.57877 | AD226: 5493.5251 | AE226: 86.863049 | AF226: 5580.3881 | AG226: 102.79108 | AH226: 0 | AI226: 102.79108 | AJ226: 5596.3162 | AK226: 86.863049 | AL226: 5683.1792 | AM226: 0.61468702 | AN226: =+AK226/AL226 -> 0.015284235 | AO226: =+U226/V226 -> 0.029623199
A227: 42705 | B227: 243572.26 | C227: 4879.4784 | D227: 248451.74 | E227: 10759.992 | F227: 0 | G227: 10759.992 | H227: 254332.25 | I227: 4879.4784 | J227: 259211.73 | K227: 4842.4119 | L227: 28.100078 | M227: 4870.512 | N227: 259174.66 | O227: 4907.5784 | P227: 264082.24 | Q227: 27.039689 | R227: 3.0561684 | T227: 77058.817 | U227: 2248.0262 | V227: 79306.844 | W227: 7539.7482 | X227: 0 | Y227: 7539.7482 | Z227: 84598.565 | AA227: 2248.0262 | AB227: 86846.592 | AC227: 27.079155 | AD227: 5691.5997 | AE227: 89.945725 | AF227: 5781.5454 | AG227: 110.07123 | AH227: 0 | AI227: 110.07123 | AJ227: 5801.6709 | AK227: 89.945725 | AL227: 5891.6167 | AM227: -0.00134897 | AN227: =+AK227/AL227 -> 0.015266731 | AO227: =+U227/V227 -> 0.02834593
A228: 42736 | B228: 234055.34 | C228: 5120.4942 | D228: 239175.83 | E228: 10220.47 | F228: 0 | G228: 10220.47 | H228: 244275.81 | I228: 5120.4942 | J228: 249396.3 | K228: 4621.3176 | L228: 28.257875 | M228: 4649.5755 | N228: 248897.12 | O228: 5148.752 | P228: 254045.88 | Q228: 49.76237 | R228: 3.0492919 | T228: 75471.714 | U228: 2389.6373 | V228: 77861.352 | W228: 7375.7626 | X228: 0 | Y228: 7375.7626 | Z228: 82847.477 | AA228: 2389.6373 | AB228: 85237.114 | AC228: 29.984654 | AD228: 5626.5255 | AE228: 96.890434 | AF228: 5723.4159 | AG228: 100.92983 | AH228: 0 | AI228: 100.92983 | AJ228: 5727.4553 | AK228: 96.890434 | AL228: 5824.3458 | AM228: 0.70171072 | AN228: =+AK228/AL228 -> 0.016635419 | AO228: =+U228/V228 -> 0.03069093
A229: 42767 | B229: 236565.91 | C229: 6000.6467 | D229: 242566.55 | E229: 9919.6639 | F229: 145.47511 | G229: 10065.139 | H229: 246485.57 | I229: 6146.1218 | J229: 252631.69 | K229: 4409.4092 | L229: 27.076318 | M229: 4436.4856 | N229: 250894.98 | O229: 6173.1981 | P229: 257068.18 | Q229: 2.1163812 | R229: 1.1880508 | T229: 76129.172 | U229: 2412.8607 | V229: 78542.032 | W229: 7180.3091 | X229: 0 | Y229: 7180.3091 | Z229: 83309.481 | AA229: 2412.8607 | AB229: 85722.342 | AC229: 7.1904789 | AD229: 5624.8198 | AE229: 125.78572 | AF229: 5750.6055 | AG229: 96.040206 | AH229: 5.100274 | AI229: 101.14048 | AJ229: 5720.86 | AK229: 130.88599 | AL229: 5851.746 | AM229: -0.17789495 | AN229: =+AK229/AL229 -> 0.022366998 | AO229: =+U229/V229 -> 0.03072063
A230: 42795 | B230: 235276.58 | C230: 5494.091 | D230: 240770.67 | E230: 10792.209 | F230: 0.0019971805 | G230: 10792.211 | H230: 246068.79 | I230: 5494.093 | J230: 251562.89 | K230: 2782.3372 | L230: 28.582773 | M230: 2810.9199 | N230: 248851.13 | O230: 5522.6758 | P230: 254373.8 | Q230: 95.671184 | R230: -0.12102177 | T230: 75312.838 | U230: 2345.7527 | V230: 77658.591 | W230: 7949.3217 | X230: 0 | Y230: 7949.3217 | Z230: 83262.16 | AA230: 2345.7527 | AB230: 85607.913 | AC230: 58.211353 | AD230: 5608.237 | AE230: 110.37893 | AF230: 5718.616 | AG230: 99.669991 | AH230: 7.002e-05 | AI230: 99.670061 | AJ230: 5707.907 | AK230: 110.379 | AL230: 5818.286 | AM230: 1.3133202 | AN230: =+AK230/AL230 -> 0.018971051 | AO230: =+U230/V230 -> 0.030205965
A231: 42826 | B231: 233181.42 | C231: 5583.5473 | D231: 238764.96 | E231: 11641.207 | F231: 0.0019681894 | G231: 11641.209 | H231: 244822.62 | I231: 5583.5493 | J231: 250406.17 | K231: 3622.3012 | L231: 35.326496 | M231: 3657.6277 | N231: 248444.92 | O231: 5618.8758 | P231: 254063.8 | Q231: 34.250109 | R231: -4.6758759 | T231: 75724.774 | U231: 2433.7753 | V231: 78158.549 | W231: 8209.243 | X231: 0 | Y231: 8209.243 | Z231: 83934.017 | AA231: 2433.7753 | AB231: 86367.792 | AC231: 91.82528 | AD231: 5601.6451 | AE231: 112.05564 | AF231: 5713.7007 | AG231: 122.09484 | AH231: 7.002e-05 | AI231: 122.09491 | AJ231: 5723.7399 | AK231: 112.05571 | AL231: 5835.7957 | AM231: -2.0482824 | AN231: =+AK231/AL231 -> 0.019201445 | AO231: =+U231/V231 -> 0.031138952
A232: 42856 | B232: 230371.21 | C232: 5645.5896 | D232: 236016.79 | E232: 11732.695 | F232: 0.0019800199 | G232: 11732.697 | H232: 242103.9 | I232: 5645.5915 | J232: 247749.49 | K232: 3062.1116 | L232: 37.741326 | M232: 3099.8529 | N232: 245166.01 | O232: 5683.3329 | P232: 250849.34 | Q232: -0.61205975 | R232: -1.2103115 | T232: 75487.031 | U232: 2575.9819 | V232: 78063.012 | W232: 8429.1613 | X232: 0 | Y232: 8429.1613 | Z232: 83916.192 | AA232: 2575.9819 | AB232: 86492.174 | AC232: 40.973482 | AD232: 5477.1969 | AE232: 108.55109 | AF232: 5585.748 | AG232: 116.82346 | AH232: 7.002e-05 | AI232: 116.82353 | AJ232: 5594.0204 | AK232: 108.55116 | AL232: 5702.5715 | AM232: -1.470597 | AN232: =+AK232/AL232 -> 0.019035475 | AO232: =+U232/V232 -> 0.03299875
A233: 42887 | B233: 230990.88 | C233: 5687.4207 | D233: 236678.3 | E233: 11745.792 | F233: 0.0019942396 | G233: 11745.794 | H233: 242736.67 | I233: 5687.4227 | J233: 248424.09 | K233: 3046.7769 | L233: 26.39722 | M233: 3073.1741 | N233: 245783.45 | O233: 5713.8199 | P233: 251497.27 | Q233: 50.977884 | R233: -1.4195724 | T233: 75723.092 | U233: 2428.2847 | V233: 78151.377 | W233: 8412.4819 | X233: 0 | Y233: 8412.4819 | Z233: 84135.574 | AA233: 2428.2847 | AB233: 86563.858 | AC233: 18.269989 | AD233: 5451.627 | AE233: 114.43194 | AF233: 5566.0589 | AG233: 117.03628 | AH233: 7.002e-05 | AI233: 117.03635 | AJ233: 5568.6632 | AK233: 114.43201 | AL233: 5683.0953 | AM233: 1.1484111 | AN233: =+AK233/AL233 -> 0.020135507 | AO233: =+U233/V233 -> 0.031071554
A234: 42917 | B234: 227669.07 | C234: 5791.2202 | D234: 233460.29 | E234: 11693.828 | F234: 0.0029661792 | G234: 11693.831 | H234: 239362.9 | I234: 5791.2231 | J234: 245154.12 | K234: 3122.0788 | L234: 27.433392 | M234: 3149.5122 | N234: 242484.98 | O234: 5818.6565 | P234: 248303.63 | Q234: 19.720276 | R234: 4.8383183 | T234: 74820.613 | U234: 2548.9936 | V234: 77369.607 | W234: 8358.9672 | X234: 0 | Y234: 8358.9672 | Z234: 83179.58 | AA234: 2548.9936 | AB234: 85728.574 | AC234: 25.199861 | AD234: 5411.7143 | AE234: 114.79346 | AF234: 5526.5077 | AG234: 118.07324 | AH234: 0.00010502 | AI234: 118.07335 | AJ234: 5529.7875 | AK234: 114.79357 | AL234: 5644.5811 | AM234: -0.1940088 | AN234: =+AK234/AL234 -> 0.020336951 | AO234: =+U234/V234 -> 0.032945671
... A250: 43405 | B250: 273161.47 | C250: 7944.6842 | D250: 281106.15 | E250: 11530.251 | F250: 0 | G250: 11530.251 | H250: 284691.72 | I250: 7944.6842 | J250: 292636.4 | K250: 5097.0938 | L250: 17.411121 | M250: 5114.505 | N250: 289788.81 | O250: 7962.0953 | P250: 297750.91 | Q250: 80.503757 | R250: -2.7598509 | T250: 96550.157 | U250: 3226.2469 | V250: 99776.403 | W250: 8008.3867 | X250: 0 | Y250: 8008.3867 | Z250: 104558.54 | AA250: 3226.2469 | AB250: 107784.79 | AC250: -95.31577 | AD250: 5488.0616 | AE250: 146.62184 | AF250: 5634.6834 | AG250: 109.43924 | AH250: 0 | AI250: 109.43924 | AJ250: 5597.5008 | AK250: 146.62184 | AL250: 5744.1227 | AM250: 5.4634575 | AN250: =+AK250/AL250 -> 0.025525541 | AO250: =+U250/V250 -> 0.032334768
A251: =+'Bcos. Públ.'!A252 -> 43435 | B251: 284714.35 | C251: 7540.6996 | D251: 292255.05 | E251: 11951.143 | F251: 0 | G251: 11951.143 | H251: 296665.49 | I251: 7540.6996 | J251: 304206.19 | K251: 3798.8602 | L251: 16.896966 | M251: 3815.7572 | N251: 300464.35 | O251: 7557.5966 | P251: 308021.95 | Q251: 310.01704 | R251: 0.23153312 | T251: 99977.487 | U251: 3270.9974 | V251: 103248.48 | W251: 8344.0144 | X251: 0 | Y251: 8344.0144 | Z251: 108321.5 | AA251: 3270.9974 | AB251: 111592.5 | AC251: 62.616689 | AD251: 5703.5153 | AE251: 131.82162 | AF251: =+AE251+AD251 -> 5835.3369 | AG251: 111.3655 | AH251: 0 | AI251: =+AH251+AG251 -> 111.3655 | AJ251: 5814.8808 | AK251: 131.82162 | AL251: =+AK251+AJ251 -> 5946.7024 | AM251: 7.6381707 | AN251: =+AK251/AL251 -> 0.022167179 | AO251: =+U251/V251 -> 0.031680828
A252: 43467 | B252: 285898.4 | C252: 8358.112 | D252: 294256.51 | E252: 11544.133 | F252: 0 | G252: 11544.133 | H252: 297442.53 | I252: 8358.112 | J252: 305800.64 | K252: 3481.1138 | L252: 16.525939 | M252: 3497.6398 | N252: 300923.64 | O252: 8374.6379 | P252: 309298.28 | Q252: ND | R252: ND | T252: 98827.19 | U252: 3384.2631 | V252: 102211.45 | W252: 8525.1794 | X252: 0 | Y252: 8525.1794 | Z252: 107352.37 | AA252: 3384.2631 | AB252: 110736.63 | AC252: ND | AD252: 5763.0347 | AE252: 153.2384 | AF252: 5916.2731 | AG252: 92.962395 | AH252: 0 | AI252: 92.962395 | AJ252: 5855.9971 | AK252: 153.2384 | AL252: 6009.2355 | AM252: ND | AN252: =+AK252/AL252 -> 0.025500482 | AO252: =+U252/V252 -> 0.03311041
A253: 43497 | B253: 285496.96 | C253: 7990.4516 | D253: 293487.41 | E253: 11048.776 | F253: 0 | G253: 11048.776 | H253: 296545.73 | I253: 7990.4516 | J253: 304536.18 | K253: 3259.4166 | L253: 17.974376 | M253: 3277.391 | N253: 299805.15 | O253: 7998.4984 | P253: 307803.65 | Q253: ND | R253: ND | T253: 99449.426 | U253: 3523.062 | V253: 102972.49 | W253: 8042.4223 | X253: 0 | Y253: 8042.4223 | Z253: 107491.85 | AA253: 3523.062 | AB253: 111014.91 | AC253: ND | AD253: 5698.0653 | AE253: 136.82244 | AF253: 5834.8878 | AG253: 92.075399 | AH253: 0 | AI253: 92.075399 | AJ253: 5790.1407 | AK253: 136.82244 | AL253: 5926.9632 | AM253: ND | AN253: =+AK253/AL253 -> 0.023084747 | AO253: =+U253/V253 -> 0.034213624
A254: 43525 | B254: 291784.55 | C254: 7865.5246 | D254: 299650.07 | E254: 11146.055 | F254: 0 | G254: 11146.055 | H254: 302930.6 | I254: 7865.5246 | J254: 310796.13 | K254: 3532.7813 | L254: 20.13498 | M254: 3552.9163 | N254: 306463.39 | O254: 7885.6596 | P254: 314349.04 | Q254: ND | R254: ND | T254: 100615.77 | U254: 2936.0371 | V254: 103551.8 | W254: 8027.1882 | X254: 0 | Y254: 8027.1882 | Z254: 108642.95 | AA254: 2936.0371 | AB254: 111578.99 | AC254: ND | AD254: 5709.2577 | AE254: 147.2192 | AF254: 5856.4769 | AG254: 93.144976 | AH254: 0 | AI254: 93.144976 | AJ254: 5802.4026 | AK254: 147.2192 | AL254: 5949.6218 | AM254: ND | AN254: =+AK254/AL254 -> 0.024744295 | AO254: =+U254/V254 -> 0.028353317
A255: 43557 | B255: 301914.61 | C255: 8389.9666 | D255: 310304.58 | E255: 11477.424 | F255: 0 | G255: 11477.424 | H255: 313392.03 | I255: 8389.9666 | J255: 321782 | K255: 3622.2736 | L255: 17.104701 | M255: 3639.3783 | N255: 317014.31 | O255: 8407.0713 | P255: 325421.38 | Q255: ND | R255: ND | T255: 103898.23 | U255: 2945.7014 | V255: 106843.93 | W255: 8263.755 | X255: 0 | Y255: 8263.755 | Z255: 112161.98 | AA255: 2945.7014 | AB255: 115107.69 | AC255: ND | AD255: 5660.6838 | AE255: 155.63492 | AF255: 5816.3187 | AG255: 91.868974 | AH255: 0 | AI255: 91.868974 | AJ255: 5752.5528 | AK255: 155.63492 | AL255: 5908.1877 | AM255: ND | AN255: =+AK255/AL255 -> 0.026342244 | AO255: =+U255/V255 -> 0.027570133
A256: 43586 | B256: 304404.04 | C256: 8614.6579 | D256: 313018.7 | E256: 11330.166 | F256: 0 | G256: 11330.166 | H256: 315734.21 | I256: 8614.6579 | J256: 324348.86 | K256: 4277.6641 | L256: 17.405222 | M256: 4295.0693 | N256: 320011.87 | O256: 8632.0631 | P256: 328643.93 | Q256: ND | R256: ND | T256: 103728.33 | U256: 3080.1264 | V256: 106808.46 | W256: 8121.9719 | X256: 0 | Y256: 8121.9719 | Z256: 111850.3 | AA256: 3080.1264 | AB256: 114930.43 | AC256: ND | AD256: 5692.605 | AE256: 156.99908 | AF256: 5849.6041 | AG256: 91.007431 | AH256: 0 | AI256: 91.007431 | AJ256: 5783.6124 | AK256: 156.99908 | AL256: 5940.6115 | AM256: ND | AN256: =+AK256/AL256 -> 0.026428101 | AO256: =+U256/V256 -> 0.028837851
A257: 43617 | B257: 302478.87 | C257: 8150.9596 | D257: 310629.82 | E257: 11375.569 | F257: 0 | G257: 11375.569 | H257: 313854.43 | I257: 8150.9596 | J257: 322005.39 | K257: 4157.7706 | L257: 17.621384 | M257: 4175.3919 | N257: 318012.21 | O257: 8168.581 | P257: 326180.79 | Q257: ND | R257: ND | T257: 104696.4 | U257: 3120.5393 | V257: 107816.94 | W257: 8199.4999 | X257: 0 | Y257: 8199.4999 | Z257: 112895.9 | AA257: 3120.5393 | AB257: 116016.44 | AC257: ND | AD257: 5621.6948 | AE257: 142.98278 | AF257: 5764.6776 | AG257: 90.275413 | AH257: 0 | AI257: 90.275413 | AJ257: 5711.9702 | AK257: 142.98278 | AL257: 5854.953 | AM257: ND | AN257: =+AK257/AL257 -> 0.024420825 | AO257: =+U257/V257 -> 0.028942941
A258: 43647 | B258: 296663.64 | C258: 8250.2525 | D258: 304913.9 | E258: 11372.251 | F258: 0 | G258: 11372.251 | H258: 308035.9 | I258: 8250.2525 | J258: 316286.15 | K258: 4806.5552 | L258: 17.06358 | M258: 4823.6187 | N258: 312842.45 | O258: 8267.316 | P258: 321109.77 | Q258: ND | R258: ND | T258: 105631.94 | U258: 3444.1331 | V258: 109076.07 | W258: 8544.4565 | X258: 0 | Y258: 8544.4565 | Z258: 114176.4 | AA258: 3444.1331 | AB258: 117620.53 | AC258: ND | AD258: 5561.3306 | AE258: 139.91614 | AF258: 5701.2467 | AG258: 82.322978 | AH258: 0 | AI258: 82.322978 | AJ258: 5643.6536 | AK258: 139.91614 | AL258: 5783.5697 | AM258: ND | AN258: =+AK258/AL258 -> 0.024192003 | AO258: =+U258/V258 -> 0.031575515
A259: 43678 | B259: 311126.7 | C259: 8582.7255 | D259: 319709.43 | E259: 11940.11 | F259: 0 | G259: 11940.11 | H259: 323066.81 | I259: 8582.7255 | J259: 331649.54 | K259: 4024.0596 | L259: 18.283353 | M259: 4042.343 | N259: 327090.87 | O259: 8601.0089 | P259: 335691.88 | Q259: ND | R259: ND | T259: 108040.7 | U259: 3726.2526 | V259: 111766.95 | W259: 8924.3076 | X259: 0 | Y259: 8924.3076 | Z259: 116965.01 | AA259: 3726.2526 | AB259: 120691.26 | AC259: ND | AD259: 5542.4377 | AE259: 132.53842 | AF259: 5674.9761 | AG259: 82.304531 | AH259: 0 | AI259: 82.304531 | AJ259: 5624.7422 | AK259: 132.53842 | AL259: 5757.2806 | AM259: ND | AN259: =+AK259/AL259 -> 0.023021011 | AO259: =+U259/V259 -> 0.033339484
A260: 43709 | B260: 313565.21 | C260: 8255.062 | D260: 321820.27 | E260: 12158.592 | F260: 0 | G260: 12158.592 | H260: 325723.8 | I260: 8255.062 | J260: 333978.86 | K260: 4130.9405 | L260: 19.224046 | M260: 4150.1645 | N260: 329854.74 | O260: 8274.286 | P260: 338129.03 | Q260: ND | R260: ND | T260: 109711.5 | U260: 3534.9285 | V260: 113246.43 | W260: 9144.0666 | X260: 0 | Y260: 9144.0666 | Z260: 118855.57 | AA260: 3534.9285 | AB260: 122390.5 | AC260: ND | AD260: 5518.6579 | AE260: 127.78184 | AF260: 5646.4398 | AG260: 81.608194 | AH260: 0 | AI260: 81.608194 | AJ260: 5600.2661 | AK260: 127.78184 | AL260: 5728.048 | AM260: ND | AN260: =+AK260/AL260 -> 0.022308096 | AO260: =+U260/V260 -> 0.03121448
A261: 43739 | B261: 318052.34 | C261: 7986.269 | D261: 326038.61 | E261: 12234.942 | F261: 0 | G261: 12234.942 | H261: 330287.28 | I261: 7986.269 | J261: 338273.55 | K261: 4058.2715 | L261: 19.61635 | M261: 4077.8879 | N261: 334345.55 | O261: 8005.8854 | P261: 342351.44 | Q261: ND | R261: ND | T261: 112501.49 | U261: 3447.7973 | V261: 115949.29 | W261: 9181.4189 | X261: 0 | Y261: 9181.4189 | Z261: 121682.91 | AA261: 3447.7973 | AB261: 125130.71 | AC261: ND | AD261: 5493.6617 | AE261: 121.29762 | AF261: 5614.9594 | AG261: 81.610097 | AH261: 0 | AI261: 81.610097 | AJ261: 5575.2718 | AK261: 121.29762 | AL261: 5696.5695 | AM261: ND | AN261: =+AK261/AL261 -> 0.021293099 | AO261: =+U261/V261 -> 0.029735391
A262: 43770 | B262: 322699.62 | C262: 8796.1733 | D262: 331495.79 | E262: 11993.847 | F262: 0 | G262: 11993.847 | H262: 334693.46 | I262: 8796.1733 | J262: 343489.64 | K262: 4151.4075 | L262: 6.3036952 | M262: 4157.7112 | N262: 338844.87 | O262: 8802.477 | P262: 347647.35 | Q262: ND | R262: ND | T262: 115760.9 | U262: 3579.258 | V262: 119340.16 | W262: 8908.6576 | X262: 0 | Y262: 8908.6576 | Z262: 124669.56 | AA262: 3579.258 | AB262: 128248.82 | AC262: ND | AD262: 5468.782 | AE262: 137.86774 | AF262: 5606.6498 | AG262: 81.532497 | AH262: 0 | AI262: 81.532497 | AJ262: 5550.3145 | AK262: 137.86774 | AL262: 5688.1823 | AM262: ND | AN262: =+AK262/AL262 -> 0.024237574 | AO262: =+U262/V262 -> 0.029992066
A263: 43800 | B263: 325802.88 | C263: 8601.6814 | D263: 334404.56 | E263: 12794.956 | F263: 0 | G263: 12794.956 | H263: 338597.84 | I263: 8601.6814 | J263: 347199.52 | K263: 5221.455 | L263: 5.7965988 | M263: 5227.2516 | N263: 343819.29 | O263: 8607.4779 | P263: 352426.77 | Q263: ND | R263: ND | T263: 119549.45 | U263: 3498.1044 | V263: 123047.56 | W263: 8937.5083 | X263: 0 | Y263: 8937.5083 | Z263: 128486.96 | AA263: 3498.1044 | AB263: 131985.07 | AC263: ND | AD263: 5524.2508 | AE263: 136.69319 | AF263: 5660.944 | AG263: 103.31711 | AH263: 0 | AI263: 103.31711 | AJ263: 5627.5679 | AK263: 136.69319 | AL263: 5764.2611 | AM263: ND | AN263: =+AK263/AL263 -> 0.023713914 | AO263: =+U263/V263 -> 0.028428881
... A323: 45627 | B323: 622778.52 | C323: 9075.4051 | D323: 631853.93 | E323: 20487.655 | F323: 0 | G323: 20487.655 | H323: 643266.18 | I323: 9075.4051 | J323: 652341.58 | K323: 43071.177 | L323: 13.30568 | M323: 43084.483 | N323: 686337.35 | O323: 9088.7107 | P323: 695426.07 | Q323: ND | R323: ND | T323: 255966.49 | U323: 7084.8078 | V323: 263051.29 | W323: 14929.08 | X323: 0 | Y323: 14929.08 | Z323: 270895.57 | AA323: 7084.8078 | AB323: 277980.38 | AC323: ND | AD323: 8324.1509 | AE323: 45.173088 | AF323: 8369.324 | AG323: 126.14203 | AH323: 0 | AI323: 126.14203 | AJ323: 8450.293 | AK323: 45.173088 | AL323: 8495.4661 | AM323: ND | AN323: =+AK323/AL323 -> 0.0053173172 | AO323: =+U323/V323 -> 0.02693318
A324: 45658 | B324: =+'[1]Bcos. Priv.'!B325*[2]TC!$B316 -> 619351.75 | C324: =+'[1]Bcos. Priv.'!C325*[2]TC!$B316 -> 9626.4677 | D324: =+'[1]Bcos. Priv.'!D325*[2]TC!$B316 -> 628978.21 | E324: =+'[1]Bcos. Priv.'!E325*[2]TC!$B316 -> 18618.255 | F324: =+'[1]Bcos. Priv.'!F325*[2]TC!$B316 -> 0 | G324: =+'[1]Bcos. Priv.'!G325*[2]TC!$B316 -> 18618.255 | H324: =+'[1]Bcos. Priv.'!H325*[2]TC!$B316 -> 637970 | I324: =+'[1]Bcos. Priv.'!I325*[2]TC!$B316 -> 9626.4677 | ... P324: =+'[1]Bcos. Priv.'!P325*[2]TC!$B316 -> 690769.99 | Q324: ND | R324: ND | T324: =+'[1]Bcos. Priv.'!T325*[2]TC!$B316 -> 258044.94 | U324: =+'[1]Bcos. Priv.'!U325*[2]TC!$B316 -> 7434.8195 | V324: =+'[1]Bcos. Priv.'!V325*[2]TC!$B316 -> 265479.76 | W324: =+'[1]Bcos. Priv.'!W325*[2]TC!$B316 -> 13186.042 | X324: =+'[1]Bcos. Priv.'!X325*[2]TC!$B316 -> 0 | Y324: =+'[1]Bcos. Priv.'!Y325*[2]TC!$B316 -> 13186.042 | Z324: =+'[1]Bcos. Priv.'!Z325*[2]TC!$B316 -> 271230.98 | AA324: =+'[1]Bcos. Priv.'!AA325*[2]TC!$B316 -> 7434.8195 | AB324: =+'[1]Bcos. Priv.'!AB325*[2]TC!$B316 -> 278665.8 | AC324: ND | AD324: =+'[1]Bcos. Priv.'!AD325 -> 8378.7117 | AE324: =+'[1]Bcos. Priv.'!AE325 -> 50.824363 | AF324: =+'[1]Bcos. Priv.'!AF325 -> 8429.5361 | AG324: =+'[1]Bcos. Priv.'!AG325 -> 125.97311 | AH324: =+'[1]Bcos. Priv.'!AH325 -> 0 | AI324: =+'[1]Bcos. Priv.'!AI325 -> 125.97311 | AJ324: =+'[1]Bcos. Priv.'!AJ325 -> 8504.6848 | AK324: =+'[1]Bcos. Priv.'!AK325 -> 50.824363 | AL324: =+'[1]Bcos. Priv.'!AL325 -> 8555.5092 | AM324: ND | AN324: =+AK324/AL324 -> 0.0059405421 | AO324: =+U324/V324 -> 0.028005222
A325: 45689 | B325: =+'[1]Bcos. Priv.'!B326*[2]TC!$B317 -> 613155.98 | C325: =+'[1]Bcos. Priv.'!C326*[2]TC!$B317 -> 9914.5949 | D325: =+'[1]Bcos. Priv.'!D326*[2]TC!$B317 -> 623070.58 | E325: =+'[1]Bcos. Priv.'!E326*[2]TC!$B317 -> 19802.446 | F325: =+'[1]Bcos. Priv.'!F326*[2]TC!$B317 -> 0 | G325: =+'[1]Bcos. Priv.'!G326*[2]TC!$B317 -> 19802.446 | H325: =+'[1]Bcos. Priv.'!H326*[2]TC!$B317 -> 632958.43 | I325: =+'[1]Bcos. Priv.'!I326*[2]TC!$B317 -> 9914.5949 | ... P325: =+'[1]Bcos. Priv.'!P326*[2]TC!$B317 -> 688826.04 | Q325: ND | R325: ND | T325: =+'[1]Bcos. Priv.'!T326*[2]TC!$B317 -> 260180.09 | U325: =+'[1]Bcos. Priv.'!U326*[2]TC!$B317 -> 7735.0637 | V325: =+'[1]Bcos. Priv.'!V326*[2]TC!$B317 -> 267915.15 | W325: =+'[1]Bcos. Priv.'!W326*[2]TC!$B317 -> 13061.966 | X325: =+'[1]Bcos. Priv.'!X326*[2]TC!$B317 -> 0 | Y325: =+'[1]Bcos. Priv.'!Y326*[2]TC!$B317 -> 13061.966 | Z325: =+'[1]Bcos. Priv.'!Z326*[2]TC!$B317 -> 273242.06 | AA325: =+'[1]Bcos. Priv.'!AA326*[2]TC!$B317 -> 7735.0637 | AB325: =+'[1]Bcos. Priv.'!AB326*[2]TC!$B317 -> 280977.12 | AC325: ND | AD325: =+'[1]Bcos. Priv.'!AD326 -> 8288.7376 | AE325: =+'[1]Bcos. Priv.'!AE326 -> 51.180724 | AF325: =+'[1]Bcos. Priv.'!AF326 -> 8339.9183 | AG325: =+'[1]Bcos. Priv.'!AG326 -> 158.28297 | AH325: =+'[1]Bcos. Priv.'!AH326 -> 0 | AI325: =+'[1]Bcos. Priv.'!AI326 -> 158.28297 | AJ325: =+'[1]Bcos. Priv.'!AJ326 -> 8447.0206 | AK325: =+'[1]Bcos. Priv.'!AK326 -> 51.180724 | AL325: =+'[1]Bcos. Priv.'!AL326 -> 8498.2013 | AM325: ND | AN325: =+AK325/AL325 -> 0.0060225361 | AO325: =+U325/V325 -> 0.028871318
A326: 45717 | B326: =+'[1]Bcos. Priv.'!B327*[2]TC!$B318 -> 619971.34 | C326: =+'[1]Bcos. Priv.'!C327*[2]TC!$B318 -> 9640.7054 | D326: =+'[1]Bcos. Priv.'!D327*[2]TC!$B318 -> 629612.04 | E326: =+'[1]Bcos. Priv.'!E327*[2]TC!$B318 -> 19460.983 | F326: =+'[1]Bcos. Priv.'!F327*[2]TC!$B318 -> 0 | G326: =+'[1]Bcos. Priv.'!G327*[2]TC!$B318 -> 19460.983 | H326: =+'[1]Bcos. Priv.'!H327*[2]TC!$B318 -> 639432.32 | I326: =+'[1]Bcos. Priv.'!I327*[2]TC!$B318 -> 9640.7054 | ... P326: =+'[1]Bcos. Priv.'!P327*[2]TC!$B318 -> 694367.02 | Q326: ND | R326: ND | T326: =+'[1]Bcos. Priv.'!T327*[2]TC!$B318 -> 266159.97 | U326: =+'[1]Bcos. Priv.'!U327*[2]TC!$B318 -> 7467.2383 | V326: =+'[1]Bcos. Priv.'!V327*[2]TC!$B318 -> 273627.2 | W326: =+'[1]Bcos. Priv.'!W327*[2]TC!$B318 -> 13010.88 | X326: =+'[1]Bcos. Priv.'!X327*[2]TC!$B318 -> 0 | Y326: =+'[1]Bcos. Priv.'!Y327*[2]TC!$B318 -> 13010.88 | Z326: =+'[1]Bcos. Priv.'!Z327*[2]TC!$B318 -> 279170.85 | AA326: =+'[1]Bcos. Priv.'!AA327*[2]TC!$B318 -> 7467.2383 | AB326: =+'[1]Bcos. Priv.'!AB327*[2]TC!$B318 -> 286638.08 | AC326: ND | AD326: =+'[1]Bcos. Priv.'!AD327 -> 8398.6842 | AE326: =+'[1]Bcos. Priv.'!AE327 -> 51.593208 | AF326: =+'[1]Bcos. Priv.'!AF327 -> 8450.2774 | AG326: =+'[1]Bcos. Priv.'!AG327 -> 153.1109 | AH326: =+'[1]Bcos. Priv.'!AH327 -> 0 | AI326: =+'[1]Bcos. Priv.'!AI327 -> 153.1109 | AJ326: =+'[1]Bcos. Priv.'!AJ327 -> 8551.7951 | AK326: =+'[1]Bcos. Priv.'!AK327 -> 51.593208 | AL326: =+'[1]Bcos. Priv.'!AL327 -> 8603.3883 | AM326: ND | AN326: =+AK326/AL326 -> 0.0059968475 | AO326: =+U326/V326 -> 0.027289824
A327: 45748 | B327: 627741.79 | C327: 10310.583 | D327: 638052.38 | E327: 19376.548 | F327: 0 | G327: 19376.548 | H327: 647118.34 | I327: 10310.583 | J327: 657428.92 | K327: 43945.298 | L327: 15.407387 | M327: 43960.705 | N327: 691063.64 | O327: 10325.991 | P327: 701389.63 | Q327: ND | R327: ND | T327: 270220.38 | U327: 8026.7523 | V327: 278247.13 | W327: 12984.195 | X327: 0 | Y327: 12984.195 | Z327: 283204.58 | AA327: 8026.7523 | AB327: 291231.33 | AC327: ND | AD327: 8522.7636 | AE327: 54.443042 | AF327: 8577.2067 | AG327: 152.38391 | AH327: 0 | AI327: 152.38391 | AJ327: 8675.1475 | AK327: 54.443042 | AL327: 8729.5906 | AM327: ND | AN327: =+AK327/AL327 -> 0.0062366088 | AO327: =+U327/V327 -> 0.028847565
A328: 45778 | B328: 642037.78 | C328: 10783.836 | D328: 652821.61 | E328: 18898.822 | F328: 0 | G328: 18898.822 | H328: 660936.6 | I328: 10783.836 | J328: 671720.43 | K328: 49564.364 | L328: 13.798642 | M328: 49578.163 | N328: 710500.96 | O328: 10797.635 | P328: 721298.6 | Q328: ND | R328: ND | T328: 274027.42 | U328: 8489.9294 | V328: 282517.35 | W328: 12611.876 | X328: 0 | Y328: 12611.876 | Z328: 286639.3 | AA328: 8489.9294 | AB328: 295129.23 | AC328: ND | AD328: 8829.8467 | AE328: 55.038799 | AF328: 8884.8855 | AG328: 150.84568 | AH328: 0 | AI328: 150.84568 | AJ328: 8980.6924 | AK328: 55.038799 | AL328: 9035.7312 | AM328: ND | AN328: =+AK328/AL328 -> 0.0060912391 | AO328: =+U328/V328 -> 0.030051002
A329: 45809 | B329: 624289.39 | C329: 11108.299 | D329: 635397.69 | E329: 18623.634 | F329: 0 | G329: 18623.634 | H329: 642913.02 | I329: 11108.299 | J329: 654021.32 | K329: 40793.667 | L329: 8.1078367 | M329: 40801.775 | N329: 683706.69 | O329: 11116.407 | P329: 694823.1 | Q329: ND | R329: ND | T329: 277753.1 | U329: 8885.5344 | V329: 286638.63 | W329: 12681.354 | X329: 0 | Y329: 12681.354 | Z329: 290434.45 | AA329: 8885.5344 | AB329: 299319.99 | AC329: ND | AD329: 8762.4227 | AE329: 56.204218 | AF329: 8818.6269 | AG329: 150.25487 | AH329: 0 | AI329: 150.25487 | AJ329: 8912.6776 | AK329: 56.204218 | AL329: 8968.8818 | AM329: ND | AN329: =+AK329/AL329 -> 0.0062665803 | AO329: =+U329/V329 -> 0.030999082
A330: 45839 | B330: 630417.32 | C330: 11400.855 | D330: 641818.17 | E330: 17839.992 | F330: 0 | G330: 17839.992 | H330: 648257.31 | I330: 11400.855 | J330: 659658.17 | K330: 40507.261 | L330: 7.7268236 | M330: 40514.988 | N330: 688764.57 | O330: 11408.582 | P330: 700173.15 | Q330: ND | R330: ND | T330: 278583.2 | U330: 9137.451 | V330: 287720.65 | W330: 11901.678 | X330: 0 | Y330: 11901.678 | Z330: 290484.88 | AA330: 9137.451 | AB330: 299622.33 | AC330: ND | AD330: 8752.9634 | AE330: 56.309181 | AF330: 8809.2725 | AG330: 147.73396 | AH330: 0 | AI330: 147.73396 | AJ330: 8900.6973 | AK330: 56.309181 | AL330: 8957.0065 | AM330: ND | AN330: =+AK330/AL330 -> 0.0062866072 | AO330: =+U330/V330 -> 0.031758064
A331: 45870 | B331: 633923.84 | C331: 10513.362 | D331: 644437.2 | E331: 20011.063 | F331: 0 | G331: 20011.063 | H331: 653934.9 | I331: 10513.362 | J331: 664448.27 | K331: 39926.26 | L331: 8.386316 | M331: 39934.646 | N331: 693861.16 | O331: 10521.748 | P331: 704382.91 | Q331: ND | R331: ND | T331: 281532.98 | U331: 8255.1412 | V331: 289788.12 | W331: 11930.918 | X331: 0 | Y331: 11930.918 | Z331: 293463.89 | AA331: 8255.1412 | AB331: 301719.04 | AC331: ND | AD331: 8810.873 | AE331: 56.462581 | AF331: 8867.3356 | AG331: 202.02886 | AH331: 0 | AI331: 202.02886 | AJ331: 9012.9019 | AK331: 56.462581 | AL331: 9069.3644 | AM331: ND | AN331: =+AK331/AL331 -> 0.0062256381 | AO331: =+U331/V331 -> 0.028486817
A332: 45901 | B332: 638841.02 | C332: 11191.259 | D332: 650032.28 | E332: 21389.787 | F332: 0 | G332: 21389.787 | H332: 660230.81 | I332: 11191.259 | J332: 671422.07 | K332: 34699.015 | L332: 11.083064 | M332: 34710.098 | N332: 694929.82 | O332: 11202.342 | P332: 706132.17 | Q332: ND | R332: ND | T332: 284563.87 | U332: 8700.6082 | V332: 293264.47 | W332: 11866.611 | X332: 0 | Y332: 11866.611 | Z332: 296430.48 | AA332: 8700.6082 | AB332: 305131.08 | AC332: ND | AD332: 8891.383 | AE332: 62.508486 | AF332: 8953.8915 | AG332: 239.00557 | AH332: 0 | AI332: 239.00557 | AJ332: 9130.3886 | AK332: 62.508486 | AL332: 9192.8971 | AM332: ND | AN332: =+AK332/AL332 -> 0.0067996503 | AO332: =+U332/V332 -> 0.029668129
A334: (1) La variación del saldo contable de los créditos brutos se encuentra influida por la transferencia de créditos a cuentas de orden (créditos castigados) de acuerdo a lo establecido por la normativa. Por este motivo se presenta la variación mensual de los créditos castigados, elemento que, para evaluar la evolución del crédito desde una perspectiva económica, debería sumarse al saldo de los créditos brutos.
A335: (2) Incluye los bancos privados en actividad en cada fecha, con excepción de los bancos La Caja Obrera, Comercial, de Crédito y de Montevideo (suspendidos en agosto de 2002), que se incluyen hasta febrero de 2003 inclusive.
A336: (3) Corresponde a los grupos N° 14010 (Préstamos), 14020 (Arrendamientos Financieros), 14060 (Ingresos Percibidos No Devengados), 14070 (Grupos de Ahorro Previo), 14080 (Deudores por Productos Financieros Devengados), 16010 (Créditos Vencidos - Sector No Público) y 16080 (Deudores por Productos Financieros) del Plan de Cuentas para EIF, excepto las cuentas de deudores por créditos documentarios diferidos y domésticos diferidos (185000 y 189001 respectivamente), las cuentas de operaciones a liquidar (369080), sector público (245000 y 393000), sector financiero (407000), y a partir de marzo de 2005 los préstamos garantizados con prenda de depósitos (509000).
A337: Nuevo Plan de cuenta: 1.4.2.1 Créditos vigentes + 1.4.2.2 Créditos vigentes (deudores por intereses)+ 1.4.2.4 Colocacion vencida + 1.4.2.5 Colocación vencida (deudores por intereses) + 1.4.2.7 Créditos en gestión + 1.4.2.8 Créditos en gestión (deudores por intereses) +1.4.2.10 Créditos morosos + 1.4.2.11 Créditos morosos (deudores por intereses)
A338: (4) Incluye a las cuentas de los grupos N° 14050 y 16040 (Créditos Vigentes y Vencidos - Sector Público Nacional y No Nacional), 14080 y 16080 (Créditos Vigentes y Vencidos - Deudores por Productos Financieros Devengados) que corresponden al sector público nacional, excepto las cuentas de operaciones a liquidar (227000, 229000 y 381000) y deudores por créditos domésticos diferidos (221000). Incluye Estado, organismos de seguridad social, gobiernos departamentales y otros integrantes del sector público.
A339: Nuevo Plan de cuenta: 1.4.3.1 Créditos vigentes + 1.4.3.2 Créditos vigentes (deudores por intereses)+ 1.4.3.4 Colocación vencida + 1.4.3.5 Colocación vencida (deudores por intereses)+ 1.4.3.7 Créditos en gestión + 1.4.3.8 Créditos en gestión (deudores por intereses) +1.4.3.10 Créditos morosos + 1.4.3.11 Créditos morosos (deudores por intereses).
A340: (5) Incluye sector privado no residente y sector público no nacional.
A342: Notas:
A343: Los meses que aparecen subrayados incluyen comentarios explicativos y vínculo a la hoja con detalle de todos los comentarios.
A344: Diferencias en las columnas de Total se deben a redondeo de las cifras.

Sheet Coop.
A1: Banco Central del Uruguay | T1: Banco Central del Uruguay
A2: Superintendencia de Servicios Financieros | T2: Superintendencia de Instituciones de Intermediación Financiera
M3: Volver al Índice | AH3: Volver al Índice
B4: CRÉDITOS BRUTOS SECTOR NO FINANCIERO (SNF) (1) | T4: CRÉDITOS BRUTOS SNF (1) - ANEXO RESIDENTES POR MONEDAS
B5: COOPERATIVAS DE INTERMEDIACIÓN FINANCIERA (2) | T5: COOPERATIVAS DE INTERMEDIACIÓN FINANCIERA (2)
B6: (Crédito Total en millones de pesos) | T6: (Créditos en MN en millones de pesos y en ME en millones de dólares)
B8: TOTAL (MN + ME) en millones de pesos
B9: RESIDENTES | K9: NO RESIDENTES (5) | N9: TOTAL | Q9: Variación mensual | T9: MONEDA NACIONAL en millones de pesos | AD9: MONEDA EXTRANJERA en millones de dólares
A10: Mes | B10: SECTOR PRIVADO (3) | E10: SECTOR PÚBLICO (4) | H10: TOTAL (S.Priv. + S.Públ) | Q10: Castigados (1) | T10: SECTOR PRIVADO (3) | W10: SECTOR PÚBLICO (4) | Z10: TOTAL (S.Priv. + S.Públ) | AC10: Variac. mens. | AD10: SECTOR PRIVADO (3) | AG10: SECTOR PÚBLICO (4) | AJ10: TOTAL (S.Priv. + S.Públ) | AM10: Variac. mens.
B11: Vigentes | C11: Vencidos | D11: Total | E11: Vigentes | F11: Vencidos | G11: Total | H11: Vigentes | I11: Vencidos | J11: Total | K11: Vigentes | L11: Vencidos | M11: Total | N11: Vigentes | O11: Vencidos | P11: Total | Q11: Resid. | R11: No resid. | T11: Vigentes | U11: Vencidos | V11: Total | W11: Vigentes | X11: Vencidos | Y11: Total | Z11: Vigentes | AA11: Vencidos | AB11: Total | AC11: Castigados (1) | AD11: Vigentes | AE11: Vencidos | AF11: Total | AG11: Vigentes | AH11: Vencidos | AI11: Total | AJ11: Vigentes | AK11: Vencidos | AL11: Total | AM11: Castigados (1)
A12: 36130 | B12: 3407.355 | C12: 443.497 | D12: 3850.852 | E12: 0 | F12: 0 | G12: 0 | H12: 3407.355 | I12: 443.497 | J12: 3850.852 | K12: 10.817 | L12: 0 | M12: 10.817 | N12: 3407.355 | O12: 443.497 | P12: 3850.852 | Q12: 1.0498192 | R12: 0 | T12: 1341.308 | U12: 173.072 | V12: 1525.197 | W12: 0 | X12: 0 | Y12: 0 | Z12: 1341.308 | AA12: 173.072 | AB12: 1525.197 | AC12: -28.914457 | AD12: 190 | AE12: 25 | AF12: 215 | AG12: 0 | AH12: 0 | AI12: 0 | AJ12: 190 | AK12: 25 | AL12: 215 | AM12: 2.7701097
A13: 36161 | B13: 3301.97 | C13: 570.44 | D13: 3872.41 | E13: 0 | F13: 0 | G13: 0 | H13: 3301.97 | I13: 570.44 | J13: 3872.41 | K13: 10.97 | L13: 0 | M13: 10.97 | N13: 3312.94 | O13: 570.44 | P13: 3883.38 | Q13: 2.7633489 | R13: 0 | T13: 1305.43 | U13: 219.4 | V13: 1524.83 | W13: 0 | X13: 0 | Y13: 0 | Z13: 1305.43 | AA13: 219.4 | AB13: 1524.83 | AC13: 0.098874 | AD13: 182 | AE13: 32 | AF13: 214 | AG13: 0 | AH13: 0 | AI13: 0 | AJ13: 182 | AK13: 32 | AL13: 214 | AM13: 0.24288741
A14: 36192 | B14: 3251.56 | C14: 637.13 | D14: 3888.69 | E14: 0 | F14: 0 | G14: 0 | H14: 3251.56 | I14: 637.13 | J14: 3888.69 | K14: 10.985 | L14: 0 | M14: 10.985 | N14: 3262.545 | O14: 637.13 | P14: 3899.675 | Q14: 0.44537497 | R14: 0 | T14: 1285.245 | U14: 241.67 | V14: 1515.93 | W14: 0 | X14: 0 | Y14: 0 | Z14: 1285.245 | AA14: 241.67 | AB14: 1515.93 | AC14: 0.25195263 | AD14: 179 | AE14: 36 | AF14: 215 | AG14: 0 | AH14: 0 | AI14: 0 | AJ14: 179 | AK14: 36 | AL14: 215 | AM14: 0.01760786
A15: 36220 | B15: 3250.835 | C15: 532.56 | D15: 3794.49 | E15: 0 | F15: 0 | G15: 0 | H15: 3261.93 | I15: 532.56 | J15: 3794.49 | K15: 11.095 | L15: 0 | M15: 11.095 | N15: 3261.93 | O15: 532.56 | P15: 3805.585 | Q15: 109.76238 | R15: 0 | T15: 1264.83 | U15: 210.805 | V15: 1475.635 | W15: 0 | X15: 0 | Y15: 0 | Z15: 1264.83 | AA15: 210.805 | AB15: 1475.635 | AC15: 36.158385 | AD15: 180 | AE15: 30 | AF15: 209 | AG15: 0 | AH15: 0 | AI15: 0 | AJ15: 180 | AK15: 30 | AL15: 209 | AM15: 6.6339788
A16: 36251 | B16: 3264.899 | C16: 546.007 | D16: 3799.763 | E16: 0 | F16: 0 | G16: 0 | H16: 3264.899 | I16: 546.007 | J16: 3799.763 | K16: 11.143 | L16: 0 | M16: 11.143 | N16: 3264.899 | O16: 546.007 | P16: 3810.906 | Q16: 2.2544573 | R16: 0 | T16: 1248.016 | U16: 211.717 | V16: 1470.876 | W16: 0 | X16: 0 | Y16: 0 | Z16: 1248.016 | AA16: 211.717 | AB16: 1470.876 | AC16: 1.6706797 | AD16: 180 | AE16: 29 | AF16: 209 | AG16: 0 | AH16: 0 | AI16: 0 | AJ16: 180 | AK16: 29 | AL16: 210 | AM16: 0.052389631
A17: 36281 | B17: 3290.742 | C17: 526.071 | D17: 3816.813 | E17: 0 | F17: 0 | G17: 0 | H17: 3290.742 | I17: 526.071 | J17: 3816.813 | K17: 11.193 | L17: 0 | M17: 11.193 | N17: 3290.742 | O17: 526.071 | P17: 3828.006 | Q17: 3.8294469 | R17: 0 | T17: 1253.616 | U17: 201.474 | V17: 1455.09 | W17: 0 | X17: 0 | Y17: 0 | Z17: 1253.616 | AA17: 201.474 | AB17: 1455.09 | AC17: 2.0650431 | AD17: 182 | AE17: 29 | AF17: 211 | AG17: 0 | AH17: 0 | AI17: 0 | AJ17: 182 | AK17: 29 | AL17: 211 | AM17: 0.15763457
A18: 36312 | B18: 3308.961 | C18: 511.695 | D18: 3809.285 | E18: 0 | F18: 0 | G18: 0 | H18: 3308.961 | I18: 511.695 | J18: 3809.285 | K18: 11.371 | L18: 0 | M18: 11.371 | N18: 3308.961 | O18: 511.695 | P18: 3820.656 | Q18: 15.881818 | R18: 0 | T18: 1239.439 | U18: 193.307 | V18: 1432.746 | W18: 0 | X18: 0 | Y18: 0 | Z18: 1239.439 | AA18: 193.307 | AB18: 1432.746 | AC18: 4.220115 | AD18: 182 | AE18: 27 | AF18: 210 | AG18: 0 | AH18: 0 | AI18: 0 | AJ18: 182 | AK18: 27 | AL18: 210 | AM18: 1.0255653
A19: 36342 | B19: 3277.5 | C19: 540.5 | D19: 3818 | E19: 0 | F19: 0 | G19: 0 | H19: 3277.5 | I19: 540.5 | J19: 3818 | K19: 11.5 | L19: 0 | M19: 11.5 | N19: 3289 | O19: 540.5 | P19: 3818 | Q19: 4.7833013 | R19: 0 | T19: 1219 | U19: 195.5 | V19: 1414.5 | W19: 0 | X19: 0 | Y19: 0 | Z19: 1219 | AA19: 195.5 | AB19: 1414.5 | AC19: 2.1820533 | AD19: 179 | AE19: 29 | AF19: 208 | AG19: 0 | AH19: 0 | AI19: 0 | AJ19: 179 | AK19: 29 | AL19: 209 | AM19: 0.22619548
A20: 36373 | B20: 3289.53 | C20: 571.585 | D20: 3861.115 | E20: 0 | F20: 0 | G20: 0 | H20: 3289.53 | I20: 571.585 | J20: 3861.115 | K20: 11.665 | L20: 0 | M20: 11.665 | N20: 3301.195 | O20: 571.585 | P20: 3861.115 | Q20: 1.051732 | R20: 0 | T20: 1224.825 | U20: 209.97 | V20: 1434.795 | W20: 0 | X20: 0 | Y20: 0 | Z20: 1224.825 | AA20: 209.97 | AB20: 1434.795 | AC20: 1.6773669 | AD20: 177 | AE20: 31 | AF20: 208 | AG20: 0 | AH20: 0 | AI20: 0 | AJ20: 177 | AK20: 31 | AL20: 208 | AM20: -0.053633515
A21: 36404 | B21: 3276.46 | C21: 594.66 | D21: 3871.12 | E21: 0 | F21: 0 | G21: 0 | H21: 3288.12 | I21: 594.66 | J21: 3882.78 | K21: 11.66 | L21: 0 | M21: 11.66 | N21: 3288.12 | O21: 594.66 | P21: 3882.78 | Q21: 1.7604277 | R21: 0 | T21: 1224.3 | U21: 221.54 | V21: 1445.84 | W21: 0 | X21: 0 | Y21: 0 | Z21: 1224.3 | AA21: 221.54 | AB21: 1445.84 | AC21: 1.9298209 | AD21: 176 | AE21: 32 | AF21: 209 | AG21: 0 | AH21: 0 | AI21: 0 | AJ21: 177 | AK21: 32 | AL21: 209 | AM21: -0.014527718
A22: 36434 | B22: 3239.6 | C22: 613.21 | D22: 3864.38 | E22: 0 | F22: 0 | G22: 0 | H22: 3239.6 | I22: 613.21 | J22: 3864.38 | K22: 11.57 | L22: 0 | M22: 11.57 | N22: 3251.17 | O22: 613.21 | P22: 3864.38 | Q22: 2.4352389 | R22: 0 | T22: 1203.28 | U22: 219.83 | V22: 1423.11 | W22: 0 | X22: 0 | Y22: 0 | Z22: 1203.28 | AA22: 219.83 | AB22: 1423.11 | AC22: 1.8325349 | AD22: 176 | AE22: 34 | AF22: 210 | AG22: 0 | AH22: 0 | AI22: 0 | AJ22: 176 | AK22: 34 | AL22: 210 | AM22: 0.052091958
A23: 36465 | B23: 3268.367 | C23: 612.097 | D23: 3880.464 | E23: 0 | F23: 0 | G23: 0 | H23: 3268.367 | I23: 612.097 | J23: 3880.464 | K23: 0 | L23: 0 | M23: 0 | N23: 3279.916 | O23: 612.097 | P23: 3880.464 | Q23: 2.4687968 | R23: 0 | T23: 1212.645 | U23: 219.431 | V23: 1432.076 | W23: 0 | X23: 0 | Y23: 0 | Z23: 1212.645 | AA23: 219.431 | AB23: 1432.076 | AC23: 2.7873573 | AD23: 178 | AE23: 34 | AF23: 212 | AG23: 0 | AH23: 0 | AI23: 0 | AJ23: 178 | AK23: 34 | AL23: 212 | AM23: -0.027583387
... A251: 43405 | B251: 444.04156 | C251: 75.881692 | D251: 519.92325 | E251: 21.233584 | F251: 0 | G251: 21.233584 | H251: 465.27514 | I251: 75.881692 | J251: 541.15684 | K251: 0 | L251: 0 | M251: 0 | N251: 465.27514 | O251: 75.881692 | P251: 541.15684 | Q251: 0.24601731 | R251: 0 | T251: 439.7633 | U251: 75.862974 | V251: 515.62627 | W251: 21.233584 | X251: 0 | Y251: 21.233584 | Z251: 460.99688 | AA251: 75.862974 | AB251: 536.85986 | AC251: 0 | AD251: 0.13294374 | AE251: 0.00058164 | AF251: 0.13352538 | AG251: 0 | AH251: 0 | AI251: 0 | AJ251: 0.13294374 | AK251: 0.00058164 | AL251: 0.13352538 | AM251: 0.0076448
A252: =+'Bcos. Públ.'!A252 -> 43435 | B252: 442.75096 | C252: 72.442606 | D252: 515.19356 | E252: 21.314396 | F252: 0 | G252: 21.314396 | H252: 464.06536 | I252: 72.442606 | J252: 536.50796 | K252: 0 | L252: 0 | M252: 0 | N252: 464.06536 | O252: 72.442606 | P252: 536.50796 | Q252: 0.18144489 | R252: 0 | T252: 438.23066 | U252: 72.429847 | V252: 510.66051 | W252: 21.314396 | X252: 0 | Y252: 21.314396 | Z252: 459.54506 | AA252: 72.429847 | AB252: 531.9749 | AC252: 0 | AD252: 0.1395585 | AE252: 0.00039391 | AF252: =+AE252+AD252 -> 0.13995241 | AG252: 0 | AH252: 0 | AI252: =+AH252+AG252 -> 0 | AJ252: 0.1395585 | AK252: 0.00039391 | AL252: =+AK252+AJ252 -> 0.13995241 | AM252: 0.00560188
A253: =+'Bcos. Públ.'!A253 -> 43467 | B253: 441.56094 | C253: 0 | D253: 441.56094 | E253: 0 | F253: 0 | G253: 0 | H253: 441.56094 | I253: 0 | J253: 441.56094 | K253: 0 | L253: 0 | M253: 0 | N253: 441.56094 | O253: 0 | P253: 441.56094 | Q253: ND | R253: ND | T253: 441.56094 | U253: 0 | V253: 441.56094 | W253: 0 | X253: 0 | Y253: 0 | Z253: 441.56094 | AA253: 0 | AB253: 441.56094 | AC253: ND | AD253: 0 | AE253: 0 | AF253: 0 | AG253: 0 | AH253: 0 | AI253: 0 | AJ253: 0 | AK253: 0 | AL253: 0 | AM253: ND
A254: 43497 | B254: 458.46107 | C254: 67.459012 | D254: 525.92008 | E254: 21.641405 | F254: 0 | G254: 21.641405 | H254: 480.10247 | I254: 67.459012 | J254: 547.56148 | K254: 0 | L254: 0 | M254: 0 | N254: 480.10247 | O254: 67.459012 | P254: 547.56148 | Q254: ND | R254: ND | T254: 454.35415 | U254: 67.452189 | V254: 521.80634 | W254: 21.641405 | X254: 0 | Y254: 21.641405 | Z254: 475.99556 | AA254: 67.452189 | AB254: 543.44774 | AC254: ND | AD254: 0.12578224 | AE254: 0.00020898 | AF254: 0.12599122 | AG254: 0 | AH254: 0 | AI254: 0 | AJ254: 0.12578224 | AK254: 0.00020898 | AL254: 0.12599122 | AM254: ND
A255: 43525 | B255: 462.09808 | C255: 69.054489 | D255: 531.15257 | E255: 21.912785 | F255: 0 | G255: 21.912785 | H255: 484.01086 | I255: 69.054489 | J255: 553.06535 | K255: 0 | L255: 0 | M255: 0 | N255: 484.01086 | O255: 69.054489 | P255: 553.06535 | Q255: ND | R255: ND | T255: 457.43625 | U255: 69.047492 | V255: 526.48375 | W255: 21.912785 | X255: 0 | Y255: 21.912785 | Z255: 479.34904 | AA255: 69.047492 | AB255: 548.39653 | AC255: ND | AD255: 0.13922541 | AE255: 0.00020898 | AF255: 0.13943439 | AG255: 0 | AH255: 0 | AI255: 0 | AJ255: 0.13922541 | AK255: 0.00020898 | AL255: 0.13943439 | AM255: ND
A256: 43556 | B256: 455.26372 | C256: 79.709991 | D256: 534.97371 | E256: 22.057074 | F256: 0 | G256: 22.057074 | H256: 477.32079 | I256: 79.709991 | J256: 557.03078 | K256: 0 | L256: 0 | M256: 0 | N256: 477.32079 | O256: 79.709991 | P256: 557.03078 | Q256: ND | R256: ND | T256: 450.63285 | U256: 79.702681 | V256: 530.33553 | W256: 22.057074 | X256: 0 | Y256: 22.057074 | Z256: 472.68992 | AA256: 79.702681 | AB256: 552.3926 | AC256: ND | AD256: 0.13238244 | AE256: 0.00020898 | AF256: 0.13259142 | AG256: 0 | AH256: 0 | AI256: 0 | AJ256: 0.13238244 | AK256: 0.00020898 | AL256: 0.13259142 | AM256: ND
A257: 43586 | B257: 458.39217 | C257: 79.438577 | D257: 537.83074 | E257: 22.165939 | F257: 0 | G257: 22.165939 | H257: 480.55811 | I257: 79.438577 | J257: 559.99668 | K257: 0 | L257: 0 | M257: 0 | N257: 480.55811 | O257: 79.438577 | P257: 559.99668 | Q257: ND | R257: ND | T257: 453.56086 | U257: 79.43121 | V257: 532.99207 | W257: 22.165939 | X257: 0 | Y257: 22.165939 | Z257: 475.7268 | AA257: 79.43121 | AB257: 555.15801 | AC257: ND | AD257: 0.13705056 | AE257: 0.00020898 | AF257: 0.13725954 | AG257: 0 | AH257: 0 | AI257: 0 | AJ257: 0.13705056 | AK257: 0.00020898 | AL257: 0.13725954 | AM257: ND
A258: 43617 | B258: 455.28596 | C258: 81.141587 | D258: 536.42755 | E258: 22.264275 | F258: 0 | G258: 22.264275 | H258: 477.55024 | I258: 81.141587 | J258: 558.69182 | K258: 0 | L258: 0 | M258: 0 | N258: 477.55024 | O258: 81.141587 | P258: 558.69182 | Q258: ND | R258: ND | T258: 448.97404 | U258: 81.134235 | V258: 530.10827 | W258: 22.264275 | X258: 0 | Y258: 22.264275 | Z258: 471.23831 | AA258: 81.134235 | AB258: 552.37254 | AC258: ND | AD258: 0.17940783 | AE258: 0.00020898 | AF258: 0.17961681 | AG258: 0 | AH258: 0 | AI258: 0 | AJ258: 0.17940783 | AK258: 0.00020898 | AL258: 0.17961681 | AM258: ND
A259: 43647 | B259: 452.70112 | C259: 82.998551 | D259: 535.69967 | E259: 22.296369 | F259: 0 | G259: 22.296369 | H259: 474.99749 | I259: 82.998551 | J259: 557.99604 | K259: 0 | L259: 0 | M259: 0 | N259: 474.99749 | O259: 82.998551 | P259: 557.99604 | Q259: ND | R259: ND | T259: 446.39657 | U259: 82.991372 | V259: 529.38795 | W259: 22.296369 | X259: 0 | Y259: 22.296369 | Z259: 468.69294 | AA259: 82.991372 | AB259: 551.68432 | AC259: ND | AD259: 0.18353837 | AE259: 0.00020898 | AF259: 0.18374735 | AG259: 0 | AH259: 0 | AI259: 0 | AJ259: 0.18353837 | AK259: 0.00020898 | AL259: 0.18374735 | AM259: ND
A260: 43678 | B260: 455.00827 | C260: 86.277769 | D260: 541.28604 | E260: 22.471047 | F260: 0 | G260: 22.471047 | H260: 477.47932 | I260: 86.277769 | J260: 563.75709 | K260: 0 | L260: 0 | M260: 0 | N260: 477.47932 | O260: 86.277769 | P260: 563.75709 | Q260: ND | R260: ND | T260: 447.74821 | U260: 86.270112 | V260: 534.01833 | W260: 22.471047 | X260: 0 | Y260: 22.471047 | Z260: 470.21926 | AA260: 86.270112 | AB260: 556.48937 | AC260: ND | AD260: 0.19813491 | AE260: 0.00020898 | AF260: 0.19834389 | AG260: 0 | AH260: 0 | AI260: 0 | AJ260: 0.19813491 | AK260: 0.00020898 | AL260: 0.19834389 | AM260: ND
A261: 43709 | B261: 468.13799 | C261: 91.766621 | D261: 559.90461 | E261: 22.672823 | F261: 0 | G261: 22.672823 | H261: 490.81082 | I261: 91.766621 | J261: 582.57744 | K261: 0 | L261: 0 | M261: 0 | N261: 490.81082 | O261: 91.766621 | P261: 582.57744 | Q261: ND | R261: ND | T261: 461.25758 | U261: 91.758901 | V261: 553.01648 | W261: 22.672823 | X261: 0 | Y261: 22.672823 | Z261: 483.9304 | AA261: 91.758901 | AB261: 575.6893 | AC261: ND | AD261: 0.18626422 | AE261: 0.00020898 | AF261: 0.1864732 | AG261: 0 | AH261: 0 | AI261: 0 | AJ261: 0.18626422 | AK261: 0.00020898 | AL261: 0.1864732 | AM261: ND
A262: 43739 | B262: 491.3816 | C262: 87.288885 | D262: 578.67049 | E262: 22.81447 | F262: 0 | G262: 22.81447 | H262: 514.19607 | I262: 87.288885 | J262: 601.48496 | K262: 0 | L262: 0 | M262: 0 | N262: 514.19607 | O262: 87.288885 | P262: 601.48496 | Q262: ND | R262: ND | T262: 483.66325 | U262: 87.281065 | V262: 570.94432 | W262: 22.81447 | X262: 0 | Y262: 22.81447 | Z262: 506.47772 | AA262: 87.281065 | AB262: 593.75879 | AC262: ND | AD262: 0.20628477 | AE262: 0.00020898 | AF262: 0.20649375 | AG262: 0 | AH262: 0 | AI262: 0 | AJ262: 0.20628477 | AK262: 0.00020898 | AL262: 0.20649375 | AM262: ND
A263: 43770 | B263: 506.66592 | C263: 88.777222 | D263: 595.44314 | E263: 22.980035 | F263: 0 | G263: 22.980035 | H263: 529.64596 | I263: 88.777222 | J263: 618.42318 | K263: 0 | L263: 0 | M263: 0 | N263: 529.64596 | O263: 88.777222 | P263: 618.42318 | Q263: ND | R263: ND | T263: 499.02056 | U263: 88.769314 | V263: 587.78988 | W263: 22.980035 | X263: 0 | Y263: 22.980035 | Z263: 522.0006 | AA263: 88.769314 | AB263: 610.76991 | AC263: ND | AD263: 0.20204439 | AE263: 0.00020898 | AF263: 0.20225337 | AG263: 0 | AH263: 0 | AI263: 0 | AJ263: 0.20204439 | AK263: 0.00020898 | AL263: 0.20225337 | AM263: ND
A264: 43800 | B264: 509.72208 | C264: 85.890201 | D264: 595.61228 | E264: 23.104974 | F264: 0 | G264: 23.104974 | H264: 532.82706 | I264: 85.890201 | J264: 618.71726 | K264: 0 | L264: 0 | M264: 0 | N264: 532.82706 | O264: 85.890201 | P264: 618.71726 | Q264: ND | R264: ND | T264: 503.25064 | U264: 85.890201 | V264: 589.14084 | W264: 23.104974 | X264: 0 | Y264: 23.104974 | Z264: 526.35561 | AA264: 85.890201 | AB264: 612.24582 | AC264: ND | AD264: 0.17332985 | AE264: 0 | AF264: 0.17332985 | AG264: 0 | AH264: 0 | AI264: 0 | AJ264: 0.17332985 | AK264: 0 | AL264: 0.17332985 | AM264: ND
A265: 43831 | B265: 518.47651 | C265: 87.045043 | D265: 605.52156 | E265: 23.124638 | F265: 0 | G265: 23.124638 | H265: 541.60115 | I265: 87.045043 | J265: 628.64619 | K265: 0 | L265: 0 | M265: 0 | N265: 541.60115 | O265: 87.045043 | P265: 628.64619 | Q265: ND | R265: ND | T265: 511.57943 | U265: 87.045043 | V265: 598.62448 | W265: 23.124638 | X265: 0 | Y265: 23.124638 | Z265: 534.70407 | AA265: 87.045043 | AB265: 621.74912 | AC265: ND | AD265: 0.18377015 | AE265: 0 | AF265: 0.18377015 | AG265: 0 | AH265: 0 | AI265: 0 | AJ265: 0.18377015 | AK265: 0 | AL265: 0.18377015 | AM265: ND
... A324: 45627 | B324: 597.39978 | C324: 147.83318 | D324: 745.23295 | E324: 32.651728 | F324: 0 | G324: 32.651728 | H324: 630.0515 | I324: 147.83318 | J324: 777.88468 | K324: 0 | L324: 0 | M324: 0 | N324: 630.0515 | O324: 147.83318 | P324: 777.88468 | Q324: ND | R324: ND | T324: 590.17873 | U324: 146.8085 | V324: 736.98723 | W324: 32.651728 | X324: 0 | Y324: 32.651728 | Z324: 622.83046 | AA324: 146.8085 | AB324: 769.63896 | AC324: ND | AD324: 0.16386889 | AE324: 0.02325321 | AF324: 0.1871221 | AG324: 0 | AH324: 0 | AI324: 0 | AJ324: 0.16386889 | AK324: 0.02325321 | AL324: 0.1871221 | AM324: ND
A325: 45658 | B325: =+'[1]Coop.'!B325*[2]TC!$B316 -> 602.34447 | C325: =+'[1]Coop.'!C325*[2]TC!$B316 -> 147.7927 | D325: =+'[1]Coop.'!D325*[2]TC!$B316 -> 750.13716 | E325: =+'[1]Coop.'!E325*[2]TC!$B316 -> 32.777024 | F325: =+'[1]Coop.'!F325*[2]TC!$B316 -> 0 | G325: =+'[1]Coop.'!G325*[2]TC!$B316 -> 32.777024 | H325: =+'[1]Coop.'!H325*[2]TC!$B316 -> 635.12149 | I325: =+'[1]Coop.'!I325*[2]TC!$B316 -> 147.7927 | ... P325: =+'[1]Coop.'!P325*[2]TC!$B316 -> 782.91419 | Q325: ND | R325: ND | T325: =+'[1]Coop.'!T325*[2]TC!$B316 -> 596.39685 | U325: =+'[1]Coop.'!U325*[2]TC!$B316 -> 145.90683 | V325: =+'[1]Coop.'!V325*[2]TC!$B316 -> 742.30369 | W325: =+'[1]Coop.'!W325*[2]TC!$B316 -> 32.777024 | X325: =+'[1]Coop.'!X325*[2]TC!$B316 -> 0 | Y325: =+'[1]Coop.'!Y325*[2]TC!$B316 -> 32.777024 | Z325: =+'[1]Coop.'!Z325*[2]TC!$B316 -> 629.17388 | AA325: =+'[1]Coop.'!AA325*[2]TC!$B316 -> 145.90683 | AB325: =+'[1]Coop.'!AB325*[2]TC!$B316 -> 775.08071 | AC325: ND | AD325: =+'[1]Coop.'!AD325 -> 0.13792534 | AE325: =+'[1]Coop.'!AE325 -> 0.04373317 | AF325: =+'[1]Coop.'!AF325 -> 0.18165851 | AG325: =+'[1]Coop.'!AG325 -> 0 | AH325: =+'[1]Coop.'!AH325 -> 0 | AI325: =+'[1]Coop.'!AI325 -> 0 | AJ325: =+'[1]Coop.'!AJ325 -> 0.13792534 | AK325: =+'[1]Coop.'!AK325 -> 0.04373317 | AL325: =+'[1]Coop.'!AL325 -> 0.18165851 | AM325: ND
A326: 45689 | B326: =+'[1]Coop.'!B326*[2]TC!$B317 -> 617.31179 | C326: =+'[1]Coop.'!C326*[2]TC!$B317 -> 146.05647 | D326: =+'[1]Coop.'!D326*[2]TC!$B317 -> 763.36826 | E326: =+'[1]Coop.'!E326*[2]TC!$B317 -> 33.103854 | F326: =+'[1]Coop.'!F326*[2]TC!$B317 -> 0 | G326: =+'[1]Coop.'!G326*[2]TC!$B317 -> 33.103854 | H326: =+'[1]Coop.'!H326*[2]TC!$B317 -> 650.41565 | I326: =+'[1]Coop.'!I326*[2]TC!$B317 -> 146.05647 | ... P326: =+'[1]Coop.'!P326*[2]TC!$B317 -> 796.47211 | Q326: ND | R326: ND | T326: =+'[1]Coop.'!T326*[2]TC!$B317 -> 610.47992 | U326: =+'[1]Coop.'!U326*[2]TC!$B317 -> 145.20264 | V326: =+'[1]Coop.'!V326*[2]TC!$B317 -> 755.68256 | W326: =+'[1]Coop.'!W326*[2]TC!$B317 -> 33.103854 | X326: =+'[1]Coop.'!X326*[2]TC!$B317 -> 0 | Y326: =+'[1]Coop.'!Y326*[2]TC!$B317 -> 33.103854 | Z326: =+'[1]Coop.'!Z326*[2]TC!$B317 -> 643.58377 | AA326: =+'[1]Coop.'!AA326*[2]TC!$B317 -> 145.20264 | AB326: =+'[1]Coop.'!AB326*[2]TC!$B317 -> 788.78641 | AC326: ND | AD326: =+'[1]Coop.'!AD326 -> 0.16042907 | AE326: =+'[1]Coop.'!AE326 -> 0.02004996 | AF326: =+'[1]Coop.'!AF326 -> 0.18047903 | AG326: =+'[1]Coop.'!AG326 -> 0 | AH326: =+'[1]Coop.'!AH326 -> 0 | AI326: =+'[1]Coop.'!AI326 -> 0 | AJ326: =+'[1]Coop.'!AJ326 -> 0.16042907 | AK326: =+'[1]Coop.'!AK326 -> 0.02004996 | AL326: =+'[1]Coop.'!AL326 -> 0.18047903 | AM326: ND
A327: 45717 | B327: =+'[1]Coop.'!B327*[2]TC!$B318 -> 613.47982 | C327: =+'[1]Coop.'!C327*[2]TC!$B318 -> 142.76092 | D327: =+'[1]Coop.'!D327*[2]TC!$B318 -> 756.24074 | E327: =+'[1]Coop.'!E327*[2]TC!$B318 -> 33.387844 | F327: =+'[1]Coop.'!F327*[2]TC!$B318 -> 0 | G327: =+'[1]Coop.'!G327*[2]TC!$B318 -> 33.387844 | H327: =+'[1]Coop.'!H327*[2]TC!$B318 -> 646.86767 | I327: =+'[1]Coop.'!I327*[2]TC!$B318 -> 142.76092 | ... P327: =+'[1]Coop.'!P327*[2]TC!$B318 -> 789.62858 | Q327: ND | R327: ND | T327: =+'[1]Coop.'!T327*[2]TC!$B318 -> 606.29793 | U327: =+'[1]Coop.'!U327*[2]TC!$B318 -> 140.99661 | V327: =+'[1]Coop.'!V327*[2]TC!$B318 -> 747.29454 | W327: =+'[1]Coop.'!W327*[2]TC!$B318 -> 33.387844 | X327: =+'[1]Coop.'!X327*[2]TC!$B318 -> 0 | Y327: =+'[1]Coop.'!Y327*[2]TC!$B318 -> 33.387844 | Z327: =+'[1]Coop.'!Z327*[2]TC!$B318 -> 639.68578 | AA327: =+'[1]Coop.'!AA327*[2]TC!$B318 -> 140.99661 | AB327: =+'[1]Coop.'!AB327*[2]TC!$B318 -> 780.68238 | AC327: ND | AD327: =+'[1]Coop.'!AD327 -> 0.17048189 | AE327: =+'[1]Coop.'!AE327 -> 0.04188074 | AF327: =+'[1]Coop.'!AF327 -> 0.21236263 | AG327: =+'[1]Coop.'!AG327 -> 0 | AH327: =+'[1]Coop.'!AH327 -> 0 | AI327: =+'[1]Coop.'!AI327 -> 0 | AJ327: =+'[1]Coop.'!AJ327 -> 0.17048189 | AK327: =+'[1]Coop.'!AK327 -> 0.04188074 | AL327: =+'[1]Coop.'!AL327 -> 0.21236263 | AM327: ND
A328: 45748 | B328: 603.66349 | C328: 150.78302 | D328: 754.4465 | E328: 33.584498 | F328: 0 | G328: 33.584498 | H328: 637.24798 | I328: 150.78302 | J328: 788.031 | K328: 0 | L328: 0 | M328: 0 | N328: 637.24798 | O328: 150.78302 | P328: 788.031 | Q328: ND | R328: ND | T328: 595.82709 | U328: 149.96598 | V328: 745.79307 | W328: 33.584498 | X328: 0 | Y328: 33.584498 | Z328: 629.41159 | AA328: 149.96598 | AB328: 779.37757 | AC328: ND | AD328: 0.18680761 | AE328: 0.01947704 | AF328: 0.20628465 | AG328: 0 | AH328: 0 | AI328: 0 | AJ328: 0.18680761 | AK328: 0.01947704 | AL328: 0.20628465 | AM328: ND
A329: 45778 | B329: 607.68018 | C329: 142.37913 | D329: 750.05931 | E329: 33.720423 | F329: 0 | G329: 33.720423 | H329: 641.4006 | I329: 142.37913 | J329: 783.77974 | K329: 0 | L329: 0 | M329: 0 | N329: 641.4006 | O329: 142.37913 | P329: 783.77974 | Q329: ND | R329: ND | T329: 599.80201 | U329: 141.57934 | V329: 741.38135 | W329: 33.720423 | X329: 0 | Y329: 33.720423 | Z329: 633.52243 | AA329: 141.57934 | AB329: 775.10177 | AC329: ND | AD329: 0.18902463 | AE329: 0.01918981 | AF329: 0.20821444 | AG329: 0 | AH329: 0 | AI329: 0 | AJ329: 0.18902463 | AK329: 0.01918981 | AL329: 0.20821444 | AM329: ND
A330: 45809 | B330: 591.46212 | C330: 148.23733 | D330: 739.69945 | E330: 33.782694 | F330: 0 | G330: 33.782694 | H330: 625.24481 | I330: 148.23733 | J330: 773.48215 | K330: 0 | L330: 0 | M330: 0 | N330: 625.24481 | O330: 148.23733 | P330: 773.48215 | Q330: ND | R330: ND | T330: 585.20124 | U330: 146.48856 | V330: 731.6898 | W330: 33.782694 | X330: 0 | Y330: 33.782694 | Z330: 618.98394 | AA330: 146.48856 | AB330: 765.47249 | AC330: ND | AD330: 0.15831088 | AE330: 0.04421909 | AF330: 0.20252997 | AG330: 0 | AH330: 0 | AI330: 0 | AJ330: 0.15831088 | AK330: 0.04421909 | AL330: 0.20252997 | AM330: ND
A331: 45839 | B331: 594.26343 | C331: 146.06235 | D331: 740.32578 | E331: 33.609612 | F331: 0 | G331: 33.609612 | H331: 627.87305 | I331: 146.06235 | J331: 773.9354 | K331: 0 | L331: 0 | M331: 0 | N331: 627.87305 | O331: 146.06235 | P331: 773.9354 | Q331: ND | R331: ND | T331: 588.25861 | U331: 144.32382 | V331: 732.58243 | W331: 33.609612 | X331: 0 | Y331: 33.609612 | Z331: 621.86822 | AA331: 144.32382 | AB331: 766.19204 | AC331: ND | AD331: 0.14938856 | AE331: 0.04325134 | AF331: 0.1926399 | AG331: 0 | AH331: 0 | AI331: 0 | AJ331: 0.14938856 | AK331: 0.04325134 | AL331: 0.1926399 | AM331: ND
A332: 45870 | B332: 584.53523 | C332: 145.83007 | D332: 730.3653 | E332: 33.633122 | F332: 0 | G332: 33.633122 | H332: 618.16835 | I332: 145.83007 | J332: 763.99842 | K332: 0 | L332: 0 | M332: 0 | N332: 618.16835 | O332: 145.83007 | P332: 763.99842 | Q332: ND | R332: ND | T332: 579.10498 | U332: 144.03265 | V332: 723.13762 | W332: 33.633122 | X332: 0 | Y332: 33.633122 | Z332: 612.7381 | AA332: 144.03265 | AB332: 756.77075 | AC332: ND | AD332: 0.13577316 | AE332: 0.04494131 | AF332: 0.18071447 | AG332: 0 | AH332: 0 | AI332: 0 | AJ332: 0.13577316 | AK332: 0.04494131 | AL332: 0.18071447 | AM332: ND
A333: 45901 | B333: 583.92565 | C333: 146.43703 | D333: 730.36269 | E333: 33.655312 | F333: 0 | G333: 33.655312 | H333: 617.58096 | I333: 146.43703 | J333: 764.018 | K333: 0 | L333: 0 | M333: 0 | N333: 617.58096 | O333: 146.43703 | P333: 764.018 | Q333: ND | R333: ND | T333: 578.37892 | U333: 144.73647 | V333: 723.11539 | W333: 33.655312 | X333: 0 | Y333: 33.655312 | Z333: 612.03423 | AA333: 144.73647 | AB333: 756.7707 | AC333: ND | AD333: 0.13920771 | AE333: 0.04267951 | AF333: 0.18188722 | AG333: 0 | AH333: 0 | AI333: 0 | AJ333: 0.13920771 | AK333: 0.04267951 | AL333: 0.18188722 | AM333: ND
A335: (1) La variación del saldo contable de los créditos brutos se encuentra influida por la transferencia de créditos a cuentas de orden (créditos castigados) de acuerdo a lo establecido por la normativa. Por este motivo se presenta la variación mensual de los créditos castigados, elemento que, para evaluar la evolución del crédito desde una perspectiva económica, debería sumarse al saldo de los créditos brutos.
A336: (2) Incluye las cooperativas de intermediación financiera en actividad en cada fecha, con excepción de la cooperativa Caycu (suspendida en agosto de 2002), que se incluye hasta diciembre de 2002 inclusive.
A337: (3) Corresponde a los grupos N° 14010 (Préstamos), 14020 (Arrendamientos Financieros), 14060 (Ingresos Percibidos No Devengados), 14070 (Grupos de Ahorro Previo), 14080 (Deudores por Productos Financieros Devengados), 16010 (Créditos Vencidos - Sector No Público) y 16080 (Deudores por Productos Financieros) del Plan de Cuentas para EIF, excepto las cuentas de deudores por créditos documentarios diferidos y domésticos diferidos (185000 y 189001 respectivamente), las cuentas de operaciones a liquidar (369080), sector público (245000 y 393000), sector financiero (407000), y a partir de marzo de 2005 los préstamos garantizados con prenda de depósitos (509000).
A338: Nuevo Plan de cuenta: 1.4.2.1 Créditos vigentes + 1.4.2.2 Créditos vigentes (deudores por intereses)+ 1.4.2.4 Colocacion vencida + 1.4.2.5 Colocación vencida (deudores por intereses) + 1.4.2.7 Créditos en gestión + 1.4.2.8 Créditos en gestión (deudores por intereses) +1.4.2.10 Créditos morosos + 1.4.2.11 Créditos morosos (deudores por intereses)
A339: (4) Incluye a las cuentas de los grupos N° 14050 y 16040 (Créditos Vigentes y Vencidos - Sector Público Nacional y No Nacional), 14080 y 16080 (Créditos Vigentes y Vencidos - Deudores por Productos Financieros Devengados) que corresponden al sector público nacional, excepto las cuentas de operaciones a liquidar (227000, 229000 y 381000) y deudores por créditos domésticos diferidos (221000). Incluye Estado, organismos de seguridad social, gobiernos departamentales y otros integrantes del sector público.
A340: Nuevo Plan de cuenta: 1.4.3.1 Créditos vigentes + 1.4.3.2 Créditos vigentes (deudores por intereses)+ 1.4.3.4 Colocación vencida + 1.4.3.5 Colocación vencida (deudores por intereses)+ 1.4.3.7 Créditos en gestión + 1.4.3.8 Créditos en gestión (deudores por intereses) +1.4.3.10 Créditos morosos + 1.4.3.11 Créditos morosos (deudores por intereses).
A341: (5) Incluye sector privado no residente y sector público no nacional.
A343: Notas:
A344: Los meses que aparecen subrayados incluyen comentarios explicativos y vínculo a la hoja con detalle de todos los comentarios.
A345: Diferencias en las columnas de Total se deben a redondeo de las cifras.

Sheet C. Financ.
A1: Banco Central del Uruguay | T1: Banco Central del Uruguay
A2: Superintendencia de Servicios Financieros | T2: Superintendencia de Instituciones de Intermediación Financiera
M3: Volver al Índice | AH3: Volver al Índice
B4: CRÉDITOS BRUTOS SECTOR NO FINANCIERO (SNF) (1) | T4: CRÉDITOS BRUTOS SNF (1) - ANEXO RESIDENTES POR MONEDAS
B5: CASAS FINANCIERAS (2) | T5: CASAS FINANCIERAS (2)
B6: (Crédito Total en millones de pesos) | T6: (Créditos en MN en millones de pesos y en ME en millones de dólares)
B8: TOTAL (MN + ME) en millones de pesos
B9: RESIDENTES | K9: NO RESIDENTES (5) | N9: TOTAL | Q9: Variación mensual | T9: MONEDA NACIONAL en millones de pesos | AD9: MONEDA EXTRANJERA en millones de dólares
A10: Mes | B10: SECTOR PRIVADO (3) | E10: SECTOR PÚBLICO (4) | H10: TOTAL (S.Priv. + S.Públ) | Q10: Castigados (1) | T10: SECTOR PRIVADO (3) | W10: SECTOR PÚBLICO (4) | Z10: TOTAL (S.Priv. + S.Públ) | AC10: Variac. mens. | AD10: SECTOR PRIVADO (3) | AG10: SECTOR PÚBLICO (4) | AJ10: TOTAL (S.Priv. + S.Públ) | AM10: Variac. mens.
B11: Vigentes | C11: Vencidos | D11: Total | E11: Vigentes | F11: Vencidos | G11: Total | H11: Vigentes | I11: Vencidos | J11: Total | K11: Vigentes | L11: Vencidos | M11: Total | N11: Vigentes | O11: Vencidos | P11: Total | Q11: Resid. | R11: No resid. | T11: Vigentes | U11: Vencidos | V11: Total | W11: Vigentes | X11: Vencidos | Y11: Total | Z11: Vigentes | AA11: Vencidos | AB11: Total | AC11: Castigados (1) | AD11: Vigentes | AE11: Vencidos | AF11: Total | AG11: Vigentes | AH11: Vencidos | AI11: Total | AJ11: Vigentes | AK11: Vencidos | AL11: Total | AM11: Castigados (1)
A12: 36130 | B12: 356.961 | C12: 129.804 | D12: 486.765 | E12: 0 | F12: 0 | G12: 0 | H12: 356.961 | I12: 129.804 | J12: 486.765 | K12: 1081.7 | L12: 32.451 | M12: 1114.151 | N12: 1438.661 | O12: 162.255 | P12: 1600.916 | Q12: -6.6973455e-05 | R12: 0 | T12: 64.902 | U12: 32.451 | V12: 97.353 | W12: 0 | X12: 0 | Y12: 0 | Z12: 64.902 | AA12: 32.451 | AB12: 97.353 | AC12: 0 | AD12: 27 | AE12: 9 | AF12: 36 | AG12: 0 | AH12: 0 | AI12: 0 | AJ12: 27 | AK12: 9 | AL12: 36 | AM12: -6.1915e-06
A13: 36161 | B13: 383.95 | C13: 54.85 | D13: 438.8 | E13: 0 | F13: 0 | G13: 0 | H13: 383.95 | I13: 54.85 | J13: 438.8 | K13: 1118.94 | L13: 10.97 | M13: 1129.91 | N13: 1502.89 | O13: 65.82 | P13: 1568.71 | Q13: 27.91996 | R13: 22.793918 | T13: 65.82 | U13: 21.94 | V13: 87.76 | W13: 0 | X13: 0 | Y13: 0 | Z13: 65.82 | AA13: 21.94 | AB13: 87.76 | AC13: 0 | AD13: 29 | AE13: 3 | AF13: 32 | AG13: 0 | AH13: 0 | AI13: 0 | AJ13: 29 | AK13: 3 | AL13: 32 | AM13: 2.5451194
A14: 36192 | B14: 373.49 | C14: 54.925 | D14: 428.415 | E14: 0 | F14: 0 | G14: 0 | H14: 373.49 | I14: 54.925 | J14: 428.415 | K14: 1120.47 | L14: 21.97 | M14: 1142.44 | N14: 1493.96 | O14: 76.895 | P14: 1570.855 | Q14: 0.24616834 | R14: 0.046795133 | T14: 65.91 | U14: 21.97 | V14: 87.88 | W14: 0 | X14: 0 | Y14: 0 | Z14: 65.91 | AA14: 21.97 | AB14: 87.88 | AC14: 0.25166721 | AD14: 28 | AE14: 3 | AF14: 30 | AG14: 0 | AH14: 0 | AI14: 0 | AJ14: 28 | AK14: 3 | AL14: 30 | AM14: -0.00050058
A15: 36220 | B15: 377.23 | C15: 44.38 | D15: 432.705 | E15: 0 | F15: 0 | G15: 0 | H15: 377.23 | I15: 44.38 | J15: 432.705 | K15: 1098.405 | L15: 22.19 | M15: 1109.5 | N15: 1475.635 | O15: 66.57 | P15: 1542.205 | Q15: 54.626126 | R15: 1.2858152 | T15: 66.57 | U15: 22.19 | V15: 88.76 | W15: 0 | X15: 0 | Y15: 0 | Z15: 66.57 | AA15: 22.19 | AB15: 88.76 | AC15: 0.85562597 | AD15: 28 | AE15: 2 | AF15: 30 | AG15: 0 | AH15: 0 | AI15: 0 | AJ15: 28 | AK15: 2 | AL15: 30 | AM15: 4.8463723
A16: 36251 | B16: 390.005 | C16: 44.572 | D16: 445.72 | E16: 0 | F16: 0 | G16: 0 | H16: 390.005 | I16: 44.572 | J16: 445.72 | K16: 1080.871 | L16: 11.143 | M16: 1092.014 | N16: 1482.019 | O16: 55.715 | P16: 1537.734 | Q16: 0.43342826 | R16: 0.033429001 | T16: 66.858 | U16: 22.286 | V16: 89.144 | W16: 0 | X16: 0 | Y16: 0 | Z16: 66.858 | AA16: 22.286 | AB16: 89.144 | AC16: 0.47066866 | AD16: 29 | AE16: 2 | AF16: 31 | AG16: 0 | AH16: 0 | AI16: 0 | AJ16: 29 | AK16: 2 | AL16: 31 | AM16: -0.0033420444
A17: 36281 | B17: 414.141 | C17: 44.772 | D17: 458.913 | E17: 0 | F17: 0 | G17: 0 | H17: 414.141 | I17: 44.772 | J17: 458.913 | K17: 1085.721 | L17: 11.193 | M17: 1096.914 | N17: 1488.669 | O17: 67.158 | P17: 1555.827 | Q17: 2.166757 | R17: 0.15380316 | T17: 67.158 | U17: 22.386 | V17: 89.544 | W17: 0 | X17: 0 | Y17: 0 | Z17: 67.158 | AA17: 22.386 | AB17: 89.544 | AC17: 0.5801443 | AD17: 30 | AE17: 2 | AF17: 32 | AG17: 0 | AH17: 0 | AI17: 0 | AJ17: 30 | AK17: 2 | AL17: 32 | AM17: 0.14175044
A18: 36312 | B18: 443.469 | C18: 45.484 | D18: 488.953 | E18: 0 | F18: 0 | G18: 0 | H18: 443.469 | I18: 45.484 | J18: 488.953 | K18: 1034.761 | L18: 22.742 | M18: 1057.503 | N18: 1466.859 | O18: 68.226 | P18: 1535.085 | Q18: 0.59491502 | R18: -0.00068765099 | T18: 68.226 | U18: 22.742 | V18: 90.968 | W18: 0 | X18: 0 | Y18: 0 | Z18: 68.226 | AA18: 22.742 | AB18: 90.968 | AC18: 0.4815822 | AD18: 32 | AE18: 2 | AF18: 34 | AG18: 0 | AH18: 0 | AI18: 0 | AJ18: 32 | AK18: 2 | AL18: 34 | AM18: 0.0099668299
A19: 36342 | B19: 460 | C19: 46 | D19: 506 | E19: 0 | F19: 0 | G19: 0 | H19: 460 | I19: 46 | J19: 506 | K19: 1069.5 | L19: 23 | M19: 1092.5 | N19: 1529.5 | O19: 69 | P19: 1598.5 | Q19: 0.63704171 | R19: 0.074768973 | T19: 69 | U19: 23 | V19: 92 | W19: 0 | X19: 0 | Y19: 0 | Z19: 69 | AA19: 23 | AB19: 92 | AC19: 0.64008313 | AD19: 33 | AE19: 2 | AF19: 35 | AG19: 0 | AH19: 0 | AI19: 0 | AJ19: 33 | AK19: 2 | AL19: 35 | AM19: -0.0002644709
A20: 36373 | B20: 466.6 | C20: 46.66 | D20: 524.925 | E20: 0 | F20: 0 | G20: 0 | H20: 466.6 | I20: 46.66 | J20: 524.925 | K20: 1166.5 | L20: 11.665 | M20: 1178.165 | N20: 1633.1 | O20: 58.325 | P20: 1691.425 | Q20: 0.51406751 | R20: 0.046888811 | T20: 69.99 | U20: 23.33 | V20: 104.985 | W20: 0 | X20: 0 | Y20: 0 | Z20: 69.99 | AA20: 23.33 | AB20: 104.985 | AC20: 0.51675822 | AD20: 34 | AE20: 2 | AF20: 36 | AG20: 0 | AH20: 0 | AI20: 0 | AJ20: 34 | AK20: 2 | AL20: 36 | AM20: -0.0002306652
A21: 36404 | B21: 513.04 | C21: 46.64 | D21: 559.68 | E21: 0 | F21: 0 | G21: 0 | H21: 513.04 | I21: 46.64 | J21: 559.68 | K21: 1177.66 | L21: 11.66 | M21: 1177.66 | N21: 1679.04 | O21: 58.3 | P21: 1749 | Q21: 0.67086127 | R21: 0.075150687 | T21: 69.96 | U21: 23.32 | V21: 104.94 | W21: 0 | X21: 0 | Y21: 0 | Z21: 69.96 | AA21: 23.32 | AB21: 104.94 | AC21: 0.59713937 | AD21: 38 | AE21: 2 | AF21: 40 | AG21: 0 | AH21: 0 | AI21: 0 | AJ21: 38 | AK21: 2 | AL21: 40 | AM21: 0.0063226331
A22: 36434 | B22: 497.51 | C22: 57.85 | D22: 555.36 | E22: 0 | F22: 0 | G22: 0 | H22: 497.51 | I22: 57.85 | J22: 555.36 | K22: 1295.84 | L22: 23.14 | M22: 1318.98 | N22: 1804.92 | O22: 80.99 | P22: 1874.34 | Q22: 0.64258916 | R22: -0.003631101 | T22: 80.99 | U22: 23.14 | V22: 104.13 | W22: 0 | X22: 0 | Y22: 0 | Z22: 80.99 | AA22: 23.14 | AB22: 104.13 | AC22: 0.6451536 | AD22: 37 | AE22: 2 | AF22: 39 | AG22: 0 | AH22: 0 | AI22: 0 | AJ22: 37 | AK22: 2 | AL22: 39 | AM22: -0.0002216453
A23: 36465 | B23: 485.058 | C23: 57.745 | D23: 542.803 | E23: 0 | F23: 0 | G23: 0 | H23: 485.058 | I23: 57.745 | J23: 542.803 | K23: 1432.076 | L23: 23.098 | M23: 1466.723 | N23: 1928.683 | O23: 80.843 | P23: 1997.977 | Q23: 0.79791312 | R23: -0.0027091817 | T23: 80.843 | U23: 23.098 | V23: 115.49 | W23: 0 | X23: 0 | Y23: 0 | Z23: 80.843 | AA23: 23.098 | AB23: 115.49 | AC23: 0.99640357 | AD23: 35 | AE23: 2 | AF23: 37 | AG23: 0 | AH23: 0 | AI23: 0 | AJ23: 35 | AK23: 2 | AL23: 37 | AM23: -0.017186808
... A251: 43405 | B251: 18.426601 | C251: 21.079191 | D251: 39.505792 | E251: 12.982416 | F251: 0 | G251: 12.982416 | H251: 31.409018 | I251: 21.079191 | J251: 52.488208 | K251: 0 | L251: 0 | M251: 0 | N251: 31.409018 | O251: 21.079191 | P251: 52.488208 | Q251: 0 | R251: -6.4362005e-09 | T251: 0 | U251: 0.21 | V251: 0.21 | W251: 12.982416 | X251: 0 | Y251: 12.982416 | Z251: 12.982416 | AA251: 0.21 | AB251: 13.192416 | AC251: 0 | AD251: 0.57259257 | AE251: 0.64849416 | AF251: 1.2210867 | AG251: 0 | AH251: 0 | AI251: 0 | AJ251: 0.57259257 | AK251: 0.64849416 | AL251: 1.2210867 | AM251: 0
A252: =+'Bcos. Públ.'!A252 -> 43435 | B252: 3.3357554 | C252: 1.3108389 | D252: 4.6465943 | E252: 13.110682 | F252: 0 | G252: 13.110682 | H252: 16.446438 | I252: 1.3108389 | J252: 17.757277 | K252: 0 | L252: 0 | M252: 0 | N252: 16.446438 | O252: 1.3108389 | P252: 17.757277 | Q252: 7.402786 | R252: 6.4780005e-09 | T252: 0 | U252: 0.21 | V252: 0.21 | W252: 13.110682 | X252: 0 | Y252: 13.110682 | Z252: 13.110682 | AA252: 0.21 | AB252: 13.320682 | AC252: 0 | AD252: 0.1029872 | AE252: 0.033987 | AF252: =+AE252+AD252 -> 0.1369742 | AG252: 0 | AH252: 0 | AI252: =+AH252+AG252 -> 0 | AJ252: 0.1029872 | AK252: 0.033987 | AL252: =+AK252+AJ252 -> 0.1369742 | AM252: 0.22855159
A253: =+'Bcos. Públ.'!A253 -> 43467 | B253: 0 | C253: 0 | D253: 0 | E253: 0 | F253: 0 | G253: 0 | H253: 0 | I253: 0 | J253: 0 | K253: 0 | L253: 0 | M253: 0 | N253: 0 | O253: 0 | P253: 0 | Q253: ND | R253: ND | T253: 0 | U253: 0 | V253: 0 | W253: 0 | X253: 0 | Y253: 0 | Z253: 0 | AA253: 0 | AB253: 0 | AC253: ND | AD253: 0 | AE253: 0 | AF253: 0 | AG253: 0 | AH253: 0 | AI253: 0 | AJ253: 0 | AK253: 0 | AL253: 0 | AM253: ND
A254: 43497 | B254: 0 | C254: 1.3197097 | D254: 1.3197097 | E254: 13.517729 | F254: 0 | G254: 13.517729 | H254: 13.517729 | I254: 1.3197097 | J254: 14.837439 | K254: 0 | L254: 0 | M254: 0 | N254: 13.517729 | O254: 1.3197097 | P254: 14.837439 | Q254: ND | R254: ND | T254: 0 | U254: 0.21000013 | V254: 0.21000013 | W254: 13.517729 | X254: 0 | Y254: 13.517729 | Z254: 13.517729 | AA254: 0.21000013 | AB254: 13.727729 | AC254: ND | AD254: 0 | AE254: 0.033987 | AF254: 0.033987 | AG254: 0 | AH254: 0 | AI254: 0 | AJ254: 0 | AK254: 0.033987 | AL254: 0.033987 | AM254: ND
A255: 43525 | B255: 0 | C255: 1.3533784 | D255: 1.3533784 | E255: 13.862597 | F255: 0 | G255: 13.862597 | H255: 13.862597 | I255: 1.3533784 | J255: 15.215975 | K255: 0 | L255: 0 | M255: 0 | N255: 13.862597 | O255: 1.3533784 | P255: 15.215975 | Q255: ND | R255: ND | T255: 0 | U255: 0.2153577 | V255: 0.2153577 | W255: 13.862597 | X255: 0 | Y255: 13.862597 | Z255: 13.862597 | AA255: 0.2153577 | AB255: 14.077954 | AC255: ND | AD255: 0 | AE255: 0.033987 | AF255: 0.033987 | AG255: 0 | AH255: 0 | AI255: 0 | AJ255: 0 | AK255: 0.033987 | AL255: 0.033987 | AM255: ND
A256: 43556 | B256: 0 | C256: 1.3988993 | D256: 1.3988993 | E256: 13.941134 | F256: 0 | G256: 13.941134 | H256: 13.941134 | I256: 1.3988993 | J256: 15.340033 | K256: 0 | L256: 0 | M256: 0 | N256: 13.941134 | O256: 1.3988993 | P256: 15.340033 | Q256: ND | R256: ND | T256: 0 | U256: 0.21000004 | V256: 0.21000004 | W256: 13.941134 | X256: 0 | Y256: 13.941134 | Z256: 13.941134 | AA256: 0.21000004 | AB256: 14.151134 | AC256: ND | AD256: 0 | AE256: 0.033987 | AF256: 0.033987 | AG256: 0 | AH256: 0 | AI256: 0 | AJ256: 0 | AK256: 0.033987 | AL256: 0.033987 | AM256: ND
A257: 43586 | B257: 0 | C257: 1.4081098 | D257: 1.4081098 | E257: 14.096293 | F257: 0 | G257: 14.096293 | H257: 14.096293 | I257: 1.4081098 | J257: 15.504403 | K257: 0 | L257: 0 | M257: 0 | N257: 14.096293 | O257: 1.4081098 | P257: 15.504403 | Q257: ND | R257: ND | T257: 0 | U257: 0.21000004 | V257: 0.21000004 | W257: 14.096293 | X257: 0 | Y257: 14.096293 | Z257: 14.096293 | AA257: 0.21000004 | AB257: 14.306293 | AC257: ND | AD257: 0 | AE257: 0.033987 | AF257: 0.033987 | AG257: 0 | AH257: 0 | AI257: 0 | AJ257: 0 | AK257: 0.033987 | AL257: 0.033987 | AM257: ND
A258: 43617 | B258: 0 | C258: 1.4069373 | D258: 1.4069373 | E258: 14.021239 | F258: 0 | G258: 14.021239 | H258: 14.021239 | I258: 1.4069373 | J258: 15.428176 | K258: 0 | L258: 0 | M258: 0 | N258: 14.021239 | O258: 1.4069373 | P258: 15.428176 | Q258: ND | R258: ND | T258: 0 | U258: 0.21120669 | V258: 0.21120669 | W258: 14.021239 | X258: 0 | Y258: 14.021239 | Z258: 14.021239 | AA258: 0.21120669 | AB258: 14.232446 | AC258: ND | AD258: 0 | AE258: 0.033987 | AF258: 0.033987 | AG258: 0 | AH258: 0 | AI258: 0 | AJ258: 0 | AK258: 0.033987 | AL258: 0.033987 | AM258: ND
A259: 43647 | B259: 0 | C259: 1.3774535 | D259: 1.3774535 | E259: 14.396358 | F259: 0 | G259: 14.396358 | H259: 14.396358 | I259: 1.3774535 | J259: 15.773812 | K259: 0 | L259: 0 | M259: 0 | N259: 14.396358 | O259: 1.3774535 | P259: 15.773812 | Q259: ND | R259: ND | T259: 0 | U259: 0.2100001 | V259: 0.2100001 | W259: 14.396358 | X259: 0 | Y259: 14.396358 | Z259: 14.396358 | AA259: 0.2100001 | AB259: 14.606358 | AC259: ND | AD259: 0 | AE259: 0.033987 | AF259: 0.033987 | AG259: 0 | AH259: 0 | AI259: 0 | AJ259: 0 | AK259: 0.033987 | AL259: 0.033987 | AM259: ND
A260: 43678 | B260: 0 | C260: 1.4553517 | D260: 1.4553517 | E260: 14.592529 | F260: 0 | G260: 14.592529 | H260: 14.592529 | I260: 1.4553517 | J260: 16.047881 | K260: 0 | L260: 0 | M260: 0 | N260: 14.592529 | O260: 1.4553517 | P260: 16.047881 | Q260: ND | R260: ND | T260: 0 | U260: 0.21000007 | V260: 0.21000007 | W260: 14.592529 | X260: 0 | Y260: 14.592529 | Z260: 14.592529 | AA260: 0.21000007 | AB260: 14.802529 | AC260: ND | AD260: 0 | AE260: 0.033987 | AF260: 0.033987 | AG260: 0 | AH260: 0 | AI260: 0 | AJ260: 0 | AK260: 0.033987 | AL260: 0.033987 | AM260: ND
A261: 43709 | B261: 0 | C261: 0 | D261: 0 | E261: 14.809311 | F261: 0 | G261: 14.809311 | H261: 14.809311 | I261: 0 | J261: 14.809311 | K261: 0 | L261: 0 | M261: 0 | N261: 14.809311 | O261: 0 | P261: 14.809311 | Q261: ND | R261: ND | T261: 0 | U261: 0 | V261: 0 | W261: 14.809311 | X261: 0 | Y261: 14.809311 | Z261: 14.809311 | AA261: 0 | AB261: 14.809311 | AC261: ND | AD261: 0 | AE261: 0 | AF261: 0 | AG261: 0 | AH261: 0 | AI261: 0 | AJ261: 0 | AK261: 0 | AL261: 0 | AM261: ND
A262: 43739 | B262: 0 | C262: 0 | D262: 0 | E262: 14.988396 | F262: 0 | G262: 14.988396 | H262: 14.988396 | I262: 0 | J262: 14.988396 | K262: 0 | L262: 0 | M262: 0 | N262: 14.988396 | O262: 0 | P262: 14.988396 | Q262: ND | R262: ND | T262: 0 | U262: 0 | V262: 0 | W262: 14.988396 | X262: 0 | Y262: 14.988396 | Z262: 14.988396 | AA262: 0 | AB262: 14.988396 | AC262: ND | AD262: 0 | AE262: 0 | AF262: 0 | AG262: 0 | AH262: 0 | AI262: 0 | AJ262: 0 | AK262: 0 | AL262: 0 | AM262: ND
A263: 43770 | B263: 0 | C263: 0 | D263: 0 | E263: 15.188083 | F263: 0 | G263: 15.188083 | H263: 15.188083 | I263: 0 | J263: 15.188083 | K263: 0 | L263: 0 | M263: 0 | N263: 15.188083 | O263: 0 | P263: 15.188083 | Q263: ND | R263: ND | T263: 0 | U263: 0 | V263: 0 | W263: 15.188083 | X263: 0 | Y263: 15.188083 | Z263: 15.188083 | AA263: 0 | AB263: 15.188083 | AC263: ND | AD263: 0 | AE263: 0 | AF263: 0 | AG263: 0 | AH263: 0 | AI263: 0 | AJ263: 0 | AK263: 0 | AL263: 0 | AM263: ND
A264: 43800 | B264: 0 | C264: 0 | D264: 0 | E264: 15.353904 | F264: 0 | G264: 0 | H264: 15.353904 | I264: 0 | J264: 15.353904 | K264: 0 | L264: 0 | M264: 0 | N264: 15.353904 | O264: 0 | P264: 0 | Q264: ND | R264: ND | T264: 0 | U264: 0 | V264: 0 | W264: 15.353904 | X264: 0 | Y264: 0 | Z264: 15.353904 | AA264: 0 | AB264: 15.353904 | AC264: ND | AD264: 0 | AE264: 0 | AF264: 0 | AG264: 0 | AH264: 0 | AI264: 0 | AJ264: 0 | AK264: 0 | AL264: 0 | AM264: ND
A265: 43831 | B265: 0 | C265: 0 | D265: 0 | E265: 15.502733 | F265: 0 | G265: 15.502733 | H265: 15.502733 | I265: 0 | J265: 15.502733 | K265: 0 | L265: 0 | M265: 0 | N265: 15.502733 | O265: 0 | P265: 15.502733 | Q265: ND | R265: ND | T265: 0 | U265: 0 | V265: 0 | W265: 15.502733 | X265: 0 | Y265: 15.502733 | Z265: 15.502733 | AA265: 0 | AB265: 15.502733 | AC265: ND | AD265: 0 | AE265: 0 | AF265: 0 | AG265: 0 | AH265: 0 | AI265: 0 | AJ265: 0 | AK265: 0 | AL265: 0 | AM265: ND
... A324: 45627 | B324: 46.629068 | C324: 0 | D324: 46.629068 | E324: 29.630566 | F324: 0 | G324: 29.630566 | H324: 76.259634 | I324: 0 | J324: 76.259634 | K324: 0 | L324: 0 | M324: 0 | N324: 76.259634 | O324: 0 | P324: 76.259634 | Q324: ND | R324: ND | T324: 0 | U324: 0 | V324: 0 | W324: 29.630566 | X324: 0 | Y324: 29.630566 | Z324: 29.630566 | AA324: 0 | AB324: 29.630566 | AC324: ND | AD324: 1.0581643 | AE324: 0 | AF324: 1.0581643 | AG324: 0 | AH324: 0 | AI324: 0 | AJ324: 1.0581643 | AK324: 0 | AL324: 1.0581643 | AM324: ND
A325: 45658 | B325: =+'[1]C. Financ.'!B325*[2]TC!$B316 -> 37.628552 | C325: =+'[1]C. Financ.'!C325*[2]TC!$B316 -> 0 | D325: =+'[1]C. Financ.'!D325*[2]TC!$B316 -> 37.628552 | E325: =+'[1]C. Financ.'!E325*[2]TC!$B316 -> 29.914099 | F325: =+'[1]C. Financ.'!F325*[2]TC!$B316 -> 0 | G325: =+'[1]C. Financ.'!G325*[2]TC!$B316 -> 29.914099 | H325: =+'[1]C. Financ.'!H325*[2]TC!$B316 -> 67.542651 | I325: =+'[1]C. Financ.'!I325*[2]TC!$B316 -> 0 | ... P325: =+'[1]C. Financ.'!P325*[2]TC!$B316 -> 67.542651 | Q325: ND | R325: ND | T325: =+'[1]C. Financ.'!T325*[2]TC!$B316 -> 0 | U325: =+'[1]C. Financ.'!U325*[2]TC!$B316 -> 0 | V325: =+'[1]C. Financ.'!V325*[2]TC!$B316 -> 0 | W325: =+'[1]C. Financ.'!W325*[2]TC!$B316 -> 29.914099 | X325: =+'[1]C. Financ.'!X325*[2]TC!$B316 -> 0 | Y325: =+'[1]C. Financ.'!Y325*[2]TC!$B316 -> 29.914099 | Z325: =+'[1]C. Financ.'!Z325*[2]TC!$B316 -> 29.914099 | AA325: =+'[1]C. Financ.'!AA325*[2]TC!$B316 -> 0 | AB325: =+'[1]C. Financ.'!AB325*[2]TC!$B316 -> 29.914099 | AC325: ND | AD325: =+'[1]C. Financ.'!AD325 -> 0.87260683 | AE325: =+'[1]C. Financ.'!AE325 -> 0 | AF325: =+'[1]C. Financ.'!AF325 -> 0.87260683 | AG325: =+'[1]C. Financ.'!AG325 -> 0 | AH325: =+'[1]C. Financ.'!AH325 -> 0 | AI325: =+'[1]C. Financ.'!AI325 -> 0 | AJ325: =+'[1]C. Financ.'!AJ325 -> 0.87260683 | AK325: =+'[1]C. Financ.'!AK325 -> 0 | AL325: =+'[1]C. Financ.'!AL325 -> 0.87260683 | AM325: ND
A326: 45689 | B326: =+'[1]C. Financ.'!B326*[2]TC!$B317 -> 83.133765 | C326: =+'[1]C. Financ.'!C326*[2]TC!$B317 -> 0 | D326: =+'[1]C. Financ.'!D326*[2]TC!$B317 -> 83.133765 | E326: =+'[1]C. Financ.'!E326*[2]TC!$B317 -> 30.321689 | F326: =+'[1]C. Financ.'!F326*[2]TC!$B317 -> 0 | G326: =+'[1]C. Financ.'!G326*[2]TC!$B317 -> 30.321689 | H326: =+'[1]C. Financ.'!H326*[2]TC!$B317 -> 113.45545 | I326: =+'[1]C. Financ.'!I326*[2]TC!$B317 -> 0 | ... P326: =+'[1]C. Financ.'!P326*[2]TC!$B317 -> 113.45545 | Q326: ND | R326: ND | T326: =+'[1]C. Financ.'!T326*[2]TC!$B317 -> 0 | U326: =+'[1]C. Financ.'!U326*[2]TC!$B317 -> 0 | V326: =+'[1]C. Financ.'!V326*[2]TC!$B317 -> 0 | W326: =+'[1]C. Financ.'!W326*[2]TC!$B317 -> 30.321689 | X326: =+'[1]C. Financ.'!X326*[2]TC!$B317 -> 0 | Y326: =+'[1]C. Financ.'!Y326*[2]TC!$B317 -> 30.321689 | Z326: =+'[1]C. Financ.'!Z326*[2]TC!$B317 -> 30.321689 | AA326: =+'[1]C. Financ.'!AA326*[2]TC!$B317 -> 0 | AB326: =+'[1]C. Financ.'!AB326*[2]TC!$B317 -> 30.321689 | AC326: ND | AD326: =+'[1]C. Financ.'!AD326 -> 1.9521842 | AE326: =+'[1]C. Financ.'!AE326 -> 0 | AF326: =+'[1]C. Financ.'!AF326 -> 1.9521842 | AG326: =+'[1]C. Financ.'!AG326 -> 0 | AH326: =+'[1]C. Financ.'!AH326 -> 0 | AI326: =+'[1]C. Financ.'!AI326 -> 0 | AJ326: =+'[1]C. Financ.'!AJ326 -> 1.9521842 | AK326: =+'[1]C. Financ.'!AK326 -> 0 | AL326: =+'[1]C. Financ.'!AL326 -> 1.9521842 | AM326: ND
A327: 45717 | B327: =+'[1]C. Financ.'!B327*[2]TC!$B318 -> 89.804551 | C327: =+'[1]C. Financ.'!C327*[2]TC!$B318 -> 0 | D327: =+'[1]C. Financ.'!D327*[2]TC!$B318 -> 89.804551 | E327: =+'[1]C. Financ.'!E327*[2]TC!$B318 -> 30.680195 | F327: =+'[1]C. Financ.'!F327*[2]TC!$B318 -> 0 | G327: =+'[1]C. Financ.'!G327*[2]TC!$B318 -> 30.680195 | H327: =+'[1]C. Financ.'!H327*[2]TC!$B318 -> 120.48475 | I327: =+'[1]C. Financ.'!I327*[2]TC!$B318 -> 0 | ... P327: =+'[1]C. Financ.'!P327*[2]TC!$B318 -> 120.48475 | Q327: ND | R327: ND | T327: =+'[1]C. Financ.'!T327*[2]TC!$B318 -> 0 | U327: =+'[1]C. Financ.'!U327*[2]TC!$B318 -> 0 | V327: =+'[1]C. Financ.'!V327*[2]TC!$B318 -> 0 | W327: =+'[1]C. Financ.'!W327*[2]TC!$B318 -> 30.680195 | X327: =+'[1]C. Financ.'!X327*[2]TC!$B318 -> 0 | Y327: =+'[1]C. Financ.'!Y327*[2]TC!$B318 -> 30.680195 | Z327: =+'[1]C. Financ.'!Z327*[2]TC!$B318 -> 30.680195 | AA327: =+'[1]C. Financ.'!AA327*[2]TC!$B318 -> 0 | AB327: =+'[1]C. Financ.'!AB327*[2]TC!$B318 -> 30.680195 | AC327: ND | AD327: =+'[1]C. Financ.'!AD327 -> 2.1317576 | AE327: =+'[1]C. Financ.'!AE327 -> 0 | AF327: =+'[1]C. Financ.'!AF327 -> 2.1317576 | AG327: =+'[1]C. Financ.'!AG327 -> 0 | AH327: =+'[1]C. Financ.'!AH327 -> 0 | AI327: =+'[1]C. Financ.'!AI327 -> 0 | AJ327: =+'[1]C. Financ.'!AJ327 -> 2.1317576 | AK327: =+'[1]C. Financ.'!AK327 -> 0 | AL327: =+'[1]C. Financ.'!AL327 -> 2.1317576 | AM327: ND
A328: 45748 | B328: 89.949507 | C328: 0 | D328: 89.949507 | E328: 30.987265 | F328: 0 | G328: 30.987265 | H328: 120.93677 | I328: 0 | J328: 120.93677 | K328: 0 | L328: 0 | M328: 0 | N328: 120.93677 | O328: 0 | P328: 120.93677 | Q328: ND | R328: ND | T328: 0 | U328: 0 | V328: 0 | W328: 30.987265 | X328: 0 | Y328: 30.987265 | Z328: 30.987265 | AA328: 0 | AB328: 30.987265 | AC328: ND | AD328: 2.1442587 | AE328: 0 | AF328: 2.1442587 | AG328: 0 | AH328: 0 | AI328: 0 | AJ328: 2.1442587 | AK328: 0 | AL328: 2.1442587 | AM328: ND
A329: 45778 | B329: 102.96832 | C329: 0 | D329: 102.96832 | E329: 31.232397 | F329: 0 | G329: 31.232397 | H329: 134.20071 | I329: 0 | J329: 134.20071 | K329: 0 | L329: 0 | M329: 0 | N329: 134.20071 | O329: 0 | P329: 134.20071 | Q329: ND | R329: ND | T329: 0 | U329: 0 | V329: 0 | W329: 31.232397 | X329: 0 | Y329: 31.232397 | Z329: 31.232397 | AA329: 0 | AB329: 31.232397 | AC329: ND | AD329: 2.4705676 | AE329: 0 | AF329: 2.4705676 | AG329: 0 | AH329: 0 | AI329: 0 | AJ329: 2.4705676 | AK329: 0 | AL329: 2.4705676 | AM329: ND
A330: 45809 | B330: 97.369057 | C330: 0 | D330: 97.369057 | E330: 31.404533 | F330: 0 | G330: 31.404533 | H330: 128.77359 | I330: 0 | J330: 128.77359 | K330: 0 | L330: 0 | M330: 0 | N330: 128.77359 | O330: 0 | P330: 128.77359 | Q330: ND | R330: ND | T330: 0 | U330: 0 | V330: 0 | W330: 31.404533 | X330: 0 | Y330: 31.404533 | Z330: 31.404533 | AA330: 0 | AB330: 31.404533 | AC330: ND | AD330: 2.4620476 | AE330: 0 | AF330: 2.4620476 | AG330: 0 | AH330: 0 | AI330: 0 | AJ330: 2.4620476 | AK330: 0 | AL330: 2.4620476 | AM330: ND
A331: 45839 | B331: 96.534168 | C331: 0 | D331: 96.534168 | E331: 31.416145 | F331: 0 | G331: 31.416145 | H331: 127.95031 | I331: 0 | J331: 127.95031 | K331: 0 | L331: 0 | M331: 0 | N331: 127.95031 | O331: 0 | P331: 127.95031 | Q331: ND | R331: ND | T331: 0 | U331: 0 | V331: 0 | W331: 31.416145 | X331: 0 | Y331: 31.416145 | Z331: 31.416145 | AA331: 0 | AB331: 31.416145 | AC331: ND | AD331: 2.4015864 | AE331: 0 | AF331: 2.4015864 | AG331: 0 | AH331: 0 | AI331: 0 | AJ331: 2.4015864 | AK331: 0 | AL331: 2.4015864 | AM331: ND
A332: 45870 | B332: 110.51703 | C332: 0 | D332: 110.51703 | E332: 31.546472 | F332: 0 | G332: 31.546472 | H332: 142.0635 | I332: 0 | J332: 142.0635 | K332: 0 | L332: 0 | M332: 0 | N332: 142.0635 | O332: 0 | P332: 142.0635 | Q332: ND | R332: ND | T332: 0 | U332: 0 | V332: 0 | W332: 31.546472 | X332: 0 | Y332: 31.546472 | Z332: 31.546472 | AA332: 0 | AB332: 31.546472 | AC332: ND | AD332: 2.7632712 | AE332: 0 | AF332: 2.7632712 | AG332: 0 | AH332: 0 | AI332: 0 | AJ332: 2.7632712 | AK332: 0 | AL332: 2.7632712 | AM332: ND
A333: 45901 | B333: 168.51849 | C333: 0 | D333: 168.51849 | E333: 31.662697 | F333: 0 | G333: 31.662697 | H333: 200.18119 | I333: 0 | J333: 200.18119 | K333: 0.76092156 | L333: 0 | M333: 0.76092156 | N333: 200.94211 | O333: 0 | P333: 200.94211 | Q333: ND | R333: ND | T333: 0 | U333: 0 | V333: 0 | W333: 31.662697 | X333: 0 | Y333: 31.662697 | Z333: 31.662697 | AA333: 0 | AB333: 31.662697 | AC333: ND | AD333: 4.229351 | AE333: 0 | AF333: 4.229351 | AG333: 0 | AH333: 0 | AI333: 0 | AJ333: 4.229351 | AK333: 0 | AL333: 4.229351 | AM333: ND
A335: (1) La variación del saldo contable de los créditos brutos se encuentra influida por la transferencia de créditos a cuentas de orden (créditos castigados) de acuerdo a lo establecido por la normativa. Por este motivo se presenta la variación mensual de los créditos castigados, elemento que, para evaluar la evolución del crédito desde una perspectiva económica, debería sumarse al saldo de los créditos brutos.
A336: (2) Incluye las casas financieras en actividad en cada fecha.
A337: (3) Corresponde a los grupos N° 14010 (Préstamos), 14020 (Arrendamientos Financieros), 14060 (Ingresos Percibidos No Devengados), 14070 (Grupos de Ahorro Previo), 14080 (Deudores por Productos Financieros Devengados), 16010 (Créditos Vencidos - Sector No Público) y 16080 (Deudores por Productos Financieros) del Plan de Cuentas para EIF, excepto las cuentas de deudores por créditos documentarios diferidos y domésticos diferidos (185000 y 189001 respectivamente), las cuentas de operaciones a liquidar (369080), sector público (245000 y 393000), sector financiero (407000), y a partir de marzo de 2005 los préstamos garantizados con prenda de depósitos (509000).
A338: Nuevo Plan de cuenta: 1.4.2.1 Créditos vigentes + 1.4.2.2 Créditos vigentes (deudores por intereses)+ 1.4.2.4 Colocacion vencida + 1.4.2.5 Colocación vencida (deudores por intereses) + 1.4.2.7 Créditos en gestión + 1.4.2.8 Créditos en gestión (deudores por intereses) +1.4.2.10 Créditos morosos + 1.4.2.11 Créditos morosos (deudores por intereses)
A339: (4) Incluye a las cuentas de los grupos N° 14050 y 16040 (Créditos Vigentes y Vencidos - Sector Público Nacional y No Nacional), 14080 y 16080 (Créditos Vigentes y Vencidos - Deudores por Productos Financieros Devengados) que corresponden al sector público nacional, excepto las cuentas de operaciones a liquidar (227000, 229000 y 381000) y deudores por créditos domésticos diferidos (221000). Incluye Estado, organismos de seguridad social, gobiernos departamentales y otros integrantes del sector público.
A340: Nuevo Plan de cuenta: 1.4.3.1 Créditos vigentes + 1.4.3.2 Créditos vigentes (deudores por intereses)+ 1.4.3.4 Colocación vencida + 1.4.3.5 Colocación vencida (deudores por intereses)+ 1.4.3.7 Créditos en gestión + 1.4.3.8 Créditos en gestión (deudores por intereses) +1.4.3.10 Créditos morosos + 1.4.3.11 Créditos morosos (deudores por intereses).
A341: (5) Incluye sector privado no residente y sector público no nacional.
A343: Notas:
A344: Los meses que aparecen subrayados incluyen comentarios explicativos y vínculo a la hoja con detalle de todos los comentarios.
A345: Diferencias en las columnas de Total se deben a redondeo de las cifras.

Sheet Total Sist. Banc.
A1: Banco Central del Uruguay | T1: Banco Central del Uruguay
A2: Superintendencia de Servicios Financieros | T2: Superintendencia de Instituciones de Intermediación Financiera
M3: Volver al Índice | AH3: Volver al Índice
B4: CRÉDITOS BRUTOS SECTOR NO FINANCIERO (SNF) (1) | T4: CRÉDITOS BRUTOS SNF (1) - ANEXO RESIDENTES POR MONEDAS
B5: TOTAL SISTEMA BANCARIO (2) | T5: TOTAL SISTEMA BANCARIO (2)
B6: (Crédito Total en millones de pesos) | T6: (Créditos en MN en millones de pesos y en ME en millones de dólares)
B8: TOTAL (MN + ME) en millones de pesos
B9: RESIDENTES | K9: NO RESIDENTES (5) | N9: TOTAL | Q9: Variación mensual | T9: MONEDA NACIONAL en millones de pesos | AD9: MONEDA EXTRANJERA en millones de dólares
A10: Mes | B10: SECTOR PRIVADO (3) | E10: SECTOR PÚBLICO (4) | H10: TOTAL (S.Priv. + S.Públ) | Q10: Castigados (1) | T10: SECTOR PRIVADO (3) | W10: SECTOR PÚBLICO (4) | Z10: TOTAL (S.Priv. + S.Públ) | AC10: Variac. mens. | AD10: SECTOR PRIVADO (3) | AG10: SECTOR PÚBLICO (4) | AJ10: TOTAL (S.Priv. + S.Públ) | AM10: Variac. mens.
B11: Vigentes | C11: Vencidos | D11: Total | E11: Vigentes | F11: Vencidos | G11: Total | H11: Vigentes | I11: Vencidos | J11: Total | K11: Vigentes | L11: Vencidos | M11: Total | N11: Vigentes | O11: Vencidos | P11: Total | Q11: Resid. | R11: No resid. | T11: Vigentes | U11: Vencidos | V11: Total | W11: Vigentes | X11: Vencidos | Y11: Total | Z11: Vigentes | AA11: Vencidos | AB11: Total | AC11: Castigados (1) | AD11: Vigentes | AE11: Vencidos | AF11: Total | AG11: Vigentes | AH11: Vencidos | AI11: Total | AJ11: Vigentes | AK11: Vencidos | AL11: Total | AM11: Castigados (1)
A12: 36130 | B12: =+'Bcos. Públ.'!B12+'Bcos. Priv.'!#REF!+'Coop.'!B12+'C. Financ.'!B12 -> #REF! | C12: =+'Bcos. Públ.'!C12+'Bcos. Priv.'!#REF!+'Coop.'!C12+'C. Financ.'!C12 -> #REF! | D12: =+'Bcos. Públ.'!D12+'Bcos. Priv.'!#REF!+'Coop.'!D12+'C. Financ.'!D12 -> #REF! | E12: =+'Bcos. Públ.'!E12+'Bcos. Priv.'!#REF!+'Coop.'!E12+'C. Financ.'!E12 -> #REF! | F12: =+'Bcos. Públ.'!F12+'Bcos. Priv.'!#REF!+'Coop.'!F12+'C. Financ.'!F12 -> #REF! | G12: =+'Bcos. Públ.'!G12+'Bcos. Priv.'!#REF!+'Coop.'!G12+'C. Financ.'!G12 -> #REF! | H12: =+'Bcos. Públ.'!H12+'Bcos. Priv.'!#REF!+'Coop.'!H12+'C. Financ.'!H12 -> #REF! | I12: =+'Bcos. Públ.'!I12+'Bcos. Priv.'!#REF!+'Coop.'!I12+'C. Financ.'!I12 -> #REF! | ... R12: =+'Bcos. Públ.'!R12+'Bcos. Priv.'!#REF!+'Coop.'!R12+'C. Financ.'!R12 -> #REF! | T12: =+'Bcos. Públ.'!T12+'Bcos. Priv.'!#REF!+'Coop.'!T12+'C. Financ.'!T12 -> #REF! | U12: =+'Bcos. Públ.'!U12+'Bcos. Priv.'!#REF!+'Coop.'!U12+'C. Financ.'!U12 -> #REF! | V12: =+'Bcos. Públ.'!V12+'Bcos. Priv.'!#REF!+'Coop.'!V12+'C. Financ.'!V12 -> #REF! | W12: =+'Bcos. Públ.'!W12+'Bcos. Priv.'!#REF!+'Coop.'!W12+'C. Financ.'!W12 -> #REF! | X12: =+'Bcos. Públ.'!X12+'Bcos. Priv.'!#REF!+'Coop.'!X12+'C. Financ.'!X12 -> #REF! | Y12: =+'Bcos. Públ.'!Y12+'Bcos. Priv.'!#REF!+'Coop.'!Y12+'C. Financ.'!Y12 -> #REF! | Z12: =+'Bcos. Públ.'!Z12+'Bcos. Priv.'!#REF!+'Coop.'!Z12+'C. Financ.'!Z12 -> #REF! | AA12: =+'Bcos. Públ.'!AA12+'Bcos. Priv.'!#REF!+'Coop.'!AA12+'C. Financ.'!AA12 -> #REF! | ... AM12: =+'Bcos. Públ.'!AM12+'Bcos. Priv.'!#REF!+'Coop.'!AM12+'C. Financ.'!AM12 -> #REF!
A13: 36161 | B13: =+'Bcos. Públ.'!B13+'Bcos. Priv.'!B12+'Coop.'!B13+'C. Financ.'!B13 -> 88900.88 | C13: =+'Bcos. Públ.'!C13+'Bcos. Priv.'!C12+'Coop.'!C13+'C. Financ.'!C13 -> 17848.19 | D13: =+'Bcos. Públ.'!D13+'Bcos. Priv.'!D12+'Coop.'!D13+'C. Financ.'!D13 -> 106749.07 | E13: =+'Bcos. Públ.'!E13+'Bcos. Priv.'!E12+'Coop.'!E13+'C. Financ.'!E13 -> 9094.13 | F13: =+'Bcos. Públ.'!F13+'Bcos. Priv.'!F12+'Coop.'!F13+'C. Financ.'!F13 -> 164.55 | G13: =+'Bcos. Públ.'!G13+'Bcos. Priv.'!G12+'Coop.'!G13+'C. Financ.'!G13 -> 9258.68 | H13: =+'Bcos. Públ.'!H13+'Bcos. Priv.'!H12+'Coop.'!H13+'C. Financ.'!H13 -> 97995.01 | I13: =+'Bcos. Públ.'!I13+'Bcos. Priv.'!I12+'Coop.'!I13+'C. Financ.'!I13 -> 18012.74 | ... R13: =+'Bcos. Públ.'!R13+'Bcos. Priv.'!R12+'Coop.'!R13+'C. Financ.'!R13 -> 102.0164 | T13: =+'Bcos. Públ.'!T13+'Bcos. Priv.'!T12+'Coop.'!T13+'C. Financ.'!T13 -> 33261.04 | U13: =+'Bcos. Públ.'!U13+'Bcos. Priv.'!U12+'Coop.'!U13+'C. Financ.'!U13 -> 7810.64 | V13: =+'Bcos. Públ.'!V13+'Bcos. Priv.'!V12+'Coop.'!V13+'C. Financ.'!V13 -> 41082.65 | W13: =+'Bcos. Públ.'!W13+'Bcos. Priv.'!W12+'Coop.'!W13+'C. Financ.'!W13 -> 4442.85 | X13: =+'Bcos. Públ.'!X13+'Bcos. Priv.'!X12+'Coop.'!X13+'C. Financ.'!X13 -> 0 | Y13: =+'Bcos. Públ.'!Y13+'Bcos. Priv.'!Y12+'Coop.'!Y13+'C. Financ.'!Y13 -> 4442.85 | Z13: =+'Bcos. Públ.'!Z13+'Bcos. Priv.'!Z12+'Coop.'!Z13+'C. Financ.'!Z13 -> 37714.86 | AA13: =+'Bcos. Públ.'!AA13+'Bcos. Priv.'!AA12+'Coop.'!AA13+'C. Financ.'!AA13 -> 7810.64 | ... AM13: =+'Bcos. Públ.'!AM13+'Bcos. Priv.'!AM12+'Coop.'!AM13+'C. Financ.'!AM13 -> 8.9484108
A14: 36192 | B14: =+'Bcos. Públ.'!B14+'Bcos. Priv.'!B13+'Coop.'!B14+'C. Financ.'!B14 -> 88495.16 | C14: =+'Bcos. Públ.'!C14+'Bcos. Priv.'!C13+'Coop.'!C14+'C. Financ.'!C14 -> 18762.38 | D14: =+'Bcos. Públ.'!D14+'Bcos. Priv.'!D13+'Coop.'!D14+'C. Financ.'!D14 -> 107268.52 | E14: =+'Bcos. Públ.'!E14+'Bcos. Priv.'!E13+'Coop.'!E14+'C. Financ.'!E14 -> 9018.685 | F14: =+'Bcos. Públ.'!F14+'Bcos. Priv.'!F13+'Coop.'!F14+'C. Financ.'!F14 -> 164.775 | G14: =+'Bcos. Públ.'!G14+'Bcos. Priv.'!G13+'Coop.'!G14+'C. Financ.'!G14 -> 9183.46 | H14: =+'Bcos. Públ.'!H14+'Bcos. Priv.'!H13+'Coop.'!H14+'C. Financ.'!H14 -> 97513.845 | I14: =+'Bcos. Públ.'!I14+'Bcos. Priv.'!I13+'Coop.'!I14+'C. Financ.'!I14 -> 18938.14 | ... R14: =+'Bcos. Públ.'!R14+'Bcos. Priv.'!R13+'Coop.'!R14+'C. Financ.'!R14 -> 20.532599 | T14: =+'Bcos. Públ.'!T14+'Bcos. Priv.'!T13+'Coop.'!T14+'C. Financ.'!T14 -> 32976.97 | U14: =+'Bcos. Públ.'!U14+'Bcos. Priv.'!U13+'Coop.'!U14+'C. Financ.'!U14 -> 8293.675 | V14: =+'Bcos. Públ.'!V14+'Bcos. Priv.'!V13+'Coop.'!V14+'C. Financ.'!V14 -> 41270.645 | W14: =+'Bcos. Públ.'!W14+'Bcos. Priv.'!W13+'Coop.'!W14+'C. Financ.'!W14 -> 4470.895 | X14: =+'Bcos. Públ.'!X14+'Bcos. Priv.'!X13+'Coop.'!X14+'C. Financ.'!X14 -> 0 | Y14: =+'Bcos. Públ.'!Y14+'Bcos. Priv.'!Y13+'Coop.'!Y14+'C. Financ.'!Y14 -> 4470.895 | Z14: =+'Bcos. Públ.'!Z14+'Bcos. Priv.'!Z13+'Coop.'!Z14+'C. Financ.'!Z14 -> 37447.865 | AA14: =+'Bcos. Públ.'!AA14+'Bcos. Priv.'!AA13+'Coop.'!AA14+'C. Financ.'!AA14 -> 8304.66 | ... AM14: =+'Bcos. Públ.'!AM14+'Bcos. Priv.'!AM13+'Coop.'!AM14+'C. Financ.'!AM14 -> 15.809732
A15: 36220 | B15: =+'Bcos. Públ.'!B15+'Bcos. Priv.'!B14+'Coop.'!B15+'C. Financ.'!B15 -> 89891.69 | C15: =+'Bcos. Públ.'!C15+'Bcos. Priv.'!C14+'Coop.'!C15+'C. Financ.'!C15 -> 17274.915 | D15: =+'Bcos. Públ.'!D15+'Bcos. Priv.'!D14+'Coop.'!D15+'C. Financ.'!D15 -> 107177.7 | E15: =+'Bcos. Públ.'!E15+'Bcos. Priv.'!E14+'Coop.'!E15+'C. Financ.'!E15 -> 9120.09 | F15: =+'Bcos. Públ.'!F15+'Bcos. Priv.'!F14+'Coop.'!F15+'C. Financ.'!F15 -> 177.52 | G15: =+'Bcos. Públ.'!G15+'Bcos. Priv.'!G14+'Coop.'!G15+'C. Financ.'!G15 -> 9297.61 | H15: =+'Bcos. Públ.'!H15+'Bcos. Priv.'!H14+'Coop.'!H15+'C. Financ.'!H15 -> 99022.875 | I15: =+'Bcos. Públ.'!I15+'Bcos. Priv.'!I14+'Coop.'!I15+'C. Financ.'!I15 -> 17452.435 | ... R15: =+'Bcos. Públ.'!R15+'Bcos. Priv.'!R14+'Coop.'!R15+'C. Financ.'!R15 -> -1.4585652 | T15: =+'Bcos. Públ.'!T15+'Bcos. Priv.'!T14+'Coop.'!T15+'C. Financ.'!T15 -> 33806.465 | U15: =+'Bcos. Públ.'!U15+'Bcos. Priv.'!U14+'Coop.'!U15+'C. Financ.'!U15 -> 7577.885 | V15: =+'Bcos. Públ.'!V15+'Bcos. Priv.'!V14+'Coop.'!V15+'C. Financ.'!V15 -> 41384.35 | W15: =+'Bcos. Públ.'!W15+'Bcos. Priv.'!W14+'Coop.'!W15+'C. Financ.'!W15 -> 4515.665 | X15: =+'Bcos. Públ.'!X15+'Bcos. Priv.'!X14+'Coop.'!X15+'C. Financ.'!X15 -> 0 | Y15: =+'Bcos. Públ.'!Y15+'Bcos. Priv.'!Y14+'Coop.'!Y15+'C. Financ.'!Y15 -> 4515.665 | Z15: =+'Bcos. Públ.'!Z15+'Bcos. Priv.'!Z14+'Coop.'!Z15+'C. Financ.'!Z15 -> 38322.13 | AA15: =+'Bcos. Públ.'!AA15+'Bcos. Priv.'!AA14+'Coop.'!AA15+'C. Financ.'!AA15 -> 7588.98 | ... AM15: =+'Bcos. Públ.'!AM15+'Bcos. Priv.'!AM14+'Coop.'!AM15+'C. Financ.'!AM15 -> 113.12946
A16: 36251 | B16: =+'Bcos. Públ.'!B16+'Bcos. Priv.'!B15+'Coop.'!B16+'C. Financ.'!B16 -> 90191.442 | C16: =+'Bcos. Públ.'!C16+'Bcos. Priv.'!C15+'Coop.'!C16+'C. Financ.'!C16 -> 16692.214 | D16: =+'Bcos. Públ.'!D16+'Bcos. Priv.'!D15+'Coop.'!D16+'C. Financ.'!D16 -> 106883.66 | E16: =+'Bcos. Públ.'!E16+'Bcos. Priv.'!E15+'Coop.'!E16+'C. Financ.'!E16 -> 9181.832 | F16: =+'Bcos. Públ.'!F16+'Bcos. Priv.'!F15+'Coop.'!F16+'C. Financ.'!F16 -> 178.288 | G16: =+'Bcos. Públ.'!G16+'Bcos. Priv.'!G15+'Coop.'!G16+'C. Financ.'!G16 -> 9348.977 | H16: =+'Bcos. Públ.'!H16+'Bcos. Priv.'!H15+'Coop.'!H16+'C. Financ.'!H16 -> 99362.131 | I16: =+'Bcos. Públ.'!I16+'Bcos. Priv.'!I15+'Coop.'!I16+'C. Financ.'!I16 -> 16870.502 | ... R16: =+'Bcos. Públ.'!R16+'Bcos. Priv.'!R15+'Coop.'!R16+'C. Financ.'!R16 -> 0.37017613 | T16: =+'Bcos. Públ.'!T16+'Bcos. Priv.'!T15+'Coop.'!T16+'C. Financ.'!T16 -> 34131.009 | U16: =+'Bcos. Públ.'!U16+'Bcos. Priv.'!U15+'Coop.'!U16+'C. Financ.'!U16 -> 7075.805 | V16: =+'Bcos. Públ.'!V16+'Bcos. Priv.'!V15+'Coop.'!V16+'C. Financ.'!V16 -> 41217.957 | W16: =+'Bcos. Públ.'!W16+'Bcos. Priv.'!W15+'Coop.'!W16+'C. Financ.'!W16 -> 4546.344 | X16: =+'Bcos. Públ.'!X16+'Bcos. Priv.'!X15+'Coop.'!X16+'C. Financ.'!X16 -> 0 | Y16: =+'Bcos. Públ.'!Y16+'Bcos. Priv.'!Y15+'Coop.'!Y16+'C. Financ.'!Y16 -> 4557.487 | Z16: =+'Bcos. Públ.'!Z16+'Bcos. Priv.'!Z15+'Coop.'!Z16+'C. Financ.'!Z16 -> 38677.353 | AA16: =+'Bcos. Públ.'!AA16+'Bcos. Priv.'!AA15+'Coop.'!AA16+'C. Financ.'!AA16 -> 7086.948 | ... AM16: =+'Bcos. Públ.'!AM16+'Bcos. Priv.'!AM15+'Coop.'!AM16+'C. Financ.'!AM16 -> 27.133591
A17: 36281 | B17: =+'Bcos. Públ.'!B17+'Bcos. Priv.'!B16+'Coop.'!B17+'C. Financ.'!B17 -> 90887.16 | C17: =+'Bcos. Públ.'!C17+'Bcos. Priv.'!C16+'Coop.'!C17+'C. Financ.'!C17 -> 16990.974 | D17: =+'Bcos. Públ.'!D17+'Bcos. Priv.'!D16+'Coop.'!D17+'C. Financ.'!D17 -> 107866.94 | E17: =+'Bcos. Públ.'!E17+'Bcos. Priv.'!E16+'Coop.'!E17+'C. Financ.'!E17 -> 9290.19 | F17: =+'Bcos. Públ.'!F17+'Bcos. Priv.'!F16+'Coop.'!F17+'C. Financ.'!F17 -> 190.281 | G17: =+'Bcos. Públ.'!G17+'Bcos. Priv.'!G16+'Coop.'!G17+'C. Financ.'!G17 -> 9491.664 | H17: =+'Bcos. Públ.'!H17+'Bcos. Priv.'!H16+'Coop.'!H17+'C. Financ.'!H17 -> 100177.35 | I17: =+'Bcos. Públ.'!I17+'Bcos. Priv.'!I16+'Coop.'!I17+'C. Financ.'!I17 -> 17192.448 | ... R17: =+'Bcos. Públ.'!R17+'Bcos. Priv.'!R16+'Coop.'!R17+'C. Financ.'!R17 -> 16.880928 | T17: =+'Bcos. Públ.'!T17+'Bcos. Priv.'!T16+'Coop.'!T17+'C. Financ.'!T17 -> 34519.212 | U17: =+'Bcos. Públ.'!U17+'Bcos. Priv.'!U16+'Coop.'!U17+'C. Financ.'!U17 -> 7018.011 | V17: =+'Bcos. Públ.'!V17+'Bcos. Priv.'!V16+'Coop.'!V17+'C. Financ.'!V17 -> 41548.416 | W17: =+'Bcos. Públ.'!W17+'Bcos. Priv.'!W16+'Coop.'!W17+'C. Financ.'!W17 -> 4611.516 | X17: =+'Bcos. Públ.'!X17+'Bcos. Priv.'!X16+'Coop.'!X17+'C. Financ.'!X17 -> 0 | Y17: =+'Bcos. Públ.'!Y17+'Bcos. Priv.'!Y16+'Coop.'!Y17+'C. Financ.'!Y17 -> 4611.516 | Z17: =+'Bcos. Públ.'!Z17+'Bcos. Priv.'!Z16+'Coop.'!Z17+'C. Financ.'!Z17 -> 39130.728 | AA17: =+'Bcos. Públ.'!AA17+'Bcos. Priv.'!AA16+'Coop.'!AA17+'C. Financ.'!AA17 -> 7018.011 | ... AM17: =+'Bcos. Públ.'!AM17+'Bcos. Priv.'!AM16+'Coop.'!AM17+'C. Financ.'!AM17 -> 3.7500598
A18: 36312 | B18: =+'Bcos. Públ.'!B18+'Bcos. Priv.'!B17+'Coop.'!B18+'C. Financ.'!B18 -> 92741.876 | C18: =+'Bcos. Públ.'!C18+'Bcos. Priv.'!C17+'Coop.'!C18+'C. Financ.'!C18 -> 17101.984 | D18: =+'Bcos. Públ.'!D18+'Bcos. Priv.'!D17+'Coop.'!D18+'C. Financ.'!D18 -> 109843.86 | E18: =+'Bcos. Públ.'!E18+'Bcos. Priv.'!E17+'Coop.'!E18+'C. Financ.'!E18 -> 9233.252 | F18: =+'Bcos. Públ.'!F18+'Bcos. Priv.'!F17+'Coop.'!F18+'C. Financ.'!F18 -> 216.049 | G18: =+'Bcos. Públ.'!G18+'Bcos. Priv.'!G17+'Coop.'!G18+'C. Financ.'!G18 -> 9449.301 | H18: =+'Bcos. Públ.'!H18+'Bcos. Priv.'!H17+'Coop.'!H18+'C. Financ.'!H18 -> 101975.13 | I18: =+'Bcos. Públ.'!I18+'Bcos. Priv.'!I17+'Coop.'!I18+'C. Financ.'!I18 -> 17329.404 | ... R18: =+'Bcos. Públ.'!R18+'Bcos. Priv.'!R17+'Coop.'!R18+'C. Financ.'!R18 -> 3.2580997 | T18: =+'Bcos. Públ.'!T18+'Bcos. Priv.'!T17+'Coop.'!T18+'C. Financ.'!T18 -> 34874.857 | U18: =+'Bcos. Públ.'!U18+'Bcos. Priv.'!U17+'Coop.'!U18+'C. Financ.'!U18 -> 6936.31 | V18: =+'Bcos. Públ.'!V18+'Bcos. Priv.'!V17+'Coop.'!V18+'C. Financ.'!V18 -> 41811.167 | W18: =+'Bcos. Públ.'!W18+'Bcos. Priv.'!W17+'Coop.'!W18+'C. Financ.'!W18 -> 4605.255 | X18: =+'Bcos. Públ.'!X18+'Bcos. Priv.'!X17+'Coop.'!X18+'C. Financ.'!X18 -> 0 | Y18: =+'Bcos. Públ.'!Y18+'Bcos. Priv.'!Y17+'Coop.'!Y18+'C. Financ.'!Y18 -> 4616.626 | Z18: =+'Bcos. Públ.'!Z18+'Bcos. Priv.'!Z17+'Coop.'!Z18+'C. Financ.'!Z18 -> 39480.112 | AA18: =+'Bcos. Públ.'!AA18+'Bcos. Priv.'!AA17+'Coop.'!AA18+'C. Financ.'!AA18 -> 6936.31 | ... AM18: =+'Bcos. Públ.'!AM18+'Bcos. Priv.'!AM17+'Coop.'!AM18+'C. Financ.'!AM18 -> 3.2113957
A19: 36342 | B19: =+'Bcos. Públ.'!B19+'Bcos. Priv.'!B18+'Coop.'!B19+'C. Financ.'!B19 -> 93115.5 | C19: =+'Bcos. Públ.'!C19+'Bcos. Priv.'!C18+'Coop.'!C19+'C. Financ.'!C19 -> 17629.5 | D19: =+'Bcos. Públ.'!D19+'Bcos. Priv.'!D18+'Coop.'!D19+'C. Financ.'!D19 -> 110745 | E19: =+'Bcos. Públ.'!E19+'Bcos. Priv.'!E18+'Coop.'!E19+'C. Financ.'!E19 -> 9246 | F19: =+'Bcos. Públ.'!F19+'Bcos. Priv.'!F18+'Coop.'!F19+'C. Financ.'!F19 -> 230 | G19: =+'Bcos. Públ.'!G19+'Bcos. Priv.'!G18+'Coop.'!G19+'C. Financ.'!G19 -> 9476 | H19: =+'Bcos. Públ.'!H19+'Bcos. Priv.'!H18+'Coop.'!H19+'C. Financ.'!H19 -> 102350 | I19: =+'Bcos. Públ.'!I19+'Bcos. Priv.'!I18+'Coop.'!I19+'C. Financ.'!I19 -> 17859.5 | ... R19: =+'Bcos. Públ.'!R19+'Bcos. Priv.'!R18+'Coop.'!R19+'C. Financ.'!R19 -> -2.2399898 | T19: =+'Bcos. Públ.'!T19+'Bcos. Priv.'!T18+'Coop.'!T19+'C. Financ.'!T19 -> 35017.5 | U19: =+'Bcos. Públ.'!U19+'Bcos. Priv.'!U18+'Coop.'!U19+'C. Financ.'!U19 -> 7153 | V19: =+'Bcos. Públ.'!V19+'Bcos. Priv.'!V18+'Coop.'!V19+'C. Financ.'!V19 -> 42159 | W19: =+'Bcos. Públ.'!W19+'Bcos. Priv.'!W18+'Coop.'!W19+'C. Financ.'!W19 -> 4611.5 | X19: =+'Bcos. Públ.'!X19+'Bcos. Priv.'!X18+'Coop.'!X19+'C. Financ.'!X19 -> 0 | Y19: =+'Bcos. Públ.'!Y19+'Bcos. Priv.'!Y18+'Coop.'!Y19+'C. Financ.'!Y19 -> 4611.5 | Z19: =+'Bcos. Públ.'!Z19+'Bcos. Priv.'!Z18+'Coop.'!Z19+'C. Financ.'!Z19 -> 39617.5 | AA19: =+'Bcos. Públ.'!AA19+'Bcos. Priv.'!AA18+'Coop.'!AA19+'C. Financ.'!AA19 -> 7153 | ... AM19: =+'Bcos. Públ.'!AM19+'Bcos. Priv.'!AM18+'Coop.'!AM19+'C. Financ.'!AM19 -> 0.1394694
A20: 36373 | B20: =+'Bcos. Públ.'!B20+'Bcos. Priv.'!B19+'Coop.'!B20+'C. Financ.'!B20 -> 92200.16 | C20: =+'Bcos. Públ.'!C20+'Bcos. Priv.'!C19+'Coop.'!C20+'C. Financ.'!C20 -> 19993.81 | D20: =+'Bcos. Públ.'!D20+'Bcos. Priv.'!D19+'Coop.'!D20+'C. Financ.'!D20 -> 112205.64 | E20: =+'Bcos. Públ.'!E20+'Bcos. Priv.'!E19+'Coop.'!E20+'C. Financ.'!E20 -> 9518.64 | F20: =+'Bcos. Públ.'!F20+'Bcos. Priv.'!F19+'Coop.'!F20+'C. Financ.'!F20 -> 198.305 | G20: =+'Bcos. Públ.'!G20+'Bcos. Priv.'!G19+'Coop.'!G20+'C. Financ.'!G20 -> 9716.945 | H20: =+'Bcos. Públ.'!H20+'Bcos. Priv.'!H19+'Coop.'!H20+'C. Financ.'!H20 -> 101718.8 | I20: =+'Bcos. Públ.'!I20+'Bcos. Priv.'!I19+'Coop.'!I20+'C. Financ.'!I20 -> 20192.115 | ... R20: =+'Bcos. Públ.'!R20+'Bcos. Priv.'!R19+'Coop.'!R20+'C. Financ.'!R20 -> -6.392077 | T20: =+'Bcos. Públ.'!T20+'Bcos. Priv.'!T19+'Coop.'!T20+'C. Financ.'!T20 -> 33700.185 | U20: =+'Bcos. Públ.'!U20+'Bcos. Priv.'!U19+'Coop.'!U20+'C. Financ.'!U20 -> 8947.055 | V20: =+'Bcos. Públ.'!V20+'Bcos. Priv.'!V19+'Coop.'!V20+'C. Financ.'!V20 -> 42647.24 | W20: =+'Bcos. Públ.'!W20+'Bcos. Priv.'!W19+'Coop.'!W20+'C. Financ.'!W20 -> 4619.34 | X20: =+'Bcos. Públ.'!X20+'Bcos. Priv.'!X19+'Coop.'!X20+'C. Financ.'!X20 -> 0 | Y20: =+'Bcos. Públ.'!Y20+'Bcos. Priv.'!Y19+'Coop.'!Y20+'C. Financ.'!Y20 -> 4631.005 | Z20: =+'Bcos. Públ.'!Z20+'Bcos. Priv.'!Z19+'Coop.'!Z20+'C. Financ.'!Z20 -> 38319.525 | AA20: =+'Bcos. Públ.'!AA20+'Bcos. Priv.'!AA19+'Coop.'!AA20+'C. Financ.'!AA20 -> 8947.055 | ... AM20: =+'Bcos. Públ.'!AM20+'Bcos. Priv.'!AM19+'Coop.'!AM20+'C. Financ.'!AM20 -> 1.5261523
A21: 36404 | B21: =+'Bcos. Públ.'!B21+'Bcos. Priv.'!B20+'Coop.'!B21+'C. Financ.'!B21 -> 92452.14 | C21: =+'Bcos. Públ.'!C21+'Bcos. Priv.'!C20+'Coop.'!C21+'C. Financ.'!C21 -> 20673.18 | D21: =+'Bcos. Públ.'!D21+'Bcos. Priv.'!D20+'Coop.'!D21+'C. Financ.'!D21 -> 113136.98 | E21: =+'Bcos. Públ.'!E21+'Bcos. Priv.'!E20+'Coop.'!E21+'C. Financ.'!E21 -> 9642.82 | F21: =+'Bcos. Públ.'!F21+'Bcos. Priv.'!F20+'Coop.'!F21+'C. Financ.'!F21 -> 198.22 | G21: =+'Bcos. Públ.'!G21+'Bcos. Priv.'!G20+'Coop.'!G21+'C. Financ.'!G21 -> 9852.7 | H21: =+'Bcos. Públ.'!H21+'Bcos. Priv.'!H20+'Coop.'!H21+'C. Financ.'!H21 -> 102129.94 | I21: =+'Bcos. Públ.'!I21+'Bcos. Priv.'!I20+'Coop.'!I21+'C. Financ.'!I21 -> 20883.06 | ... R21: =+'Bcos. Públ.'!R21+'Bcos. Priv.'!R20+'Coop.'!R21+'C. Financ.'!R21 -> 0.59396752 | T21: =+'Bcos. Públ.'!T21+'Bcos. Priv.'!T20+'Coop.'!T21+'C. Financ.'!T21 -> 33930.6 | U21: =+'Bcos. Públ.'!U21+'Bcos. Priv.'!U20+'Coop.'!U21+'C. Financ.'!U21 -> 9328 | V21: =+'Bcos. Públ.'!V21+'Bcos. Priv.'!V20+'Coop.'!V21+'C. Financ.'!V21 -> 43270.26 | W21: =+'Bcos. Públ.'!W21+'Bcos. Priv.'!W20+'Coop.'!W21+'C. Financ.'!W21 -> 4687.32 | X21: =+'Bcos. Públ.'!X21+'Bcos. Priv.'!X20+'Coop.'!X21+'C. Financ.'!X21 -> 0 | Y21: =+'Bcos. Públ.'!Y21+'Bcos. Priv.'!Y20+'Coop.'!Y21+'C. Financ.'!Y21 -> 4698.98 | Z21: =+'Bcos. Públ.'!Z21+'Bcos. Priv.'!Z20+'Coop.'!Z21+'C. Financ.'!Z21 -> 38617.92 | AA21: =+'Bcos. Públ.'!AA21+'Bcos. Priv.'!AA20+'Coop.'!AA21+'C. Financ.'!AA21 -> 9328 | ... AM21: =+'Bcos. Públ.'!AM21+'Bcos. Priv.'!AM20+'Coop.'!AM21+'C. Financ.'!AM21 -> 2.169202
A22: 36434 | B22: =+'Bcos. Públ.'!B22+'Bcos. Priv.'!B21+'Coop.'!B22+'C. Financ.'!B22 -> 92490.58 | C22: =+'Bcos. Públ.'!C22+'Bcos. Priv.'!C21+'Coop.'!C22+'C. Financ.'!C22 -> 21427.64 | D22: =+'Bcos. Públ.'!D22+'Bcos. Priv.'!D21+'Coop.'!D22+'C. Financ.'!D22 -> 113929.79 | E22: =+'Bcos. Públ.'!E22+'Bcos. Priv.'!E21+'Coop.'!E22+'C. Financ.'!E22 -> 9707.23 | F22: =+'Bcos. Públ.'!F22+'Bcos. Priv.'!F21+'Coop.'!F22+'C. Financ.'!F22 -> 104.13 | G22: =+'Bcos. Públ.'!G22+'Bcos. Priv.'!G21+'Coop.'!G22+'C. Financ.'!G22 -> 9822.93 | H22: =+'Bcos. Públ.'!H22+'Bcos. Priv.'!H21+'Coop.'!H22+'C. Financ.'!H22 -> 102209.38 | I22: =+'Bcos. Públ.'!I22+'Bcos. Priv.'!I21+'Coop.'!I22+'C. Financ.'!I22 -> 21543.34 | ... R22: =+'Bcos. Públ.'!R22+'Bcos. Priv.'!R21+'Coop.'!R22+'C. Financ.'!R22 -> 0.36367337 | T22: =+'Bcos. Públ.'!T22+'Bcos. Priv.'!T21+'Coop.'!T22+'C. Financ.'!T22 -> 33853.82 | U22: =+'Bcos. Públ.'!U22+'Bcos. Priv.'!U21+'Coop.'!U22+'C. Financ.'!U22 -> 9672.52 | V22: =+'Bcos. Públ.'!V22+'Bcos. Priv.'!V21+'Coop.'!V22+'C. Financ.'!V22 -> 43526.34 | W22: =+'Bcos. Públ.'!W22+'Bcos. Priv.'!W21+'Coop.'!W22+'C. Financ.'!W22 -> 4685.85 | X22: =+'Bcos. Públ.'!X22+'Bcos. Priv.'!X21+'Coop.'!X22+'C. Financ.'!X22 -> 0 | Y22: =+'Bcos. Públ.'!Y22+'Bcos. Priv.'!Y21+'Coop.'!Y22+'C. Financ.'!Y22 -> 4697.42 | Z22: =+'Bcos. Públ.'!Z22+'Bcos. Priv.'!Z21+'Coop.'!Z22+'C. Financ.'!Z22 -> 38539.67 | AA22: =+'Bcos. Públ.'!AA22+'Bcos. Priv.'!AA21+'Coop.'!AA22+'C. Financ.'!AA22 -> 9684.09 | ... AM22: =+'Bcos. Públ.'!AM22+'Bcos. Priv.'!AM21+'Coop.'!AM22+'C. Financ.'!AM22 -> 2.1485936
A23: 36465 | B23: =+'Bcos. Públ.'!B23+'Bcos. Priv.'!B22+'Coop.'!B23+'C. Financ.'!B23 -> 92103.275 | C23: =+'Bcos. Públ.'!C23+'Bcos. Priv.'!C22+'Coop.'!C23+'C. Financ.'!C23 -> 21989.296 | D23: =+'Bcos. Públ.'!D23+'Bcos. Priv.'!D22+'Coop.'!D23+'C. Financ.'!D23 -> 114081.02 | E23: =+'Bcos. Públ.'!E23+'Bcos. Priv.'!E22+'Coop.'!E23+'C. Financ.'!E23 -> 9966.787 | F23: =+'Bcos. Públ.'!F23+'Bcos. Priv.'!F22+'Coop.'!F23+'C. Financ.'!F23 -> 196.333 | G23: =+'Bcos. Públ.'!G23+'Bcos. Priv.'!G22+'Coop.'!G23+'C. Financ.'!G23 -> 10163.12 | H23: =+'Bcos. Públ.'!H23+'Bcos. Priv.'!H22+'Coop.'!H23+'C. Financ.'!H23 -> 102070.06 | I23: =+'Bcos. Públ.'!I23+'Bcos. Priv.'!I22+'Coop.'!I23+'C. Financ.'!I23 -> 22185.629 | ... R23: =+'Bcos. Públ.'!R23+'Bcos. Priv.'!R22+'Coop.'!R23+'C. Financ.'!R23 -> 39.242886 | T23: =+'Bcos. Públ.'!T23+'Bcos. Priv.'!T22+'Coop.'!T23+'C. Financ.'!T23 -> 33803.923 | U23: =+'Bcos. Públ.'!U23+'Bcos. Priv.'!U22+'Coop.'!U23+'C. Financ.'!U23 -> 9909.042 | V23: =+'Bcos. Públ.'!V23+'Bcos. Priv.'!V22+'Coop.'!V23+'C. Financ.'!V23 -> 43747.612 | W23: =+'Bcos. Públ.'!W23+'Bcos. Priv.'!W22+'Coop.'!W23+'C. Financ.'!W23 -> 4769.737 | X23: =+'Bcos. Públ.'!X23+'Bcos. Priv.'!X22+'Coop.'!X23+'C. Financ.'!X23 -> 11.549 | Y23: =+'Bcos. Públ.'!Y23+'Bcos. Priv.'!Y22+'Coop.'!Y23+'C. Financ.'!Y23 -> 4781.286 | Z23: =+'Bcos. Públ.'!Z23+'Bcos. Priv.'!Z22+'Coop.'!Z23+'C. Financ.'!Z23 -> 38585.209 | AA23: =+'Bcos. Públ.'!AA23+'Bcos. Priv.'!AA22+'Coop.'!AA23+'C. Financ.'!AA23 -> 9932.14 | ... AM23: =+'Bcos. Públ.'!AM23+'Bcos. Priv.'!AM22+'Coop.'!AM23+'C. Financ.'!AM23 -> 1.8758141
A24: 36495 | B24: =+'Bcos. Públ.'!B24+'Bcos. Priv.'!B23+'Coop.'!B24+'C. Financ.'!B24 -> 93674.975 | C24: =+'Bcos. Públ.'!C24+'Bcos. Priv.'!C23+'Coop.'!C24+'C. Financ.'!C24 -> 22800.245 | D24: =+'Bcos. Públ.'!D24+'Bcos. Priv.'!D23+'Coop.'!D24+'C. Financ.'!D24 -> 116463.6 | E24: =+'Bcos. Públ.'!E24+'Bcos. Priv.'!E23+'Coop.'!E24+'C. Financ.'!E24 -> 9977.285 | F24: =+'Bcos. Públ.'!F24+'Bcos. Priv.'!F23+'Coop.'!F24+'C. Financ.'!F24 -> 220.685 | G24: =+'Bcos. Públ.'!G24+'Bcos. Priv.'!G23+'Coop.'!G24+'C. Financ.'!G24 -> 10209.585 | H24: =+'Bcos. Públ.'!H24+'Bcos. Priv.'!H23+'Coop.'!H24+'C. Financ.'!H24 -> 103663.87 | I24: =+'Bcos. Públ.'!I24+'Bcos. Priv.'!I23+'Coop.'!I24+'C. Financ.'!I24 -> 23009.315 | ... R24: =+'Bcos. Públ.'!R24+'Bcos. Priv.'!R23+'Coop.'!R24+'C. Financ.'!R24 -> -0.28836285 | T24: =+'Bcos. Públ.'!T24+'Bcos. Priv.'!T23+'Coop.'!T24+'C. Financ.'!T24 -> 34937.92 | U24: =+'Bcos. Públ.'!U24+'Bcos. Priv.'!U23+'Coop.'!U24+'C. Financ.'!U24 -> 10592.88 | V24: =+'Bcos. Públ.'!V24+'Bcos. Priv.'!V23+'Coop.'!V24+'C. Financ.'!V24 -> 45530.8 | W24: =+'Bcos. Públ.'!W24+'Bcos. Priv.'!W23+'Coop.'!W24+'C. Financ.'!W24 -> 4750.535 | X24: =+'Bcos. Públ.'!X24+'Bcos. Priv.'!X23+'Coop.'!X24+'C. Financ.'!X24 -> 11.615 | Y24: =+'Bcos. Públ.'!Y24+'Bcos. Priv.'!Y23+'Coop.'!Y24+'C. Financ.'!Y24 -> 4762.15 | Z24: =+'Bcos. Públ.'!Z24+'Bcos. Priv.'!Z23+'Coop.'!Z24+'C. Financ.'!Z24 -> 39688.455 | AA24: =+'Bcos. Públ.'!AA24+'Bcos. Priv.'!AA23+'Coop.'!AA24+'C. Financ.'!AA24 -> 10592.88 | ... AM24: =+'Bcos. Públ.'!AM24+'Bcos. Priv.'!AM23+'Coop.'!AM24+'C. Financ.'!AM24 -> 4.9417908
... A207: 42064 | B207: =+'Bcos. Públ.'!B207+'Bcos. Priv.'!B206+'Coop.'!B207+'C. Financ.'!B207 -> 359677.74 | C207: =+'Bcos. Públ.'!C207+'Bcos. Priv.'!C206+'Coop.'!C207+'C. Financ.'!C207 -> 8113.2624 | D207: =+'Bcos. Públ.'!D207+'Bcos. Priv.'!D206+'Coop.'!D207+'C. Financ.'!D207 -> 367791 | E207: =+'Bcos. Públ.'!E207+'Bcos. Priv.'!E206+'Coop.'!E207+'C. Financ.'!E207 -> 29792.428 | F207: =+'Bcos. Públ.'!F207+'Bcos. Priv.'!F206+'Coop.'!F207+'C. Financ.'!F207 -> 3.1108619 | G207: =+'Bcos. Públ.'!G207+'Bcos. Priv.'!G206+'Coop.'!G207+'C. Financ.'!G207 -> 29795.539 | H207: =+'Bcos. Públ.'!H207+'Bcos. Priv.'!H206+'Coop.'!H207+'C. Financ.'!H207 -> 389470.17 | I207: =+'Bcos. Públ.'!I207+'Bcos. Priv.'!I206+'Coop.'!I207+'C. Financ.'!I207 -> 8116.3733 | ... R207: =+'Bcos. Públ.'!R207+'Bcos. Priv.'!R206+'Coop.'!R207+'C. Financ.'!R207 -> 7.2521918 | T207: =+'Bcos. Públ.'!T207+'Bcos. Priv.'!T206+'Coop.'!T207+'C. Financ.'!T207 -> 154192.48 | U207: =+'Bcos. Públ.'!U207+'Bcos. Priv.'!U206+'Coop.'!U207+'C. Financ.'!U207 -> 3985.5246 | V207: =+'Bcos. Públ.'!V207+'Bcos. Priv.'!V206+'Coop.'!V207+'C. Financ.'!V207 -> 158178.01 | W207: =+'Bcos. Públ.'!W207+'Bcos. Priv.'!W206+'Coop.'!W207+'C. Financ.'!W207 -> 22669.778 | X207: =+'Bcos. Públ.'!X207+'Bcos. Priv.'!X206+'Coop.'!X207+'C. Financ.'!X207 -> 3.1080824 | Y207: =+'Bcos. Públ.'!Y207+'Bcos. Priv.'!Y206+'Coop.'!Y207+'C. Financ.'!Y207 -> 22672.886 | Z207: =+'Bcos. Públ.'!Z207+'Bcos. Priv.'!Z206+'Coop.'!Z207+'C. Financ.'!Z207 -> 176862.26 | AA207: =+'Bcos. Públ.'!AA207+'Bcos. Priv.'!AA206+'Coop.'!AA207+'C. Financ.'!AA207 -> 3988.6327 | ... AM207: =+'Bcos. Públ.'!AM207+'Bcos. Priv.'!AM206+'Coop.'!AM207+'C. Financ.'!AM207 -> -0.85851666
A208: =+'Bcos. Públ.'!A208 -> 42095 | B208: =+'Bcos. Públ.'!B208+'Bcos. Priv.'!B207+'Coop.'!B208+'C. Financ.'!B208 -> 369179.12 | C208: =+'Bcos. Públ.'!C208+'Bcos. Priv.'!C207+'Coop.'!C208+'C. Financ.'!C208 -> 8248.0754 | D208: =+'Bcos. Públ.'!D208+'Bcos. Priv.'!D207+'Coop.'!D208+'C. Financ.'!D208 -> 377427.19 | E208: =+'Bcos. Públ.'!E208+'Bcos. Priv.'!E207+'Coop.'!E208+'C. Financ.'!E208 -> 23051.749 | F208: =+'Bcos. Públ.'!F208+'Bcos. Priv.'!F207+'Coop.'!F208+'C. Financ.'!F208 -> 3.0705923 | G208: =+'Bcos. Públ.'!G208+'Bcos. Priv.'!G207+'Coop.'!G208+'C. Financ.'!G208 -> 23054.82 | H208: =+'Bcos. Públ.'!H208+'Bcos. Priv.'!H207+'Coop.'!H208+'C. Financ.'!H208 -> 392230.87 | I208: =+'Bcos. Públ.'!I208+'Bcos. Priv.'!I207+'Coop.'!I208+'C. Financ.'!I208 -> 8251.146 | ... R208: =+'Bcos. Públ.'!R208+'Bcos. Priv.'!R207+'Coop.'!R208+'C. Financ.'!R208 -> 2.4291014 | T208: =+'Bcos. Públ.'!T208+'Bcos. Priv.'!T207+'Coop.'!T208+'C. Financ.'!T208 -> 155786.64 | U208: =+'Bcos. Públ.'!U208+'Bcos. Priv.'!U207+'Coop.'!U208+'C. Financ.'!U208 -> 4047.3559 | V208: =+'Bcos. Públ.'!V208+'Bcos. Priv.'!V207+'Coop.'!V208+'C. Financ.'!V208 -> 159834 | W208: =+'Bcos. Públ.'!W208+'Bcos. Priv.'!W207+'Coop.'!W208+'C. Financ.'!W208 -> 15722.318 | X208: =+'Bcos. Públ.'!X208+'Bcos. Priv.'!X207+'Coop.'!X208+'C. Financ.'!X208 -> 3.0677365 | Y208: =+'Bcos. Públ.'!Y208+'Bcos. Priv.'!Y207+'Coop.'!Y208+'C. Financ.'!Y208 -> 15725.386 | Z208: =+'Bcos. Públ.'!Z208+'Bcos. Priv.'!Z207+'Coop.'!Z208+'C. Financ.'!Z208 -> 171508.96 | AA208: =+'Bcos. Públ.'!AA208+'Bcos. Priv.'!AA207+'Coop.'!AA208+'C. Financ.'!AA208 -> 4050.4237 | ... AM208: =+'Bcos. Públ.'!AM208+'Bcos. Priv.'!AM207+'Coop.'!AM208+'C. Financ.'!AM208 -> -2.4712444
A209: =+'Bcos. Públ.'!A209 -> 42125 | B209: =+'Bcos. Públ.'!B209+'Bcos. Priv.'!B208+'Coop.'!B209+'C. Financ.'!B209 -> 373502.9 | C209: =+'Bcos. Públ.'!C209+'Bcos. Priv.'!C208+'Coop.'!C209+'C. Financ.'!C209 -> 8663.3298 | D209: =+'Bcos. Públ.'!D209+'Bcos. Priv.'!D208+'Coop.'!D209+'C. Financ.'!D209 -> 382166.23 | E209: =+'Bcos. Públ.'!E209+'Bcos. Priv.'!E208+'Coop.'!E209+'C. Financ.'!E209 -> 24314.895 | F209: =+'Bcos. Públ.'!F209+'Bcos. Priv.'!F208+'Coop.'!F209+'C. Financ.'!F209 -> 3.0429783 | G209: =+'Bcos. Públ.'!G209+'Bcos. Priv.'!G208+'Coop.'!G209+'C. Financ.'!G209 -> 24317.938 | H209: =+'Bcos. Públ.'!H209+'Bcos. Priv.'!H208+'Coop.'!H209+'C. Financ.'!H209 -> 397817.8 | I209: =+'Bcos. Públ.'!I209+'Bcos. Priv.'!I208+'Coop.'!I209+'C. Financ.'!I209 -> 8666.3728 | ... R209: =+'Bcos. Públ.'!R209+'Bcos. Priv.'!R208+'Coop.'!R209+'C. Financ.'!R209 -> -4.638054 | T209: =+'Bcos. Públ.'!T209+'Bcos. Priv.'!T208+'Coop.'!T209+'C. Financ.'!T209 -> 157277.52 | U209: =+'Bcos. Públ.'!U209+'Bcos. Priv.'!U208+'Coop.'!U209+'C. Financ.'!U209 -> 4235.3256 | V209: =+'Bcos. Públ.'!V209+'Bcos. Priv.'!V208+'Coop.'!V209+'C. Financ.'!V209 -> 161512.85 | W209: =+'Bcos. Públ.'!W209+'Bcos. Priv.'!W208+'Coop.'!W209+'C. Financ.'!W209 -> 16839.26 | X209: =+'Bcos. Públ.'!X209+'Bcos. Priv.'!X208+'Coop.'!X209+'C. Financ.'!X209 -> 3.0400798 | Y209: =+'Bcos. Públ.'!Y209+'Bcos. Priv.'!Y208+'Coop.'!Y209+'C. Financ.'!Y209 -> 16842.3 | Z209: =+'Bcos. Públ.'!Z209+'Bcos. Priv.'!Z208+'Coop.'!Z209+'C. Financ.'!Z209 -> 174116.78 | AA209: =+'Bcos. Públ.'!AA209+'Bcos. Priv.'!AA208+'Coop.'!AA209+'C. Financ.'!AA209 -> 4238.3656 | ... AM209: =+'Bcos. Públ.'!AM209+'Bcos. Priv.'!AM208+'Coop.'!AM209+'C. Financ.'!AM209 -> -2.3691118
A210: =+'Bcos. Públ.'!A210 -> 42156 | B210: =+'Bcos. Públ.'!B210+'Bcos. Priv.'!B209+'Coop.'!B210+'C. Financ.'!B210 -> 377974.48 | C210: =+'Bcos. Públ.'!C210+'Bcos. Priv.'!C209+'Coop.'!C210+'C. Financ.'!C210 -> 8680.9867 | D210: =+'Bcos. Públ.'!D210+'Bcos. Priv.'!D209+'Coop.'!D210+'C. Financ.'!D210 -> 386655.47 | E210: =+'Bcos. Públ.'!E210+'Bcos. Priv.'!E209+'Coop.'!E210+'C. Financ.'!E210 -> 23347.485 | F210: =+'Bcos. Públ.'!F210+'Bcos. Priv.'!F209+'Coop.'!F210+'C. Financ.'!F210 -> 2.9864851 | G210: =+'Bcos. Públ.'!G210+'Bcos. Priv.'!G209+'Coop.'!G210+'C. Financ.'!G210 -> 23350.472 | H210: =+'Bcos. Públ.'!H210+'Bcos. Priv.'!H209+'Coop.'!H210+'C. Financ.'!H210 -> 401321.97 | I210: =+'Bcos. Públ.'!I210+'Bcos. Priv.'!I209+'Coop.'!I210+'C. Financ.'!I210 -> 8683.9731 | ... R210: =+'Bcos. Públ.'!R210+'Bcos. Priv.'!R209+'Coop.'!R210+'C. Financ.'!R210 -> 0.26064307 | T210: =+'Bcos. Públ.'!T210+'Bcos. Priv.'!T209+'Coop.'!T210+'C. Financ.'!T210 -> 159420.67 | U210: =+'Bcos. Públ.'!U210+'Bcos. Priv.'!U209+'Coop.'!U210+'C. Financ.'!U210 -> 4207.4126 | V210: =+'Bcos. Públ.'!V210+'Bcos. Priv.'!V209+'Coop.'!V210+'C. Financ.'!V210 -> 163628.09 | W210: =+'Bcos. Públ.'!W210+'Bcos. Priv.'!W209+'Coop.'!W210+'C. Financ.'!W210 -> 16115.019 | X210: =+'Bcos. Públ.'!X210+'Bcos. Priv.'!X209+'Coop.'!X210+'C. Financ.'!X210 -> 2.9855393 | Y210: =+'Bcos. Públ.'!Y210+'Bcos. Priv.'!Y209+'Coop.'!Y210+'C. Financ.'!Y210 -> 16118.004 | Z210: =+'Bcos. Públ.'!Z210+'Bcos. Priv.'!Z209+'Coop.'!Z210+'C. Financ.'!Z210 -> 175535.69 | AA210: =+'Bcos. Públ.'!AA210+'Bcos. Priv.'!AA209+'Coop.'!AA210+'C. Financ.'!AA210 -> 4210.3981 | ... AM210: =+'Bcos. Públ.'!AM210+'Bcos. Priv.'!AM209+'Coop.'!AM210+'C. Financ.'!AM210 -> 5.0212135
A211: =+'Bcos. Públ.'!A211 -> 42186 | B211: =+'Bcos. Públ.'!B211+'Bcos. Priv.'!B210+'Coop.'!B211+'C. Financ.'!B211 -> 388883.66 | C211: =+'Bcos. Públ.'!C211+'Bcos. Priv.'!C210+'Coop.'!C211+'C. Financ.'!C211 -> 8816.4696 | D211: =+'Bcos. Públ.'!D211+'Bcos. Priv.'!D210+'Coop.'!D211+'C. Financ.'!D211 -> 397700.12 | E211: =+'Bcos. Públ.'!E211+'Bcos. Priv.'!E210+'Coop.'!E211+'C. Financ.'!E211 -> 23042.939 | F211: =+'Bcos. Públ.'!F211+'Bcos. Priv.'!F210+'Coop.'!F211+'C. Financ.'!F211 -> 1.7475546 | G211: =+'Bcos. Públ.'!G211+'Bcos. Priv.'!G210+'Coop.'!G211+'C. Financ.'!G211 -> 23044.687 | H211: =+'Bcos. Públ.'!H211+'Bcos. Priv.'!H210+'Coop.'!H211+'C. Financ.'!H211 -> 411926.59 | I211: =+'Bcos. Públ.'!I211+'Bcos. Priv.'!I210+'Coop.'!I211+'C. Financ.'!I211 -> 8818.2171 | ... R211: =+'Bcos. Públ.'!R211+'Bcos. Priv.'!R210+'Coop.'!R211+'C. Financ.'!R211 -> -8.2069582 | T211: =+'Bcos. Públ.'!T211+'Bcos. Priv.'!T210+'Coop.'!T211+'C. Financ.'!T211 -> 161172 | U211: =+'Bcos. Públ.'!U211+'Bcos. Priv.'!U210+'Coop.'!U211+'C. Financ.'!U211 -> 4253.8542 | V211: =+'Bcos. Públ.'!V211+'Bcos. Priv.'!V210+'Coop.'!V211+'C. Financ.'!V211 -> 165425.85 | W211: =+'Bcos. Públ.'!W211+'Bcos. Priv.'!W210+'Coop.'!W211+'C. Financ.'!W211 -> 15525.617 | X211: =+'Bcos. Públ.'!X211+'Bcos. Priv.'!X210+'Coop.'!X211+'C. Financ.'!X211 -> 1.7465579 | Y211: =+'Bcos. Públ.'!Y211+'Bcos. Priv.'!Y210+'Coop.'!Y211+'C. Financ.'!Y211 -> 15527.364 | Z211: =+'Bcos. Públ.'!Z211+'Bcos. Priv.'!Z210+'Coop.'!Z211+'C. Financ.'!Z211 -> 176697.62 | AA211: =+'Bcos. Públ.'!AA211+'Bcos. Priv.'!AA210+'Coop.'!AA211+'C. Financ.'!AA211 -> 4255.6008 | ... AM211: =+'Bcos. Públ.'!AM211+'Bcos. Priv.'!AM210+'Coop.'!AM211+'C. Financ.'!AM211 -> 8.7349939
A212: =+'Bcos. Públ.'!A212 -> 42217 | B212: =+'Bcos. Públ.'!B212+'Bcos. Priv.'!B211+'Coop.'!B212+'C. Financ.'!B212 -> 386077.71 | C212: =+'Bcos. Públ.'!C212+'Bcos. Priv.'!C211+'Coop.'!C212+'C. Financ.'!C212 -> 9453.27 | D212: =+'Bcos. Públ.'!D212+'Bcos. Priv.'!D211+'Coop.'!D212+'C. Financ.'!D212 -> 395530.98 | E212: =+'Bcos. Públ.'!E212+'Bcos. Priv.'!E211+'Coop.'!E212+'C. Financ.'!E212 -> 24902.113 | F212: =+'Bcos. Públ.'!F212+'Bcos. Priv.'!F211+'Coop.'!F212+'C. Financ.'!F212 -> 20.116469 | G212: =+'Bcos. Públ.'!G212+'Bcos. Priv.'!G211+'Coop.'!G212+'C. Financ.'!G212 -> 24922.229 | H212: =+'Bcos. Públ.'!H212+'Bcos. Priv.'!H211+'Coop.'!H212+'C. Financ.'!H212 -> 410979.82 | I212: =+'Bcos. Públ.'!I212+'Bcos. Priv.'!I211+'Coop.'!I212+'C. Financ.'!I212 -> 9473.3865 | ... R212: =+'Bcos. Públ.'!R212+'Bcos. Priv.'!R211+'Coop.'!R212+'C. Financ.'!R212 -> -4.1199054 | T212: =+'Bcos. Públ.'!T212+'Bcos. Priv.'!T211+'Coop.'!T212+'C. Financ.'!T212 -> 162036.4 | U212: =+'Bcos. Públ.'!U212+'Bcos. Priv.'!U211+'Coop.'!U212+'C. Financ.'!U212 -> 4512.2832 | V212: =+'Bcos. Públ.'!V212+'Bcos. Priv.'!V211+'Coop.'!V212+'C. Financ.'!V212 -> 166548.68 | W212: =+'Bcos. Públ.'!W212+'Bcos. Priv.'!W211+'Coop.'!W212+'C. Financ.'!W212 -> 16935.717 | X212: =+'Bcos. Públ.'!X212+'Bcos. Priv.'!X211+'Coop.'!X212+'C. Financ.'!X212 -> 20.11547 | Y212: =+'Bcos. Públ.'!Y212+'Bcos. Priv.'!Y211+'Coop.'!Y212+'C. Financ.'!Y212 -> 16955.832 | Z212: =+'Bcos. Públ.'!Z212+'Bcos. Priv.'!Z211+'Coop.'!Z212+'C. Financ.'!Z212 -> 178972.11 | AA212: =+'Bcos. Públ.'!AA212+'Bcos. Priv.'!AA211+'Coop.'!AA212+'C. Financ.'!AA212 -> 4532.3987 | ... AM212: =+'Bcos. Públ.'!AM212+'Bcos. Priv.'!AM211+'Coop.'!AM212+'C. Financ.'!AM212 -> 3.329233
A213: =+'Bcos. Públ.'!A213 -> 42248 | B213: =+'Bcos. Públ.'!B213+'Bcos. Priv.'!B212+'Coop.'!B213+'C. Financ.'!B213 -> 393701.48 | C213: =+'Bcos. Públ.'!C213+'Bcos. Priv.'!C212+'Coop.'!C213+'C. Financ.'!C213 -> 9480.5624 | D213: =+'Bcos. Públ.'!D213+'Bcos. Priv.'!D212+'Coop.'!D213+'C. Financ.'!D213 -> 403182.04 | E213: =+'Bcos. Públ.'!E213+'Bcos. Priv.'!E212+'Coop.'!E213+'C. Financ.'!E213 -> 25819.334 | F213: =+'Bcos. Públ.'!F213+'Bcos. Priv.'!F212+'Coop.'!F213+'C. Financ.'!F213 -> 20.354319 | G213: =+'Bcos. Públ.'!G213+'Bcos. Priv.'!G212+'Coop.'!G213+'C. Financ.'!G213 -> 25839.689 | H213: =+'Bcos. Públ.'!H213+'Bcos. Priv.'!H212+'Coop.'!H213+'C. Financ.'!H213 -> 419520.81 | I213: =+'Bcos. Públ.'!I213+'Bcos. Priv.'!I212+'Coop.'!I213+'C. Financ.'!I213 -> 9500.9167 | ... R213: =+'Bcos. Públ.'!R213+'Bcos. Priv.'!R212+'Coop.'!R213+'C. Financ.'!R213 -> -503.18165 | T213: =+'Bcos. Públ.'!T213+'Bcos. Priv.'!T212+'Coop.'!T213+'C. Financ.'!T213 -> 166002.42 | U213: =+'Bcos. Públ.'!U213+'Bcos. Priv.'!U212+'Coop.'!U213+'C. Financ.'!U213 -> 4631.2034 | V213: =+'Bcos. Públ.'!V213+'Bcos. Priv.'!V212+'Coop.'!V213+'C. Financ.'!V213 -> 170633.62 | W213: =+'Bcos. Públ.'!W213+'Bcos. Priv.'!W212+'Coop.'!W213+'C. Financ.'!W213 -> 17550.286 | X213: =+'Bcos. Públ.'!X213+'Bcos. Priv.'!X212+'Coop.'!X213+'C. Financ.'!X213 -> 20.3533 | Y213: =+'Bcos. Públ.'!Y213+'Bcos. Priv.'!Y212+'Coop.'!Y213+'C. Financ.'!Y213 -> 17570.64 | Z213: =+'Bcos. Públ.'!Z213+'Bcos. Priv.'!Z212+'Coop.'!Z213+'C. Financ.'!Z213 -> 183552.71 | AA213: =+'Bcos. Públ.'!AA213+'Bcos. Priv.'!AA212+'Coop.'!AA213+'C. Financ.'!AA213 -> 4651.5567 | ... AM213: =+'Bcos. Públ.'!AM213+'Bcos. Priv.'!AM212+'Coop.'!AM213+'C. Financ.'!AM213 -> 6.7600718
A214: =+'Bcos. Públ.'!A214 -> 42278 | B214: =+'Bcos. Públ.'!B214+'Bcos. Priv.'!B213+'Coop.'!B214+'C. Financ.'!B214 -> 399055.25 | C214: =+'Bcos. Públ.'!C214+'Bcos. Priv.'!C213+'Coop.'!C214+'C. Financ.'!C214 -> 9544.7666 | D214: =+'Bcos. Públ.'!D214+'Bcos. Priv.'!D213+'Coop.'!D214+'C. Financ.'!D214 -> 408600.01 | E214: =+'Bcos. Públ.'!E214+'Bcos. Priv.'!E213+'Coop.'!E214+'C. Financ.'!E214 -> 27309.06 | F214: =+'Bcos. Públ.'!F214+'Bcos. Priv.'!F213+'Coop.'!F214+'C. Financ.'!F214 -> 0.0091756904 | G214: =+'Bcos. Públ.'!G214+'Bcos. Priv.'!G213+'Coop.'!G214+'C. Financ.'!G214 -> 27309.07 | H214: =+'Bcos. Públ.'!H214+'Bcos. Priv.'!H213+'Coop.'!H214+'C. Financ.'!H214 -> 426364.31 | I214: =+'Bcos. Públ.'!I214+'Bcos. Priv.'!I213+'Coop.'!I214+'C. Financ.'!I214 -> 9544.7758 | ... R214: =+'Bcos. Públ.'!R214+'Bcos. Priv.'!R213+'Coop.'!R214+'C. Financ.'!R214 -> 1.8977472 | T214: =+'Bcos. Públ.'!T214+'Bcos. Priv.'!T213+'Coop.'!T214+'C. Financ.'!T214 -> 169159.31 | U214: =+'Bcos. Públ.'!U214+'Bcos. Priv.'!U213+'Coop.'!U214+'C. Financ.'!U214 -> 4656.3762 | V214: =+'Bcos. Públ.'!V214+'Bcos. Priv.'!V213+'Coop.'!V214+'C. Financ.'!V214 -> 173815.68 | W214: =+'Bcos. Públ.'!W214+'Bcos. Priv.'!W213+'Coop.'!W214+'C. Financ.'!W214 -> 17456.774 | X214: =+'Bcos. Públ.'!X214+'Bcos. Priv.'!X213+'Coop.'!X214+'C. Financ.'!X214 -> 0.0060923712 | Y214: =+'Bcos. Públ.'!Y214+'Bcos. Priv.'!Y213+'Coop.'!Y214+'C. Financ.'!Y214 -> 17456.78 | Z214: =+'Bcos. Públ.'!Z214+'Bcos. Priv.'!Z213+'Coop.'!Z214+'C. Financ.'!Z214 -> 186616.08 | AA214: =+'Bcos. Públ.'!AA214+'Bcos. Priv.'!AA213+'Coop.'!AA214+'C. Financ.'!AA214 -> 4656.3823 | ... AM214: =+'Bcos. Públ.'!AM214+'Bcos. Priv.'!AM213+'Coop.'!AM214+'C. Financ.'!AM214 -> 2.4275769
A215: =+'Bcos. Públ.'!A215 -> 42309 | B215: =+'Bcos. Públ.'!B215+'Bcos. Priv.'!B214+'Coop.'!B215+'C. Financ.'!B215 -> 404399.03 | C215: =+'Bcos. Públ.'!C215+'Bcos. Priv.'!C214+'Coop.'!C215+'C. Financ.'!C215 -> 10362.153 | D215: =+'Bcos. Públ.'!D215+'Bcos. Priv.'!D214+'Coop.'!D215+'C. Financ.'!D215 -> 414761.18 | E215: =+'Bcos. Públ.'!E215+'Bcos. Priv.'!E214+'Coop.'!E215+'C. Financ.'!E215 -> 28180.85 | F215: =+'Bcos. Públ.'!F215+'Bcos. Priv.'!F214+'Coop.'!F215+'C. Financ.'!F215 -> 0.0086750897 | G215: =+'Bcos. Públ.'!G215+'Bcos. Priv.'!G214+'Coop.'!G215+'C. Financ.'!G215 -> 28180.859 | H215: =+'Bcos. Públ.'!H215+'Bcos. Priv.'!H214+'Coop.'!H215+'C. Financ.'!H215 -> 432579.88 | I215: =+'Bcos. Públ.'!I215+'Bcos. Priv.'!I214+'Coop.'!I215+'C. Financ.'!I215 -> 10362.162 | ... R215: =+'Bcos. Públ.'!R215+'Bcos. Priv.'!R214+'Coop.'!R215+'C. Financ.'!R215 -> -5.2467605 | T215: =+'Bcos. Públ.'!T215+'Bcos. Priv.'!T214+'Coop.'!T215+'C. Financ.'!T215 -> 173925.43 | U215: =+'Bcos. Públ.'!U215+'Bcos. Priv.'!U214+'Coop.'!U215+'C. Financ.'!U215 -> 4886.5358 | V215: =+'Bcos. Públ.'!V215+'Bcos. Priv.'!V214+'Coop.'!V215+'C. Financ.'!V215 -> 178811.96 | W215: =+'Bcos. Públ.'!W215+'Bcos. Priv.'!W214+'Coop.'!W215+'C. Financ.'!W215 -> 18220.19 | X215: =+'Bcos. Públ.'!X215+'Bcos. Priv.'!X214+'Coop.'!X215+'C. Financ.'!X215 -> 0.0055690788 | Y215: =+'Bcos. Públ.'!Y215+'Bcos. Priv.'!Y214+'Coop.'!Y215+'C. Financ.'!Y215 -> 18220.195 | Z215: =+'Bcos. Públ.'!Z215+'Bcos. Priv.'!Z214+'Coop.'!Z215+'C. Financ.'!Z215 -> 192145.62 | AA215: =+'Bcos. Públ.'!AA215+'Bcos. Priv.'!AA214+'Coop.'!AA215+'C. Financ.'!AA215 -> 4886.5414 | ... AM215: =+'Bcos. Públ.'!AM215+'Bcos. Priv.'!AM214+'Coop.'!AM215+'C. Financ.'!AM215 -> 2.5099902
A216: =+'Bcos. Públ.'!A216 -> 42339 | B216: =+'Bcos. Públ.'!B216+'Bcos. Priv.'!B215+'Coop.'!B216+'C. Financ.'!B216 -> 418658.35 | C216: =+'Bcos. Públ.'!C216+'Bcos. Priv.'!C215+'Coop.'!C216+'C. Financ.'!C216 -> 9713.0064 | D216: =+'Bcos. Públ.'!D216+'Bcos. Priv.'!D215+'Coop.'!D216+'C. Financ.'!D216 -> 428371.36 | E216: =+'Bcos. Públ.'!E216+'Bcos. Priv.'!E215+'Coop.'!E216+'C. Financ.'!E216 -> 25455.527 | F216: =+'Bcos. Públ.'!F216+'Bcos. Priv.'!F215+'Coop.'!F216+'C. Financ.'!F216 -> 0.0087034508 | G216: =+'Bcos. Públ.'!G216+'Bcos. Priv.'!G215+'Coop.'!G216+'C. Financ.'!G216 -> 25455.536 | H216: =+'Bcos. Públ.'!H216+'Bcos. Priv.'!H215+'Coop.'!H216+'C. Financ.'!H216 -> 444113.88 | I216: =+'Bcos. Públ.'!I216+'Bcos. Priv.'!I215+'Coop.'!I216+'C. Financ.'!I216 -> 9713.0151 | ... R216: =+'Bcos. Públ.'!R216+'Bcos. Priv.'!R215+'Coop.'!R216+'C. Financ.'!R216 -> -0.84849259 | T216: =+'Bcos. Públ.'!T216+'Bcos. Priv.'!T215+'Coop.'!T216+'C. Financ.'!T216 -> 182316.74 | U216: =+'Bcos. Públ.'!U216+'Bcos. Priv.'!U215+'Coop.'!U216+'C. Financ.'!U216 -> 4755.5665 | V216: =+'Bcos. Públ.'!V216+'Bcos. Priv.'!V215+'Coop.'!V216+'C. Financ.'!V216 -> 187072.3 | W216: =+'Bcos. Públ.'!W216+'Bcos. Priv.'!W215+'Coop.'!W216+'C. Financ.'!W216 -> 16036.722 | X216: =+'Bcos. Públ.'!X216+'Bcos. Priv.'!X215+'Coop.'!X216+'C. Financ.'!X216 -> 0.0055667798 | Y216: =+'Bcos. Públ.'!Y216+'Bcos. Priv.'!Y215+'Coop.'!Y216+'C. Financ.'!Y216 -> 16036.727 | Z216: =+'Bcos. Públ.'!Z216+'Bcos. Priv.'!Z215+'Coop.'!Z216+'C. Financ.'!Z216 -> 198353.46 | AA216: =+'Bcos. Públ.'!AA216+'Bcos. Priv.'!AA215+'Coop.'!AA216+'C. Financ.'!AA216 -> 4755.572 | ... AM216: =+'Bcos. Públ.'!AM216+'Bcos. Priv.'!AM215+'Coop.'!AM216+'C. Financ.'!AM216 -> 9.1929796
A217: =+'Bcos. Públ.'!A217 -> 42370 | B217: =+'Bcos. Públ.'!B217+'Bcos. Priv.'!B216+'Coop.'!B217+'C. Financ.'!B217 -> 425811.52 | C217: =+'Bcos. Públ.'!C217+'Bcos. Priv.'!C216+'Coop.'!C217+'C. Financ.'!C217 -> 10008.448 | D217: =+'Bcos. Públ.'!D217+'Bcos. Priv.'!D216+'Coop.'!D217+'C. Financ.'!D217 -> 435819.97 | E217: =+'Bcos. Públ.'!E217+'Bcos. Priv.'!E216+'Coop.'!E217+'C. Financ.'!E217 -> 24378.993 | F217: =+'Bcos. Públ.'!F217+'Bcos. Priv.'!F216+'Coop.'!F217+'C. Financ.'!F217 -> 0.011007161 | G217: =+'Bcos. Públ.'!G217+'Bcos. Priv.'!G216+'Coop.'!G217+'C. Financ.'!G217 -> 24379.004 | H217: =+'Bcos. Públ.'!H217+'Bcos. Priv.'!H216+'Coop.'!H217+'C. Financ.'!H217 -> 450190.51 | I217: =+'Bcos. Públ.'!I217+'Bcos. Priv.'!I216+'Coop.'!I217+'C. Financ.'!I217 -> 10008.459 | ... R217: =+'Bcos. Públ.'!R217+'Bcos. Priv.'!R216+'Coop.'!R217+'C. Financ.'!R217 -> -1.7793926 | T217: =+'Bcos. Públ.'!T217+'Bcos. Priv.'!T216+'Coop.'!T217+'C. Financ.'!T217 -> 181296.55 | U217: =+'Bcos. Públ.'!U217+'Bcos. Priv.'!U216+'Coop.'!U217+'C. Financ.'!U217 -> 4918.0102 | V217: =+'Bcos. Públ.'!V217+'Bcos. Priv.'!V216+'Coop.'!V217+'C. Financ.'!V217 -> 186214.56 | W217: =+'Bcos. Públ.'!W217+'Bcos. Priv.'!W216+'Coop.'!W217+'C. Financ.'!W217 -> 15129.226 | X217: =+'Bcos. Públ.'!X217+'Bcos. Priv.'!X216+'Coop.'!X217+'C. Financ.'!X217 -> 0.0055807609 | Y217: =+'Bcos. Públ.'!Y217+'Bcos. Priv.'!Y216+'Coop.'!Y217+'C. Financ.'!Y217 -> 15129.232 | Z217: =+'Bcos. Públ.'!Z217+'Bcos. Priv.'!Z216+'Coop.'!Z217+'C. Financ.'!Z217 -> 196425.78 | AA217: =+'Bcos. Públ.'!AA217+'Bcos. Priv.'!AA216+'Coop.'!AA217+'C. Financ.'!AA217 -> 4918.0158 | ... AM217: =+'Bcos. Públ.'!AM217+'Bcos. Priv.'!AM216+'Coop.'!AM217+'C. Financ.'!AM217 -> 2.2320428
A218: =+'Bcos. Públ.'!A218 -> 42401 | B218: =+'Bcos. Públ.'!B218+'Bcos. Priv.'!B217+'Coop.'!B218+'C. Financ.'!B218 -> 436594.42 | C218: =+'Bcos. Públ.'!C218+'Bcos. Priv.'!C217+'Coop.'!C218+'C. Financ.'!C218 -> 11913.405 | D218: =+'Bcos. Públ.'!D218+'Bcos. Priv.'!D217+'Coop.'!D218+'C. Financ.'!D218 -> 448507.82 | E218: =+'Bcos. Públ.'!E218+'Bcos. Priv.'!E217+'Coop.'!E218+'C. Financ.'!E218 -> 22400.298 | F218: =+'Bcos. Públ.'!F218+'Bcos. Priv.'!F217+'Coop.'!F218+'C. Financ.'!F218 -> 0.011244281 | G218: =+'Bcos. Públ.'!G218+'Bcos. Priv.'!G217+'Coop.'!G218+'C. Financ.'!G218 -> 22400.309 | H218: =+'Bcos. Públ.'!H218+'Bcos. Priv.'!H217+'Coop.'!H218+'C. Financ.'!H218 -> 458994.72 | I218: =+'Bcos. Públ.'!I218+'Bcos. Priv.'!I217+'Coop.'!I218+'C. Financ.'!I218 -> 11913.416 | ... R218: =+'Bcos. Públ.'!R218+'Bcos. Priv.'!R217+'Coop.'!R218+'C. Financ.'!R218 -> 0 | T218: =+'Bcos. Públ.'!T218+'Bcos. Priv.'!T217+'Coop.'!T218+'C. Financ.'!T218 -> 182609.19 | U218: =+'Bcos. Públ.'!U218+'Bcos. Priv.'!U217+'Coop.'!U218+'C. Financ.'!U218 -> 5115.7742 | V218: =+'Bcos. Públ.'!V218+'Bcos. Priv.'!V217+'Coop.'!V218+'C. Financ.'!V218 -> 187724.96 | W218: =+'Bcos. Públ.'!W218+'Bcos. Priv.'!W217+'Coop.'!W218+'C. Financ.'!W218 -> 15247.759 | X218: =+'Bcos. Públ.'!X218+'Bcos. Priv.'!X217+'Coop.'!X218+'C. Financ.'!X218 -> 0.0055922998 | Y218: =+'Bcos. Públ.'!Y218+'Bcos. Priv.'!Y217+'Coop.'!Y218+'C. Financ.'!Y218 -> 15247.765 | Z218: =+'Bcos. Públ.'!Z218+'Bcos. Priv.'!Z217+'Coop.'!Z218+'C. Financ.'!Z218 -> 197856.95 | AA218: =+'Bcos. Públ.'!AA218+'Bcos. Priv.'!AA217+'Coop.'!AA218+'C. Financ.'!AA218 -> 5115.7798 | ... AM218: =+'Bcos. Públ.'!AM218+'Bcos. Priv.'!AM217+'Coop.'!AM218+'C. Financ.'!AM218 -> 0
A219: =+'Bcos. Públ.'!A219 -> 42430 | B219: =+'Bcos. Públ.'!B219+'Bcos. Priv.'!B218+'Coop.'!B219+'C. Financ.'!B219 -> 436195.37 | C219: =+'Bcos. Públ.'!C219+'Bcos. Priv.'!C218+'Coop.'!C219+'C. Financ.'!C219 -> 12395.963 | D219: =+'Bcos. Públ.'!D219+'Bcos. Priv.'!D218+'Coop.'!D219+'C. Financ.'!D219 -> 448591.34 | E219: =+'Bcos. Públ.'!E219+'Bcos. Priv.'!E218+'Coop.'!E219+'C. Financ.'!E219 -> 21447.936 | F219: =+'Bcos. Públ.'!F219+'Bcos. Priv.'!F218+'Coop.'!F219+'C. Financ.'!F219 -> 0.01146121 | G219: =+'Bcos. Públ.'!G219+'Bcos. Priv.'!G218+'Coop.'!G219+'C. Financ.'!G219 -> 21447.947 | H219: =+'Bcos. Públ.'!H219+'Bcos. Priv.'!H218+'Coop.'!H219+'C. Financ.'!H219 -> 457643.31 | I219: =+'Bcos. Públ.'!I219+'Bcos. Priv.'!I218+'Coop.'!I219+'C. Financ.'!I219 -> 12395.975 | ... R219: =+'Bcos. Públ.'!R219+'Bcos. Priv.'!R218+'Coop.'!R219+'C. Financ.'!R219 -> 11.196337 | T219: =+'Bcos. Públ.'!T219+'Bcos. Priv.'!T218+'Coop.'!T219+'C. Financ.'!T219 -> 186594.44 | U219: =+'Bcos. Públ.'!U219+'Bcos. Priv.'!U218+'Coop.'!U219+'C. Financ.'!U219 -> 5321.6834 | V219: =+'Bcos. Públ.'!V219+'Bcos. Priv.'!V218+'Coop.'!V219+'C. Financ.'!V219 -> 191916.12 | W219: =+'Bcos. Públ.'!W219+'Bcos. Priv.'!W218+'Coop.'!W219+'C. Financ.'!W219 -> 14498.009 | X219: =+'Bcos. Públ.'!X219+'Bcos. Priv.'!X218+'Coop.'!X219+'C. Financ.'!X219 -> 0.0059105605 | Y219: =+'Bcos. Públ.'!Y219+'Bcos. Priv.'!Y218+'Coop.'!Y219+'C. Financ.'!Y219 -> 14498.015 | Z219: =+'Bcos. Públ.'!Z219+'Bcos. Priv.'!Z218+'Coop.'!Z219+'C. Financ.'!Z219 -> 201092.45 | AA219: =+'Bcos. Públ.'!AA219+'Bcos. Priv.'!AA218+'Coop.'!AA219+'C. Financ.'!AA219 -> 5321.6893 | ... AM219: =+'Bcos. Públ.'!AM219+'Bcos. Priv.'!AM218+'Coop.'!AM219+'C. Financ.'!AM219 -> 3.7430822
... A240: =+'Bcos. Públ.'!A240 -> 43070 | B240: =+'Bcos. Públ.'!B240+'Bcos. Priv.'!B239+'Coop.'!B240+'C. Financ.'!B240 -> 421125.67 | C240: =+'Bcos. Públ.'!C240+'Bcos. Priv.'!C239+'Coop.'!C240+'C. Financ.'!C240 -> 15932.329 | D240: =+'Bcos. Públ.'!D240+'Bcos. Priv.'!D239+'Coop.'!D240+'C. Financ.'!D240 -> 437058 | E240: =+'Bcos. Públ.'!E240+'Bcos. Priv.'!E239+'Coop.'!E240+'C. Financ.'!E240 -> 21013.357 | F240: =+'Bcos. Públ.'!F240+'Bcos. Priv.'!F239+'Coop.'!F240+'C. Financ.'!F240 -> 0.0056091209 | G240: =+'Bcos. Públ.'!G240+'Bcos. Priv.'!G239+'Coop.'!G240+'C. Financ.'!G240 -> 21013.363 | H240: =+'Bcos. Públ.'!H240+'Bcos. Priv.'!H239+'Coop.'!H240+'C. Financ.'!H240 -> 442139.03 | I240: =+'Bcos. Públ.'!I240+'Bcos. Priv.'!I239+'Coop.'!I240+'C. Financ.'!I240 -> 15932.335 | ... R240: =+'Bcos. Públ.'!R240+'Bcos. Priv.'!R239+'Coop.'!R240+'C. Financ.'!R240 -> -0.72988427 | T240: =+'Bcos. Públ.'!T240+'Bcos. Priv.'!T239+'Coop.'!T240+'C. Financ.'!T240 -> 206250.94 | U240: =+'Bcos. Públ.'!U240+'Bcos. Priv.'!U239+'Coop.'!U240+'C. Financ.'!U240 -> 6663.8078 | V240: =+'Bcos. Públ.'!V240+'Bcos. Priv.'!V239+'Coop.'!V240+'C. Financ.'!V240 -> 212914.74 | W240: =+'Bcos. Públ.'!W240+'Bcos. Priv.'!W239+'Coop.'!W240+'C. Financ.'!W240 -> 16130.563 | X240: =+'Bcos. Públ.'!X240+'Bcos. Priv.'!X239+'Coop.'!X240+'C. Financ.'!X240 -> 0.0015815799 | Y240: =+'Bcos. Públ.'!Y240+'Bcos. Priv.'!Y239+'Coop.'!Y240+'C. Financ.'!Y240 -> 16130.564 | Z240: =+'Bcos. Públ.'!Z240+'Bcos. Priv.'!Z239+'Coop.'!Z240+'C. Financ.'!Z240 -> 222381.5 | AA240: =+'Bcos. Públ.'!AA240+'Bcos. Priv.'!AA239+'Coop.'!AA240+'C. Financ.'!AA240 -> 6663.8094 | ... AM240: =+'Bcos. Públ.'!AM240+'Bcos. Priv.'!AM239+'Coop.'!AM240+'C. Financ.'!AM240 -> 29.569164
A241: 43101 | B241: =+'Bcos. Públ.'!B241+'Bcos. Priv.'!B240+'Coop.'!B241+'C. Financ.'!B241 -> 412777.27 | C241: =+'Bcos. Públ.'!C241+'Bcos. Priv.'!C240+'Coop.'!C241+'C. Financ.'!C241 -> 16396.841 | D241: =+'Bcos. Públ.'!D241+'Bcos. Priv.'!D240+'Coop.'!D241+'C. Financ.'!D241 -> 429174.11 | E241: =+'Bcos. Públ.'!E241+'Bcos. Priv.'!E240+'Coop.'!E241+'C. Financ.'!E241 -> 20007.633 | F241: =+'Bcos. Públ.'!F241+'Bcos. Priv.'!F240+'Coop.'!F241+'C. Financ.'!F241 -> 0.0039725103 | G241: =+'Bcos. Públ.'!G241+'Bcos. Priv.'!G240+'Coop.'!G241+'C. Financ.'!G241 -> 20007.637 | H241: =+'Bcos. Públ.'!H241+'Bcos. Priv.'!H240+'Coop.'!H241+'C. Financ.'!H241 -> 432784.9 | I241: =+'Bcos. Públ.'!I241+'Bcos. Priv.'!I240+'Coop.'!I241+'C. Financ.'!I241 -> 16396.845 | ... R241: =+'Bcos. Públ.'!R241+'Bcos. Priv.'!R240+'Coop.'!R241+'C. Financ.'!R241 -> 3.6706495 | T241: =+'Bcos. Públ.'!T241+'Bcos. Priv.'!T240+'Coop.'!T241+'C. Financ.'!T241 -> 204517.3 | U241: =+'Bcos. Públ.'!U241+'Bcos. Priv.'!U240+'Coop.'!U241+'C. Financ.'!U241 -> 6702.4783 | V241: =+'Bcos. Públ.'!V241+'Bcos. Priv.'!V240+'Coop.'!V241+'C. Financ.'!V241 -> 211219.78 | W241: =+'Bcos. Públ.'!W241+'Bcos. Priv.'!W240+'Coop.'!W241+'C. Financ.'!W241 -> 15643.486 | X241: =+'Bcos. Públ.'!X241+'Bcos. Priv.'!X240+'Coop.'!X241+'C. Financ.'!X241 -> 0 | Y241: =+'Bcos. Públ.'!Y241+'Bcos. Priv.'!Y240+'Coop.'!Y241+'C. Financ.'!Y241 -> 15643.486 | Z241: =+'Bcos. Públ.'!Z241+'Bcos. Priv.'!Z240+'Coop.'!Z241+'C. Financ.'!Z241 -> 220160.79 | AA241: =+'Bcos. Públ.'!AA241+'Bcos. Priv.'!AA240+'Coop.'!AA241+'C. Financ.'!AA241 -> 6702.4783 | ... AM241: =+'Bcos. Públ.'!AM241+'Bcos. Priv.'!AM240+'Coop.'!AM241+'C. Financ.'!AM241 -> 4.2126876
A242: =+'Bcos. Públ.'!A242 -> 43132 | B242: =+'Bcos. Públ.'!B242+'Bcos. Priv.'!B241+'Coop.'!B242+'C. Financ.'!B242 -> 412087.28 | C242: =+'Bcos. Públ.'!C242+'Bcos. Priv.'!C241+'Coop.'!C242+'C. Financ.'!C242 -> 16861.383 | D242: =+'Bcos. Públ.'!D242+'Bcos. Priv.'!D241+'Coop.'!D242+'C. Financ.'!D242 -> 428948.66 | E242: =+'Bcos. Públ.'!E242+'Bcos. Priv.'!E241+'Coop.'!E242+'C. Financ.'!E242 -> 25000.089 | F242: =+'Bcos. Públ.'!F242+'Bcos. Priv.'!F241+'Coop.'!F242+'C. Financ.'!F242 -> 0.0039645291 | G242: =+'Bcos. Públ.'!G242+'Bcos. Priv.'!G241+'Coop.'!G242+'C. Financ.'!G242 -> 25000.093 | H242: =+'Bcos. Públ.'!H242+'Bcos. Priv.'!H241+'Coop.'!H242+'C. Financ.'!H242 -> 437087.36 | I242: =+'Bcos. Públ.'!I242+'Bcos. Priv.'!I241+'Coop.'!I242+'C. Financ.'!I242 -> 16861.387 | ... R242: =+'Bcos. Públ.'!R242+'Bcos. Priv.'!R241+'Coop.'!R242+'C. Financ.'!R242 -> 10.193759 | T242: =+'Bcos. Públ.'!T242+'Bcos. Priv.'!T241+'Coop.'!T242+'C. Financ.'!T242 -> 206590.16 | U242: =+'Bcos. Públ.'!U242+'Bcos. Priv.'!U241+'Coop.'!U242+'C. Financ.'!U242 -> 6905.9956 | V242: =+'Bcos. Públ.'!V242+'Bcos. Priv.'!V241+'Coop.'!V242+'C. Financ.'!V242 -> 213496.16 | W242: =+'Bcos. Públ.'!W242+'Bcos. Priv.'!W241+'Coop.'!W242+'C. Financ.'!W242 -> 20591.11 | X242: =+'Bcos. Públ.'!X242+'Bcos. Priv.'!X241+'Coop.'!X242+'C. Financ.'!X242 -> 0 | Y242: =+'Bcos. Públ.'!Y242+'Bcos. Priv.'!Y241+'Coop.'!Y242+'C. Financ.'!Y242 -> 20591.11 | Z242: =+'Bcos. Públ.'!Z242+'Bcos. Priv.'!Z241+'Coop.'!Z242+'C. Financ.'!Z242 -> 227181.27 | AA242: =+'Bcos. Públ.'!AA242+'Bcos. Priv.'!AA241+'Coop.'!AA242+'C. Financ.'!AA242 -> 6905.9956 | ... AM242: =+'Bcos. Públ.'!AM242+'Bcos. Priv.'!AM241+'Coop.'!AM242+'C. Financ.'!AM242 -> 5.2835335
A243: =+'Bcos. Públ.'!A243 -> 43160 | B243: =+'Bcos. Públ.'!B243+'Bcos. Priv.'!B242+'Coop.'!B243+'C. Financ.'!B243 -> 417027.99 | C243: =+'Bcos. Públ.'!C243+'Bcos. Priv.'!C242+'Coop.'!C243+'C. Financ.'!C243 -> 17616.174 | D243: =+'Bcos. Públ.'!D243+'Bcos. Priv.'!D242+'Coop.'!D243+'C. Financ.'!D243 -> 434644.17 | E243: =+'Bcos. Públ.'!E243+'Bcos. Priv.'!E242+'Coop.'!E243+'C. Financ.'!E243 -> 21755.705 | F243: =+'Bcos. Públ.'!F243+'Bcos. Priv.'!F242+'Coop.'!F243+'C. Financ.'!F243 -> 0.0039701299 | G243: =+'Bcos. Públ.'!G243+'Bcos. Priv.'!G242+'Coop.'!G243+'C. Financ.'!G243 -> 21755.709 | H243: =+'Bcos. Públ.'!H243+'Bcos. Priv.'!H242+'Coop.'!H243+'C. Financ.'!H243 -> 438783.7 | I243: =+'Bcos. Públ.'!I243+'Bcos. Priv.'!I242+'Coop.'!I243+'C. Financ.'!I243 -> 17616.178 | ... R243: =+'Bcos. Públ.'!R243+'Bcos. Priv.'!R242+'Coop.'!R243+'C. Financ.'!R243 -> -1.007993 | T243: =+'Bcos. Públ.'!T243+'Bcos. Priv.'!T242+'Coop.'!T243+'C. Financ.'!T243 -> 209020.78 | U243: =+'Bcos. Públ.'!U243+'Bcos. Priv.'!U242+'Coop.'!U243+'C. Financ.'!U243 -> 6972.2582 | V243: =+'Bcos. Públ.'!V243+'Bcos. Priv.'!V242+'Coop.'!V243+'C. Financ.'!V243 -> 215993.03 | W243: =+'Bcos. Públ.'!W243+'Bcos. Priv.'!W242+'Coop.'!W243+'C. Financ.'!W243 -> 17319.147 | X243: =+'Bcos. Públ.'!X243+'Bcos. Priv.'!X242+'Coop.'!X243+'C. Financ.'!X243 -> 0 | Y243: =+'Bcos. Públ.'!Y243+'Bcos. Priv.'!Y242+'Coop.'!Y243+'C. Financ.'!Y243 -> 17319.147 | Z243: =+'Bcos. Públ.'!Z243+'Bcos. Priv.'!Z242+'Coop.'!Z243+'C. Financ.'!Z243 -> 226339.92 | AA243: =+'Bcos. Públ.'!AA243+'Bcos. Priv.'!AA242+'Coop.'!AA243+'C. Financ.'!AA243 -> 6972.2582 | ... AM243: =+'Bcos. Públ.'!AM243+'Bcos. Priv.'!AM242+'Coop.'!AM243+'C. Financ.'!AM243 -> 4.9066888
A244: =+'Bcos. Públ.'!A244 -> 43191 | B244: =+'Bcos. Públ.'!B244+'Bcos. Priv.'!B243+'Coop.'!B244+'C. Financ.'!B244 -> 418910.79 | C244: =+'Bcos. Públ.'!C244+'Bcos. Priv.'!C243+'Coop.'!C244+'C. Financ.'!C244 -> 17509.432 | D244: =+'Bcos. Públ.'!D244+'Bcos. Priv.'!D243+'Coop.'!D244+'C. Financ.'!D244 -> 436420.22 | E244: =+'Bcos. Públ.'!E244+'Bcos. Priv.'!E243+'Coop.'!E244+'C. Financ.'!E244 -> 22231.622 | F244: =+'Bcos. Públ.'!F244+'Bcos. Priv.'!F243+'Coop.'!F244+'C. Financ.'!F244 -> 0.0040040091 | G244: =+'Bcos. Públ.'!G244+'Bcos. Priv.'!G243+'Coop.'!G244+'C. Financ.'!G244 -> 22231.626 | H244: =+'Bcos. Públ.'!H244+'Bcos. Priv.'!H243+'Coop.'!H244+'C. Financ.'!H244 -> 441142.41 | I244: =+'Bcos. Públ.'!I244+'Bcos. Priv.'!I243+'Coop.'!I244+'C. Financ.'!I244 -> 17509.436 | ... R244: =+'Bcos. Públ.'!R244+'Bcos. Priv.'!R243+'Coop.'!R244+'C. Financ.'!R244 -> 27.642986 | T244: =+'Bcos. Públ.'!T244+'Bcos. Priv.'!T243+'Coop.'!T244+'C. Financ.'!T244 -> 208677.9 | U244: =+'Bcos. Públ.'!U244+'Bcos. Priv.'!U243+'Coop.'!U244+'C. Financ.'!U244 -> 6883.9959 | V244: =+'Bcos. Públ.'!V244+'Bcos. Priv.'!V243+'Coop.'!V244+'C. Financ.'!V244 -> 215561.9 | W244: =+'Bcos. Públ.'!W244+'Bcos. Priv.'!W243+'Coop.'!W244+'C. Financ.'!W244 -> 18689.372 | X244: =+'Bcos. Públ.'!X244+'Bcos. Priv.'!X243+'Coop.'!X244+'C. Financ.'!X244 -> 0 | Y244: =+'Bcos. Públ.'!Y244+'Bcos. Priv.'!Y243+'Coop.'!Y244+'C. Financ.'!Y244 -> 18689.372 | Z244: =+'Bcos. Públ.'!Z244+'Bcos. Priv.'!Z243+'Coop.'!Z244+'C. Financ.'!Z244 -> 227367.28 | AA244: =+'Bcos. Públ.'!AA244+'Bcos. Priv.'!AA243+'Coop.'!AA244+'C. Financ.'!AA244 -> 6883.9959 | ... AM244: =+'Bcos. Públ.'!AM244+'Bcos. Priv.'!AM243+'Coop.'!AM244+'C. Financ.'!AM244 -> 12.627203
A245: =+'Bcos. Públ.'!A245 -> 43221 | B245: =+'Bcos. Públ.'!B245+'Bcos. Priv.'!B244+'Coop.'!B245+'C. Financ.'!B245 -> 439216.87 | C245: =+'Bcos. Públ.'!C245+'Bcos. Priv.'!C244+'Coop.'!C245+'C. Financ.'!C245 -> 17657.034 | D245: =+'Bcos. Públ.'!D245+'Bcos. Priv.'!D244+'Coop.'!D245+'C. Financ.'!D245 -> 456873.91 | E245: =+'Bcos. Públ.'!E245+'Bcos. Priv.'!E244+'Coop.'!E245+'C. Financ.'!E245 -> 20989.191 | F245: =+'Bcos. Públ.'!F245+'Bcos. Priv.'!F244+'Coop.'!F245+'C. Financ.'!F245 -> 157.99073 | G245: =+'Bcos. Públ.'!G245+'Bcos. Priv.'!G244+'Coop.'!G245+'C. Financ.'!G245 -> 21147.181 | H245: =+'Bcos. Públ.'!H245+'Bcos. Priv.'!H244+'Coop.'!H245+'C. Financ.'!H245 -> 460206.07 | I245: =+'Bcos. Públ.'!I245+'Bcos. Priv.'!I244+'Coop.'!I245+'C. Financ.'!I245 -> 17815.025 | ... R245: =+'Bcos. Públ.'!R245+'Bcos. Priv.'!R244+'Coop.'!R245+'C. Financ.'!R245 -> -42.70249 | T245: =+'Bcos. Públ.'!T245+'Bcos. Priv.'!T244+'Coop.'!T245+'C. Financ.'!T245 -> 209589.37 | U245: =+'Bcos. Públ.'!U245+'Bcos. Priv.'!U244+'Coop.'!U245+'C. Financ.'!U245 -> 6675.75 | V245: =+'Bcos. Públ.'!V245+'Bcos. Priv.'!V244+'Coop.'!V245+'C. Financ.'!V245 -> 216265.12 | W245: =+'Bcos. Públ.'!W245+'Bcos. Priv.'!W244+'Coop.'!W245+'C. Financ.'!W245 -> 17317.57 | X245: =+'Bcos. Públ.'!X245+'Bcos. Priv.'!X244+'Coop.'!X245+'C. Financ.'!X245 -> 0 | Y245: =+'Bcos. Públ.'!Y245+'Bcos. Priv.'!Y244+'Coop.'!Y245+'C. Financ.'!Y245 -> 17317.57 | Z245: =+'Bcos. Públ.'!Z245+'Bcos. Priv.'!Z244+'Coop.'!Z245+'C. Financ.'!Z245 -> 226906.94 | AA245: =+'Bcos. Públ.'!AA245+'Bcos. Priv.'!AA244+'Coop.'!AA245+'C. Financ.'!AA245 -> 6675.75 | ... AM245: =+'Bcos. Públ.'!AM245+'Bcos. Priv.'!AM244+'Coop.'!AM245+'C. Financ.'!AM245 -> 26.855351
A246: =+'Bcos. Públ.'!A246 -> 43252 | B246: =+'Bcos. Públ.'!B246+'Bcos. Priv.'!B245+'Coop.'!B246+'C. Financ.'!B246 -> 443939.46 | C246: =+'Bcos. Públ.'!C246+'Bcos. Priv.'!C245+'Coop.'!C246+'C. Financ.'!C246 -> 17652.86 | D246: =+'Bcos. Públ.'!D246+'Bcos. Priv.'!D245+'Coop.'!D246+'C. Financ.'!D246 -> 461592.32 | E246: =+'Bcos. Públ.'!E246+'Bcos. Priv.'!E245+'Coop.'!E246+'C. Financ.'!E246 -> 21193.365 | F246: =+'Bcos. Públ.'!F246+'Bcos. Priv.'!F245+'Coop.'!F246+'C. Financ.'!F246 -> 0 | G246: =+'Bcos. Públ.'!G246+'Bcos. Priv.'!G245+'Coop.'!G246+'C. Financ.'!G246 -> 21193.365 | H246: =+'Bcos. Públ.'!H246+'Bcos. Priv.'!H245+'Coop.'!H246+'C. Financ.'!H246 -> 465132.83 | I246: =+'Bcos. Públ.'!I246+'Bcos. Priv.'!I245+'Coop.'!I246+'C. Financ.'!I246 -> 17652.86 | ... R246: =+'Bcos. Públ.'!R246+'Bcos. Priv.'!R245+'Coop.'!R246+'C. Financ.'!R246 -> -2.7997512 | T246: =+'Bcos. Públ.'!T246+'Bcos. Priv.'!T245+'Coop.'!T246+'C. Financ.'!T246 -> 211444.54 | U246: =+'Bcos. Públ.'!U246+'Bcos. Priv.'!U245+'Coop.'!U246+'C. Financ.'!U246 -> 6601.9095 | V246: =+'Bcos. Públ.'!V246+'Bcos. Priv.'!V245+'Coop.'!V246+'C. Financ.'!V246 -> 218046.45 | W246: =+'Bcos. Públ.'!W246+'Bcos. Priv.'!W245+'Coop.'!W246+'C. Financ.'!W246 -> 17366.203 | X246: =+'Bcos. Públ.'!X246+'Bcos. Priv.'!X245+'Coop.'!X246+'C. Financ.'!X246 -> 0 | Y246: =+'Bcos. Públ.'!Y246+'Bcos. Priv.'!Y245+'Coop.'!Y246+'C. Financ.'!Y246 -> 17366.203 | Z246: =+'Bcos. Públ.'!Z246+'Bcos. Priv.'!Z245+'Coop.'!Z246+'C. Financ.'!Z246 -> 228810.74 | AA246: =+'Bcos. Públ.'!AA246+'Bcos. Priv.'!AA245+'Coop.'!AA246+'C. Financ.'!AA246 -> 6601.9095 | ... AM246: =+'Bcos. Públ.'!AM246+'Bcos. Priv.'!AM245+'Coop.'!AM246+'C. Financ.'!AM246 -> 6.9311228
A247: =+'Bcos. Públ.'!A247 -> 43282 | B247: =+'Bcos. Públ.'!B247+'Bcos. Priv.'!B246+'Coop.'!B247+'C. Financ.'!B247 -> 437814.08 | C247: =+'Bcos. Públ.'!C247+'Bcos. Priv.'!C246+'Coop.'!C247+'C. Financ.'!C247 -> 17642.918 | D247: =+'Bcos. Públ.'!D247+'Bcos. Priv.'!D246+'Coop.'!D247+'C. Financ.'!D247 -> 455457 | E247: =+'Bcos. Públ.'!E247+'Bcos. Priv.'!E246+'Coop.'!E247+'C. Financ.'!E247 -> 20009.551 | F247: =+'Bcos. Públ.'!F247+'Bcos. Priv.'!F246+'Coop.'!F247+'C. Financ.'!F247 -> 0.12962547 | G247: =+'Bcos. Públ.'!G247+'Bcos. Priv.'!G246+'Coop.'!G247+'C. Financ.'!G247 -> 20009.681 | H247: =+'Bcos. Públ.'!H247+'Bcos. Priv.'!H246+'Coop.'!H247+'C. Financ.'!H247 -> 457823.63 | I247: =+'Bcos. Públ.'!I247+'Bcos. Priv.'!I246+'Coop.'!I247+'C. Financ.'!I247 -> 17643.048 | ... R247: =+'Bcos. Públ.'!R247+'Bcos. Priv.'!R246+'Coop.'!R247+'C. Financ.'!R247 -> 2.732019 | T247: =+'Bcos. Públ.'!T247+'Bcos. Priv.'!T246+'Coop.'!T247+'C. Financ.'!T247 -> 212994.68 | U247: =+'Bcos. Públ.'!U247+'Bcos. Priv.'!U246+'Coop.'!U247+'C. Financ.'!U247 -> 6738.8286 | V247: =+'Bcos. Públ.'!V247+'Bcos. Priv.'!V246+'Coop.'!V247+'C. Financ.'!V247 -> 219733.51 | W247: =+'Bcos. Públ.'!W247+'Bcos. Priv.'!W246+'Coop.'!W247+'C. Financ.'!W247 -> 16312.086 | X247: =+'Bcos. Públ.'!X247+'Bcos. Priv.'!X246+'Coop.'!X247+'C. Financ.'!X247 -> 0.07778191 | Y247: =+'Bcos. Públ.'!Y247+'Bcos. Priv.'!Y246+'Coop.'!Y247+'C. Financ.'!Y247 -> 16312.164 | Z247: =+'Bcos. Públ.'!Z247+'Bcos. Priv.'!Z246+'Coop.'!Z247+'C. Financ.'!Z247 -> 229306.77 | AA247: =+'Bcos. Públ.'!AA247+'Bcos. Priv.'!AA246+'Coop.'!AA247+'C. Financ.'!AA247 -> 6738.9064 | ... AM247: =+'Bcos. Públ.'!AM247+'Bcos. Priv.'!AM246+'Coop.'!AM247+'C. Financ.'!AM247 -> 8.4564739
